Workbook

Sheet Gráficos
K2: La industria manufacturera uruguaya muestra una reducción sostenida del apalancamiento: el pasivo no corriente cayó del 46,5% al 18,3% del capital total entre 2006 y 2024, mientras que los intereses disminuyeron del 11,2% al 7,9% de la ganancia. Esto se explica por el mayor crecimiento del stock de capital, cuyo índice alcanzó 457,2 en 2024, frente a 161,0 del endeudamiento.
K15: La rentabilidad sobre el patrimonio neto presenta valores muy elevados —con un máximo de 1.458% en 2014 y 609% en 2024—, lo que implica un patrimonio neto reducido. Al descontar la inversión en capital fijo, la tasa de ganancia registra un promedio de apenas 3%, con un mínimo de −31% en 2015, un máximo de 21% en 2018 y una recuperación hasta 7% en 2024. En conjunto, el menor endeudamiento convive con una rentabilidad efectiva baja y fuertemente cíclica.

Sheet Fuentes
B2: Endeudamiento con el sistema financiero nacional. No externo. Son saldos de créditos con el sistema financiero bancario local + endeudamiento a través de obligaciones nacionales a nivel local también.
B4: Link
B5: https://www.ciu.com.uy/wp-content/uploads/2026/04/Endeudamiento-industrial-N30_2-_Sem_2025.pdf

Sheet TG PN
B1: corrientes | C1: corrientes | D1: constantes | E1: corrientes | F1: corrientes | G1: Mill USD | H1: Mill USD | J1: 1870-1912: Willebald et al (15); +13: PHES -Silvana Maubrigades | L1: Mill USD | M1: Mill USD | N1: Mill USD | O1: Mill USD | P1: Mill USD | Q1: Mill USD | S1: Mill USD | AE1: Millones de pesos | AF1: Millones de pesos | AG1: Millones de pesos
B2: capital_total_adelantado | C2: stock_capital | D2: capital_total_adelantado | E2: Ganancia desp de impuestos | F2: fbcf | G2: Endeudamiento Industrial | H2: Intereses pagos por la industria | I2: intereses pagos por eaae, ajuste c/ microdatos (90%) | J2: Tipo de cambio libre | K2: TC Paridad c/prod no agraria | L2: capital_total_adelantado | M2: stock_capital | N2: Ganancia | O2: FBCF | P2: Ganancia desp de intereses pagados | Q2: Ganancia desp de impuestos e intereses pagados, menos la FBCF | R2: % de los intereses respecto de la ganancia | S2: Patrimonio neto (Aprox.) | T2: stock de capital menos endeudamiento | U2: Pasivo no corriente / KTA | V2: Endeudamiento (2006 = 100) | W2: stock_capital (2006 = 100) | X2: Tasa de ganancia manuf | Y2: Tasa de ganancia capital propio | Z2: Tasa de ganancia capital propio desp de FBCF | AA2: Tasa de ganancia PN (sobre capital fijo menos endeudamiento) | AB2: Promedio | AE2: Intereses x TC | AF2: Intereses por TCP | AG2: Abaratamiento por tc. Diferencia intereses | AH2: Abaratamiento sobre ganancia desp de impuestos
A3: 2001 | B3: 3.9864242e+10 | C3: 28622363000 | D3: 2.3946122e+11 | E3: 5.0869177e+09 | F3: 3539644000 | J3: 13.408852 | K3: 19.078999 | L3: =B3/J3/1000000 -> 2972.9795 | M3: =C3/J3/1000000 -> 2134.5871 | N3: =E3/J3/1000000 -> 379.37011 | O3: =F3/J3/1000000 -> 263.97815 | W3: =M3/M$8*100 -> 89.859415 | X3: ='rama-C'!AD2 -> 0.12760603
A4: 2002 | B4: 5.0476907e+10 | D4: 2.0999612e+11 | E4: 1.348539e+10 | J4: 21.587268 | K4: 22.652647 | L4: =B4/J4/1000000 -> 2338.2721 | N4: =E4/J4/1000000 -> 624.69183 | X4: ='rama-C'!AD3 -> 0.26715959
A5: 2003 | B5: 6.5662459e+10 | C5: 48103564060 | D5: 1.9856951e+11 | E5: 1.2655823e+10 | F5: 6899547696 | J5: 28.369939 | K5: 26.367312 | L5: =B5/J5/1000000 -> 2314.5083 | M5: =C5/J5/1000000 -> 1695.5822 | N5: =E5/J5/1000000 -> 446.09976 | O5: =F5/J5/1000000 -> 243.19924 | W5: =M5/M$8*100 -> 71.378686 | X5: ='rama-C'!AD4 -> 0.19274062
A6: 2004 | B6: 7.2889933e+10 | C6: 50525577181 | D6: 2.497745e+11 | E6: 1.9229598e+10 | F6: 6396127195 | J6: 28.703792 | K6: 29.122846 | L6: =B6/J6/1000000 -> 2539.3834 | M6: =C6/J6/1000000 -> 1760.2405 | N6: =E6/J6/1000000 -> 669.93233 | O6: =F6/J6/1000000 -> 222.83213 | W6: =M6/M$8*100 -> 74.100597 | X6: ='rama-C'!AD5 -> 0.26381693
A7: 2005 | B7: 7.5872497e+10 | C7: 52418214093 | D7: 3.0450928e+11 | E7: 1.735402e+10 | F7: 6464007473 | J7: 24.478579 | K7: 28.325217 | L7: =B7/J7/1000000 -> 3099.5466 | M7: =C7/J7/1000000 -> 2141.3912 | N7: =E7/J7/1000000 -> 708.94719 | O7: =F7/J7/1000000 -> 264.06792 | W7: =M7/M$8*100 -> 90.145845 | X7: ='rama-C'!AD6 -> 0.22872609
A8: 2006 | B8: 8.056767e+10 | C8: 5.7185677e+10 | D8: 2.7392317e+11 | E8: 1.7995065e+10 | F8: 6.5161369e+09 | G8: 1556.8148 | H8: 83.75346 | I8: =H8*0.9 -> 75.378114 | J8: 24.073374 | K8: 29.954262 | L8: =B8/J8/1000000 -> 3346.7544 | M8: =C8/J8/1000000 -> 2375.4741 | N8: =E8/J8/1000000 -> 747.50904 | O8: =F8/J8/1000000 -> 270.67817 | P8: =N8-H8 -> 663.75558 | Q8: =P8-O8 -> 393.0774 | R8: =H8/N8 -> 0.11204341 | S8: =L8-G8 -> 1789.9396 | T8: =M8-G8 -> 818.6593 | U8: =G8/L8 -> 0.46517152 | V8: =G8/G$8*100 -> 100 | W8: =M8/M$8*100 -> 100 | X8: ='rama-C'!AD7 -> 0.22335342 | AE8: =$I8*J8 -> 1814.6055 | AF8: =$I8*K8 -> 2257.8958 | AG8: =AF8-AE8 -> 443.29025 | AH8: =AG8/(E8/1000000) -> 0.02463399
A9: 2007 | B9: 1.1812089e+11 | C9: 8.8288213e+10 | D9: 3.2429228e+11 | E9: 2.41105e+10 | F9: 1.735929e+10 | G9: 1737.3081 | H9: 89.035722 | I9: =H9*0.9 -> 80.13215 | J9: 23.471036 | K9: 30.861639 | L9: =B9/J9/1000000 -> 5032.6237 | M9: =C9/J9/1000000 -> 3761.5814 | N9: =E9/J9/1000000 -> 1027.2448 | O9: =F9/J9/1000000 -> 739.60474 | P9: =N9-H9 -> 938.20909 | Q9: =P9-O9 -> 198.60435 | R9: =H9/N9 -> 0.086674297 | S9: =L9-G9 -> 3295.3157 | T9: =M9-G9 -> 2024.2734 | U9: =G9/L9 -> 0.34520921 | V9: =G9/G$8*100 -> 111.59375 | W9: =M9/M$8*100 -> 158.35076 | X9: ='rama-C'!AD8 -> 0.20411715 | Y9: =S9/P9 -> 3.5123467 | Z9: =Q9/S9 -> 0.060268688 | AA9: =P9/T9 -> 0.46347945 | AB9: =AVERAGE(Z$9:Z$26) -> 0.034243627 | AE9: =$I9*J9 -> 1880.7846 | AF9: =$I9*K9 -> 2473.0095 | AG9: =AF9-AE9 -> 592.22491 | AH9: =AG9/(E9/1000000) -> 0.024562946
A10: 2008 | B10: 1.4476563e+11 | C10: 1.0797121e+11 | D10: 3.496873e+11 | E10: 2.6698283e+10 | F10: 1.7442926e+10 | G10: 1785.2371 | H10: 92.377722 | I10: =H10*0.9 -> 83.139949 | J10: 20.949345 | K10: 30.471964 | L10: =B10/J10/1000000 -> 6910.2702 | M10: =C10/J10/1000000 -> 5153.9183 | N10: =E10/J10/1000000 -> 1274.4209 | O10: =F10/J10/1000000 -> 832.62394 | P10: =N10-H10 -> 1182.0432 | Q10: =P10-O10 -> 349.41924 | R10: =H10/N10 -> 0.072486038 | S10: =L10-G10 -> 5125.0331 | T10: =M10-G10 -> 3368.6811 | U10: =G10/L10 -> 0.25834549 | V10: =G10/G$8*100 -> 114.67241 | W10: =M10/M$8*100 -> 216.96377 | X10: ='rama-C'!AD9 -> 0.18442418 | Y10: =S10/P10 -> 4.335741 | Z10: =Q10/S10 -> 0.068178923 | AA10: =P10/T10 -> 0.35089197 | AB10: =AVERAGE(Z$9:Z$26) -> 0.034243627 | AE10: =$I10*J10 -> 1741.7275 | AF10: =$I10*K10 -> 2533.4375 | AG10: =AF10-AE10 -> 791.71006 | AH10: =AG10/(E10/1000000) -> 0.029653969
A11: 2009 | B11: 1.2763899e+11 | C11: 9.3192118e+10 | D11: 3.3559366e+11 | E11: 1.801868e+10 | F11: 7.9610854e+09 | G11: 1666.6448 | H11: 93.63592 | I11: =H11*0.9 -> 84.272328 | J11: 22.567971 | K11: 32.276463 | L11: =B11/J11/1000000 -> 5655.7583 | M11: =C11/J11/1000000 -> 4129.3973 | N11: =E11/J11/1000000 -> 798.41826 | O11: =F11/J11/1000000 -> 352.76035 | P11: =N11-H11 -> 704.78234 | Q11: =P11-O11 -> 352.02199 | R11: =H11/N11 -> 0.11727678 | S11: =L11-G11 -> 3989.1135 | T11: =M11-G11 -> 2462.7524 | U11: =G11/L11 -> 0.29468106 | V11: =G11/G$8*100 -> 107.05479 | W11: =M11/M$8*100 -> 173.83466 | X11: ='rama-C'!AD10 -> 0.14116909 | Y11: =S11/P11 -> 5.6600644 | Z11: =Q11/S11 -> 0.088245669 | AA11: =P11/T11 -> 0.28617669 | AB11: =AVERAGE(Z$9:Z$26) -> 0.034243627 | AE11: =$I11*J11 -> 1901.8555 | AF11: =$I11*K11 -> 2720.0127 | AG11: =AF11-AE11 -> 818.15722 | AH11: =AG11/(E11/1000000) -> 0.045406057
A12: 2010 | B12: 1.3817191e+11 | C12: 9.973781e+10 | D12: 4.0692949e+11 | E12: 2.4477634e+10 | F12: 1.0581329e+10 | G12: 1792.8303 | H12: 74.52889 | I12: =H12*0.9 -> 67.076001 | J12: 20.059238 | K12: 32.828748 | L12: =B12/J12/1000000 -> 6888.1932 | M12: =C12/J12/1000000 -> 4972.1635 | N12: =E12/J12/1000000 -> 1220.2674 | O12: =F12/J12/1000000 -> 527.50402 | P12: =N12-H12 -> 1145.7385 | Q12: =P12-O12 -> 618.2345 | R12: =H12/N12 -> 0.061075867 | S12: =L12-G12 -> 5095.3629 | T12: =M12-G12 -> 3179.3332 | U12: =G12/L12 -> 0.26027584 | V12: =G12/G$8*100 -> 115.16015 | W12: =M12/M$8*100 -> 209.31247 | X12: ='rama-C'!AD11 -> 0.17715348 | Y12: =S12/P12 -> 4.4472302 | Z12: =Q12/S12 -> 0.12133277 | AA12: =P12/T12 -> 0.3603707 | AB12: =AVERAGE(Z$9:Z$26) -> 0.034243627 | AE12: =$I12*J12 -> 1345.4935 | AF12: =$I12*K12 -> 2202.0211 | AG12: =AF12-AE12 -> 856.52767 | AH12: =AG12/(E12/1000000) -> 0.034992257
A13: 2011 | B13: 1.6459051e+11 | D13: 3.9455398e+11 | E13: 1.5603516e+10 | G13: 2051.7036 | H13: 85.105635 | I13: =H13*0.9 -> 76.595071 | J13: 19.314209 | K13: 34.651025 | L13: =B13/J13/1000000 -> 8521.7321 | N13: =E13/J13/1000000 -> 807.87756 | P13: =N13-H13 -> 722.77192 | Q13: =P13-O13 -> 722.77192 | R13: =H13/N13 -> 0.10534472 | S13: =L13-G13 -> 6470.0284 | U13: =G13/L13 -> 0.24076134 | V13: =G13/G$8*100 -> 131.78855 | X13: ='rama-C'!AD12 -> 0.094802037 | Y13: =S13/P13 -> 8.9516876 | Z13: =Q13/S13 -> 0.11171078 | AB13: =AVERAGE(Z$9:Z$26) -> 0.034243627 | AE13: =$I13*J13 -> 1479.3732 | AF13: =$I13*K13 -> 2654.0977 | AG13: =AF13-AE13 -> 1174.7245 | AH13: =AG13/(E13/1000000) -> 0.075285886
A14: 2012 | B14: 1.6778489e+11 | C14: 1.1807022e+11 | D14: 3.9509125e+11 | E14: 1.2653049e+10 | F14: 1.7144628e+10 | G14: 2252.2035 | H14: 102.14219 | I14: =H14*0.9 -> 91.92797 | J14: 20.310164 | K14: 35.243068 | L14: =B14/J14/1000000 -> 8261.1292 | M14: =C14/J14/1000000 -> 5813.3565 | N14: =E14/J14/1000000 -> 622.99097 | O14: =F14/J14/1000000 -> 844.14033 | P14: =N14-H14 -> 520.84878 | Q14: =P14-O14 -> -323.29155 | R14: =H14/N14 -> 0.16395453 | S14: =L14-G14 -> 6008.9257 | T14: =M14-G14 -> 3561.153 | U14: =G14/L14 -> 0.27262659 | V14: =G14/G$8*100 -> 144.6674 | W14: =M14/M$8*100 -> 244.72405 | X14: ='rama-C'!AD13 -> 0.075412326 | Y14: =S14/P14 -> 11.536795 | Z14: =Q14/S14 -> -0.053801888 | AA14: =P14/T14 -> 0.14625846 | AB14: =AVERAGE(Z$9:Z$26) -> 0.034243627 | AE14: =$I14*J14 -> 1867.0721 | AF14: =$I14*K14 -> 3239.8237 | AG14: =AF14-AE14 -> 1372.7515 | AH14: =AG14/(E14/1000000) -> 0.10849176
A15: 2013 | B15: 1.8349807e+11 | C15: 1.3030327e+11 | D15: 4.1091262e+11 | E15: 1.2278747e+10 | F15: 2.8790673e+10 | G15: 2329.9271 | H15: 115.22407 | I15: =H15*0.9 -> 103.70167 | J15: 20.481618 | K15: 35.991435 | L15: =B15/J15/1000000 -> 8959.159 | M15: =C15/J15/1000000 -> 6361.9616 | N15: =E15/J15/1000000 -> 599.50085 | O15: =F15/J15/1000000 -> 1405.6835 | P15: =N15-H15 -> 484.27678 | Q15: =P15-O15 -> -921.40674 | R15: =H15/N15 -> 0.19220002 | S15: =L15-G15 -> 6629.2319 | T15: =M15-G15 -> 4032.0346 | U15: =G15/L15 -> 0.26006092 | V15: =G15/G$8*100 -> 149.65987 | W15: =M15/M$8*100 -> 267.81861 | X15: ='rama-C'!AD14 -> 0.066914858 | Y15: =S15/P15 -> 13.688932 | Z15: =Q15/S15 -> -0.13899148 | AA15: =P15/T15 -> 0.1201073 | AB15: =AVERAGE(Z$9:Z$26) -> 0.034243627 | AE15: =$I15*J15 -> 2123.9779 | AF15: =$I15*K15 -> 3732.3718 | AG15: =AF15-AE15 -> 1608.3939 | AH15: =AG15/(E15/1000000) -> 0.13099006
A16: 2014 | B16: 2.5937714e+11 | C16: 1.9842942e+11 | D16: 4.5420126e+11 | E16: 1.7067828e+10 | F16: 7.8176629e+10 | G16: 2179.4861 | H16: 118.36466 | I16: =H16*0.9 -> 106.5282 | J16: 23.246061 | K16: 38.372773 | L16: =B16/J16/1000000 -> 11157.896 | M16: =C16/J16/1000000 -> 8536.0448 | N16: =E16/J16/1000000 -> 734.22452 | O16: =F16/J16/1000000 -> 3363.0054 | P16: =N16-H16 -> 615.85985 | Q16: =P16-O16 -> -2747.1456 | R16: =H16/N16 -> 0.16121045 | S16: =L16-G16 -> 8978.4103 | T16: =M16-G16 -> 6356.5586 | U16: =G16/L16 -> 0.19533127 | V16: =G16/G$8*100 -> 139.99649 | W16: =M16/M$8*100 -> 359.34068 | X16: ='rama-C'!AD15 -> 0.06580313 | Y16: =S16/P16 -> 14.578658 | Z16: =Q16/S16 -> -0.30597238 | AA16: =P16/T16 -> 0.096885735 | AB16: =AVERAGE(Z$9:Z$26) -> 0.034243627 | AE16: =$I16*J16 -> 2476.361 | AF16: =$I16*K16 -> 4087.7823 | AG16: =AF16-AE16 -> 1611.4214 | AH16: =AG16/(E16/1000000) -> 0.094412796
A17: 2015 | B17: 2.7046004e+11 | C17: 2.0781379e+11 | D17: 4.546719e+11 | E17: 2.4840445e+10 | F17: 2.6806672e+10 | G17: 2377.4684 | H17: 110.4421 | I17: =H17*0.9 -> 99.397894 | J17: 27.327226 | K17: 41.149156 | L17: =B17/J17/1000000 -> 9897.091 | M17: =C17/J17/1000000 -> 7604.6429 | N17: =E17/J17/1000000 -> 908.99988 | O17: =F17/J17/1000000 -> 980.9511 | P17: =N17-H17 -> 798.55777 | Q17: =P17-O17 -> -182.39333 | R17: =H17/N17 -> 0.12149848 | S17: =L17-G17 -> 7519.6227 | T17: =M17-G17 -> 5227.1745 | U17: =G17/L17 -> 0.2402189 | V17: =G17/G$8*100 -> 152.71363 | W17: =M17/M$8*100 -> 320.13158 | X17: ='rama-C'!AD16 -> 0.091845157 | Y17: =S17/P17 -> 9.4165042 | Z17: =Q17/S17 -> -0.024255649 | AA17: =P17/T17 -> 0.15277044 | AB17: =AVERAGE(Z$9:Z$26) -> 0.034243627 | AE17: =$I17*J17 -> 2716.2687 | AF17: =$I17*K17 -> 4090.1395 | AG17: =AF17-AE17 -> 1373.8707 | AH17: =AG17/(E17/1000000) -> 0.055307815
A18: 2016 | B18: 2.8330238e+11 | C18: 2.188245e+11 | D18: 4.5819744e+11 | E18: 1.9680939e+10 | F18: 1.7409372e+10 | G18: 2353.9156 | H18: 116.70317 | I18: =H18*0.9 -> 105.03285 | J18: 30.1626 | K18: 44.043941 | L18: =B18/J18/1000000 -> 9392.5052 | M18: =C18/J18/1000000 -> 7254.8288 | N18: =E18/J18/1000000 -> 652.49479 | O18: =F18/J18/1000000 -> 577.18405 | P18: =N18-H18 -> 535.79162 | Q18: =P18-O18 -> -41.392433 | R18: =H18/N18 -> 0.17885686 | S18: =L18-G18 -> 7038.5896 | T18: =M18-G18 -> 4900.9132 | U18: =G18/L18 -> 0.25061637 | V18: =G18/G$8*100 -> 151.20075 | W18: =M18/M$8*100 -> 305.40551 | X18: ='rama-C'!AD17 -> 0.069469729 | Y18: =S18/P18 -> 13.136804 | Z18: =Q18/S18 -> -0.0058807851 | AA18: =P18/T18 -> 0.10932486 | AB18: =AVERAGE(Z$9:Z$26) -> 0.034243627 | AE18: =$I18*J18 -> 3168.0639 | AF18: =$I18*K18 -> 4626.0608 | AG18: =AF18-AE18 -> 1457.9969 | AH18: =AG18/(E18/1000000) -> 0.07408167
A19: 2017 | B19: 2.7320664e+11 | C19: 2.097731e+11 | D19: 4.5688633e+11 | E19: 4.7598175e+10 | F19: 1.703624e+10 | G19: 2159.4332 | H19: 109.68601 | I19: =H19*0.9 -> 98.717406 | J19: 28.65 | K19: 44.520022 | L19: =B19/J19/1000000 -> 9536.0083 | M19: =C19/J19/1000000 -> 7321.9231 | N19: =E19/J19/1000000 -> 1661.3674 | O19: =F19/J19/1000000 -> 594.63316 | P19: =N19-H19 -> 1551.6813 | Q19: =P19-O19 -> 957.04819 | R19: =H19/N19 -> 0.066021525 | S19: =L19-G19 -> 7376.5751 | T19: =M19-G19 -> 5162.4899 | U19: =G19/L19 -> 0.22645044 | V19: =G19/G$8*100 -> 138.70842 | W19: =M19/M$8*100 -> 308.22997 | X19: ='rama-C'!AD18 -> 0.17422042 | Y19: =S19/P19 -> 4.7539239 | Z19: =Q19/S19 -> 0.12974154 | AA19: =P19/T19 -> 0.3005684 | AB19: =AVERAGE(Z$9:Z$26) -> 0.034243627 | AE19: =$I19*J19 -> 2828.2537 | AF19: =$I19*K19 -> 4394.9011 | AG19: =AF19-AE19 -> 1566.6474 | AH19: =AG19/(E19/1000000) -> 0.032914023
A20: 2018 | B20: 303469927276 | C20: 2.3094465e+11 | D20: 4.6660865e+11 | E20: 7.3700681e+10 | F20: 2.1403884e+10 | G20: 2408.2765 | H20: 118.23441 | I20: =H20*0.9 -> 106.41097 | J20: 30.77 | K20: 47.58936 | L20: =B20/J20/1000000 -> 9862.5261 | M20: =C20/J20/1000000 -> 7505.5136 | N20: =E20/J20/1000000 -> 2395.2123 | O20: =F20/J20/1000000 -> 695.60883 | P20: =N20-H20 -> 2276.9778 | Q20: =P20-O20 -> 1581.369 | R20: =H20/N20 -> 0.049362813 | S20: =L20-G20 -> 7454.2496 | T20: =M20-G20 -> 5097.2371 | U20: =G20/L20 -> 0.24418455 | V20: =G20/G$8*100 -> 154.69255 | W20: =M20/M$8*100 -> 315.95855 | X20: ='rama-C'!AD19 -> 0.24285992 | Y20: =S20/P20 -> 3.2737471 | Z20: =Q20/S20 -> 0.21214329 | AA20: =P20/T20 -> 0.44670824 | AB20: =AVERAGE(Z$9:Z$26) -> 0.034243627 | AE20: =$I20*J20 -> 3274.2656 | AF20: =$I20*K20 -> 5064.0301 | AG20: =AF20-AE20 -> 1789.7645 | AH20: =AG20/(E20/1000000) -> 0.024284232
A21: 2019 | B21: 3.3849056e+11 | C21: 259048160897 | D21: 4.7965711e+11 | E21: 5.7159846e+10 | F21: 30759048024 | G21: 2177.6592 | H21: 123.64706 | I21: =H21*0.9 -> 111.28236 | J21: 35.3 | K21: 50.391059 | L21: =B21/J21/1000000 -> 9588.9677 | M21: =C21/J21/1000000 -> 7338.4748 | N21: =E21/J21/1000000 -> 1619.2591 | O21: =F21/J21/1000000 -> 871.36113 | P21: =N21-H21 -> 1495.612 | Q21: =P21-O21 -> 624.25089 | R21: =H21/N21 -> 0.076360271 | S21: =L21-G21 -> 7411.3085 | T21: =M21-G21 -> 5160.8157 | U21: =G21/L21 -> 0.22710048 | V21: =G21/G$8*100 -> 139.87914 | W21: =M21/M$8*100 -> 308.92674 | X21: ='rama-C'!AD20 -> 0.16886688 | Y21: =S21/P21 -> 4.9553684 | Z21: =Q21/S21 -> 0.084229511 | AA21: =P21/T21 -> 0.28980148 | AB21: =AVERAGE(Z$9:Z$26) -> 0.034243627 | AE21: =$I21*J21 -> 3928.2672 | AF21: =$I21*K21 -> 5607.6358 | AG21: =AF21-AE21 -> 1679.3686 | AH21: =AG21/(E21/1000000) -> 0.029380216
A22: 2020 | B22: 3.762764e+11 | C22: 2.963226e+11 | D22: 4.4815014e+11 | E22: 5.5200295e+10 | F22: 4.094156e+10 | G22: 2172.8074 | H22: 106.45435 | I22: =H22*0.9 -> 95.808915 | J22: 42 | K22: 57.605681 | L22: =B22/J22/1000000 -> 8958.9618 | M22: =C22/J22/1000000 -> 7055.3 | N22: =E22/J22/1000000 -> 1314.2927 | O22: =F22/J22/1000000 -> 974.79905 | P22: =N22-H22 -> 1207.8384 | Q22: =P22-O22 -> 233.03935 | R22: =H22/N22 -> 0.080997442 | S22: =L22-G22 -> 6786.1544 | T22: =M22-G22 -> 4882.4926 | U22: =G22/L22 -> 0.24252893 | V22: =G22/G$8*100 -> 139.56749 | W22: =M22/M$8*100 -> 297.00597 | X22: ='rama-C'!AD21 -> 0.14670146 | Y22: =S22/P22 -> 5.6184291 | Z22: =Q22/S22 -> 0.034340414 | AA22: =P22/T22 -> 0.24738151 | AB22: =AVERAGE(Z$9:Z$26) -> 0.034243627 | AE22: =$I22*J22 -> 4023.9745 | AF22: =$I22*K22 -> 5519.1378 | AG22: =AF22-AE22 -> 1495.1634 | AH22: =AG22/(E22/1000000) -> 0.027086148
A23: 2021 | B23: 4.6969871e+11 | C23: 3.7719399e+11 | D23: 4.5759101e+11 | E23: 1.0933949e+11 | F23: 8.3942984e+10 | G23: 2232.9524 | H23: 86.973256 | I23: =H23*0.9 -> 78.27593 | J23: 43.56 | K23: 58.976208 | L23: =B23/J23/1000000 -> 10782.799 | M23: =C23/J23/1000000 -> 8659.1824 | N23: =E23/J23/1000000 -> 2510.0893 | O23: =F23/J23/1000000 -> 1927.0657 | P23: =N23-H23 -> 2423.116 | Q23: =P23-O23 -> 496.05026 | R23: =H23/N23 -> 0.034649468 | S23: =L23-G23 -> 8549.8463 | T23: =M23-G23 -> 6426.23 | U23: =G23/L23 -> 0.20708468 | V23: =G23/G$8*100 -> 143.43083 | W23: =M23/M$8*100 -> 364.52438 | X23: ='rama-C'!AD22 -> 0.23278643 | Y23: =S23/P23 -> 3.5284511 | Z23: =Q23/S23 -> 0.058018617 | AA23: =P23/T23 -> 0.37706649 | AB23: =AVERAGE(Z$9:Z$26) -> 0.034243627 | AE23: =$I23*J23 -> 3409.6995 | AF23: =$I23*K23 -> 4616.4176 | AG23: =AF23-AE23 -> 1206.718 | AH23: =AG23/(E23/1000000) -> 0.011036434
A24: 2022 | B24: 5.074139e+11 | C24: 3.9260348e+11 | D24: 4.5646201e+11 | E24: 1.1087673e+11 | F24: 6.9687014e+10 | G24: 2453.2461 | H24: 113.81053 | I24: =H24*0.9 -> 102.42947 | J24: 41.3 | K24: 58.134197 | L24: =B24/J24/1000000 -> 12286.051 | M24: =C24/J24/1000000 -> 9506.1375 | N24: =E24/J24/1000000 -> 2684.6666 | O24: =F24/J24/1000000 -> 1687.3369 | P24: =N24-H24 -> 2570.8561 | Q24: =P24-O24 -> 883.51917 | R24: =H24/N24 -> 0.042392797 | S24: =L24-G24 -> 9832.8047 | T24: =M24-G24 -> 7052.8914 | U24: =G24/L24 -> 0.19967735 | V24: =G24/G$8*100 -> 157.58111 | W24: =M24/M$8*100 -> 400.17853 | X24: ='rama-C'!AD23 -> 0.21851339 | Y24: =S24/P24 -> 3.82472 | Z24: =Q24/S24 -> 0.089854237 | AA24: =P24/T24 -> 0.36451094 | AB24: =AVERAGE(Z$9:Z$26) -> 0.034243627 | AE24: =$I24*J24 -> 4230.3373 | AF24: =$I24*K24 -> 5954.6552 | AG24: =AF24-AE24 -> 1724.3179 | AH24: =AG24/(E24/1000000) -> 0.015551667
A25: 2023 | B25: 5.1091334e+11 | C25: 4.0246279e+11 | D25: 4.658893e+11 | E25: 7.1043588e+10 | F25: 5.6457789e+10 | G25: 2596.6553 | H25: 160.27276 | I25: =H25*0.9 -> 144.24548 | J25: 38.695 | K25: 60.006461 | L25: =B25/J25/1000000 -> 13203.601 | M25: =C25/J25/1000000 -> 10400.899 | N25: =E25/J25/1000000 -> 1835.9888 | O25: =F25/J25/1000000 -> 1459.0461 | P25: =N25-H25 -> 1675.7161 | Q25: =P25-O25 -> 216.67 | R25: =H25/N25 -> 0.087295061 | S25: =L25-G25 -> 10606.946 | T25: =M25-G25 -> 7804.2438 | U25: =G25/L25 -> 0.19666266 | V25: =G25/G$8*100 -> 166.79282 | W25: =M25/M$8*100 -> 437.84519 | X25: ='rama-C'!AD24 -> 0.13905213 | Y25: =S25/P25 -> 6.3297988 | Z25: =Q25/S25 -> 0.020427181 | AA25: =P25/T25 -> 0.21471857 | AB25: =AVERAGE(Z$9:Z$26) -> 0.034243627 | AE25: =$I25*J25 -> 5581.5789 | AF25: =$I25*K25 -> 8655.6609 | AG25: =AF25-AE25 -> 3074.082 | AH25: =AG25/(E25/1000000) -> 0.043270364
A26: 2024 | B26: 5.5096522e+11 | C26: 4.3696596e+11 | D26: 4.8398942e+11 | E26: 8.0163643e+10 | F26: 4.3801058e+10 | G26: 2506.69 | H26: 156.51051 | I26: =H26*0.9 -> 140.85946 | J26: 40.235 | K26: 61.848214 | L26: =B26/J26/1000000 -> 13693.68 | M26: =C26/J26/1000000 -> 10860.344 | N26: =E26/J26/1000000 -> 1992.3858 | O26: =F26/J26/1000000 -> 1088.6307 | P26: =N26-H26 -> 1835.8753 | Q26: =P26-O26 -> 747.24456 | R26: =H26/N26 -> 0.078554317 | S26: =L26-G26 -> 11186.99 | T26: =M26-G26 -> 8353.6544 | U26: =G26/L26 -> 0.18305452 | V26: =G26/G$8*100 -> 161.01402 | W26: =M26/M$8*100 -> 457.18639 | X26: ='rama-C'!AD25 -> 0.14549674 | Y26: =S26/P26 -> 6.0935458 | Z26: =Q26/S26 -> 0.066795854 | AA26: =P26/T26 -> 0.21976912 | AB26: =AVERAGE(Z$9:Z$26) -> 0.034243627 | AE26: =$I26*J26 -> 5667.4802 | AF26: =$I26*K26 -> 8711.9058 | AG26: =AF26-AE26 -> 3044.4256 | AH26: =AG26/(E26/1000000) -> 0.037977635
A27: 2025 | G27: 2704.0963 | H27: 144.46263 | I27: =H27*0.9 -> 130.01636 | J27: 41.08 | K27: 62.865715

Sheet metodología
A1: seccion_contenido | B1: nombre | C1: tipo | D1: aplica_en | E1: definicion | F1: fuente_formula
A2: estructura_libro | B2: metodología | C2: hoja | D2: Libro completo | E2: Referencia de lectura del archivo: describe las hojas y el diccionario de variables. | F2: Construida por el postproceso R.
A3: estructura_libro | B3: eaae | C3: hoja | D3: Panel base | E3: Panel completo con unidad año por sección CIIU homologada. | F3: CSV fechado del panel EAAE.
A4: estructura_libro | B4: rama-C | C4: hoja | D4: Panel base | E4: Subconjunto del panel para la rama industrial, sección C. | F4: Filtro seccion == C.
A5: estructura_libro | B5: check-calidad-C | C5: hoja | D5: Validación | E5: Indicadores anuales de control para la rama industrial. | F5: Derivada del panel rama-C.
A6: estructura_libro | B6: economia_total | C6: hoja | D6: Panel base | E6: Agregado anual de todas las secciones del panel. | F6: Suma de variables aditivas por año.
A7: estructura_libro | B7: check-calidad-total | C7: hoja | D7: Validación | E7: Indicadores anuales de control para la economía total. | F7: Derivada de economia_total.
A8: estructura_libro | B8: resultados-total-corrientes | C8: hoja | D8: Resultados | E8: Insumos y variables calculadas para economía total en valores corrientes. | F8: Cálculos propios desde economia_total.
A9: estructura_libro | B9: resultados-industrial-corrientes | C9: hoja | D9: Resultados | E9: Insumos y variables calculadas para la rama industrial en valores corrientes. | F9: Cálculos propios desde rama-C.
A10: estructura_libro | B10: resultados-total-constante | C10: hoja | D10: Resultados | E10: Insumos y variables calculadas para economía total en precios de 2005. | F10: Deflacta corrientes con índices Oyanthabal.
A11: estructura_libro | B11: resultados-industrial-constante | C11: hoja | D11: Resultados | E11: Insumos y variables calculadas para industria en precios de 2005. | F11: Deflacta corrientes con índices Oyanthabal.
A12: estructura_libro | B12: resultados-total-var-pct | C12: hoja | D12: Resultados | E12: Variación porcentual interanual de los resultados constantes de economía total. | F12: (x[t] / x[t-1] - 1) * 100.
... A64: diccionario_variables | B64: *_ind_2005 | C64: transformación | D64: Hojas resultados-*-ind-2005 | E64: Sufijo de variables expresadas como índice con base 2005=1. | F64: Encadenamiento desde variaciones interanuales.

Sheet eaae
A1: anno | B1: seccion | C1: epoca | D1: ciiu_version | E1: vbp_pp | F1: vbp_pb | G1: vab_pp | H1: vab_pb | I1: vab_pb_estimado | J1: consumo_intermedio_estimado | K1: capital_circulante_constante_adelantado | L1: remuneraciones | M1: capital_variable_adelantado | N1: puestos_trabajo | O1: n_empresas | P1: fbcf | Q1: fbkf_maq_eq | R1: adquisiciones_importadas | S1: adquisiciones_origen_importado | T1: importaciones_maquinaria | U1: consumo_capital_fijo | V1: impuestos_netos | W1: stock_capital | X1: stock_capital_imputado | Y1: capital_total_adelantado | Z1: excedente_bruto | AA1: part_salarial | AB1: productividad
A2: 2001 | B2: C | C2: 1 | D2: Rev.3 | E2: 89240215000 | G2: 32030854000 | I2: 2.6506273e+10 | J2: 6.2733942e+10 | K2: 9.5051428e+09 | L2: 11462459000 | M2: 1.7367362e+09 | N2: 113817 | O2: 12367 | P2: 3539644000 | Q2: 2057120000 | R2: 1075519000 | U2: 3127411000 | V2: 6829485000 | W2: 28622363000 | X2: 28622363000 | Y2: 3.9864242e+10 | Z2: 20568395000 | AA2: 0.3578568 | AB2: 281424.16
A3: 2001 | B3: D_E | C3: 1 | D3: Rev.3 | E3: 13263801000 | G3: 10613610000 | I3: 10613610000 | J3: 2650191000 | L3: 3599292000 | N3: 14928 | O3: 7 | P3: 1873944000 | Q3: 148103000 | R3: 1707000 | U3: 1928502000 | V3: 111535000 | W3: 50479997000 | X3: 50479997000 | Z3: 7014318000 | AA3: 0.33912043 | AB3: 710986.74
A4: 2001 | B4: G | C4: 1 | D4: Rev.3 | E4: 43491119000 | G4: 24957624000 | I4: 2.2794518e+10 | J4: 2.0696601e+10 | L4: 10823278000 | N4: 168971 | O4: 41141 | P4: 2205103000 | Q4: 530457000 | R4: 107333000 | U4: 1670535000 | V4: 1114492000 | W4: 14490199000 | X4: 14490199000 | Z4: 14134346000 | AA4: 0.4336662 | AB4: 147703.59
A5: 2001 | B5: H_J | C5: 1 | D5: Rev.3 | E5: 33566050000 | G5: 13456590000 | I5: 1.3454267e+10 | J5: 2.0111783e+10 | L5: 6544975000 | N5: 62695 | O5: 15659 | P5: 3337731000 | Q5: 1415592000 | R5: 1786934000 | U5: 1509319000 | V5: -154331000 | W5: 13202423000 | X5: 13202423000 | Z5: 6911615000 | AA5: 0.48637694 | AB5: 214635.78
A6: 2001 | B6: I | C6: 1 | D6: Rev.3 | E6: 6105764000 | G6: 2287136000 | I6: 2.2861472e+09 | J6: 3.8196168e+09 | L6: 1474027000 | N6: 26097 | O6: 6303 | P6: 2415023000 | Q6: 192837000 | R6: 24742000 | U6: 446253000 | V6: 39553000 | W6: 5880745000 | X6: 5880745000 | Z6: 813109000 | AA6: 0.64448594 | AB6: 87639.805
A7: 2001 | B7: L_M_N | C7: 1 | D7: Rev.3 | E7: 14837125000 | G7: 8359713000 | I7: 8.3595946e+09 | J7: 6.4775304e+09 | L7: 3864244000 | N7: 60371 | O7: 13253 | P7: 908730000 | Q7: 520775000 | R7: 158545000 | U7: 360497000 | V7: 82393000 | W7: 3280605000 | X7: 3280605000 | Z7: 4495469000 | AA7: 0.46224601 | AB7: 138472.33
A8: 2001 | B8: P | C8: 1 | D8: Rev.3 | E8: 3554736000 | G8: 2803083000 | I8: 2803083000 | J8: 751653000 | L8: 2188777000 | N8: 30186 | O8: 1863 | P8: 241141000 | Q8: 31142000 | R8: 5934000 | U8: 73414000 | V8: 1245000 | W8: 1895620000 | X8: 1895620000 | Z8: 614306000 | AA8: 0.7808463 | AB8: 92860.366
A9: 2001 | B9: Q | C9: 1 | D9: Rev.3 | E9: 20736564000 | G9: 11456887000 | I9: 11456887000 | J9: 9279677000 | L9: 8963981000 | N9: 61559 | O9: 2773 | P9: 1063210000 | Q9: 340762000 | R9: 15697000 | U9: 358413000 | V9: 204284000 | W9: 5999539000 | X9: 5999539000 | Z9: 2492906000 | AA9: 0.78240983 | AB9: 186112.3
A10: 2002 | B10: C | C10: 2 | D10: Rev.3 | E10: 104934883446 | G10: 39381506784 | I10: 3.2589108e+10 | J10: 7.2345776e+10 | K10: 1.0961481e+10 | L10: 9421078355 | M10: 1.4274361e+09 | N10: 76575 | O10: 2884 | U10: 3758469943 | V10: 5924169665 | X10: 3.808799e+10 | Y10: 5.0476907e+10 | Z10: 29960428429 | AA10: 0.23922595 | AB10: 514286.74
A11: 2002 | B11: D_E | C11: 2 | D11: Rev.3 | E11: 15787447980 | G11: 12439436732 | I11: 12439436732 | J11: 3348011248 | L11: 3806404173 | N11: 12215 | O11: 6 | U11: 3105564554 | V11: 89560282 | X11: 6.2423317e+10 | Z11: 8633032559 | AA11: 0.3059949 | AB11: 1018373.9
A12: 2002 | B12: G | C12: 2 | D12: Rev.3 | E12: 31693348520 | G12: 18177965195 | I12: 1.660246e+10 | J12: 1.5090888e+10 | L12: 7709632973 | N12: 76468 | O12: 4704 | U12: 1426375588 | V12: 632733549 | X12: 1.0354076e+10 | Z12: 10468332222 | AA12: 0.42411969 | AB12: 237719.9
A13: 2002 | B13: H_J | C13: 2 | D13: Rev.3 | E13: 37112316985 | G13: 15304944081 | I13: 1.5302302e+10 | J13: 2.1810015e+10 | L13: 6795894609 | N13: 37362 | O13: 1139 | U13: 1592530017 | V13: 69155721 | X13: 7.3606656e+09 | Z13: 8509049472 | AA13: 0.44403263 | AB13: 409639.31
A14: 2002 | B14: I | C14: 2 | D14: Rev.3 | E14: 6055117793 | G14: 2738851808 | I14: 2.7376677e+09 | J14: 3.3174501e+09 | L14: 1165502269 | N14: 14784 | O14: 837 | U14: 346961879 | V14: 206430881 | X14: 7.4495924e+09 | Z14: 1573349539 | AA14: 0.42554412 | AB14: 185257.83
A15: 2002 | B15: L_M_N | C15: 2 | D15: Rev.3 | E15: 10532305500 | G15: 5766938265 | I15: 5.7668566e+09 | J15: 4.7654489e+09 | L15: 3189588114 | N15: 36920 | O15: 1207 | U15: 319767425 | V15: -38267584 | X15: 2.3128315e+09 | Z15: 2577350151 | AA15: 0.55308172 | AB15: 156200.93
A16: 2002 | B16: P | C16: 2 | D16: Rev.3 | E16: 3635163473 | G16: 2764590458 | I16: 2764590458 | J16: 870573015 | L16: 2232779019 | N16: 29269 | O16: 795 | U16: 186228974 | V16: 1845445 | X16: 4.1293645e+09 | Z16: 531811439 | AA16: 0.80763464 | AB16: 94454.558
A17: 2002 | B17: Q | C17: 2 | D17: Rev.3 | E17: 18542655551 | G17: 9779564144 | I17: 9779564144 | J17: 8763091407 | L17: 8301959694 | N17: 56404 | O17: 726 | U17: 427982536 | V17: 308347891 | X17: 6.4899612e+09 | Z17: 1477604450 | AA17: 0.84890897 | AB17: 173384.23
A18: 2003 | B18: C | C18: 2 | D18: Rev.3 | E18: 139349946300 | G18: 41497361974 | I18: 3.4340027e+10 | J18: 1.0500992e+11 | K18: 1.5910594e+10 | L18: 10878789626 | M18: 1.6483015e+09 | N18: 83356 | O18: 2884 | P18: 6899547696 | Q18: 5558448986 | R18: 5256351292 | U18: 4714590576 | V18: 6090823735 | W18: 48103564060 | X18: 48103564060 | Y18: 6.5662459e+10 | Z18: 30618572348 | AA18: 0.26215617 | AB18: 497832.93
A19: 2003 | B19: D_E | C19: 2 | D19: Rev.3 | E19: 17778374536 | G19: 15099711405 | I19: 15099711405 | J19: 2678663131 | L19: 3709025707 | N19: 11033 | O19: 6 | P19: 1881480432 | Q19: 729819150 | R19: 289523 | U19: 2816673366 | V19: 71005452 | W19: 18404738826 | X19: 18404738826 | Z19: 11390685698 | AA19: 0.24563554 | AB19: 1368595.3
A20: 2003 | B20: G | C20: 2 | D20: Rev.3 | E20: 37563631203 | G20: 21571353022 | I20: 1.9701739e+10 | J20: 1.7861892e+10 | L20: 7998489144 | N20: 77964 | O20: 4704 | P20: 1137150229 | Q20: 345789196 | R20: 84676957 | U20: 1828622094 | V20: 718525744 | W20: 13454000561 | X20: 13454000561 | Z20: 13572863878 | AA20: 0.37079219 | AB20: 276683.51
A21: 2003 | B21: H_J | C21: 2 | D21: Rev.3 | E21: 45516690384 | G21: 16906173266 | I21: 1.6903255e+10 | J21: 2.8613436e+10 | L21: 6746978974 | N21: 36295 | O21: 1139 | P21: 2989215591 | Q21: 1954096578 | R21: 336383626 | U21: 4184128201 | V21: 148694272 | W21: 16977971617 | X21: 16977971617 | Z21: 10159194292 | AA21: 0.39908375 | AB21: 465798.96
A22: 2003 | B22: I | C22: 2 | D22: Rev.3 | E22: 7545694909 | G22: 3215599713 | I22: 3.2142095e+09 | J22: 4.3314854e+09 | L22: 1331138827 | N22: 15423 | O22: 837 | P22: 407835768 | Q22: 234293111 | R22: 4134443 | U22: 581911564 | V22: 185578578 | W22: 15394752061 | X22: 15394752061 | Z22: 1884460886 | AA22: 0.41396285 | AB22: 208493.79
A23: 2003 | B23: L_M_N | C23: 2 | D23: Rev.3 | E23: 10840882783 | G23: 5781255267 | I23: 5.7811734e+09 | J23: 5.0597094e+09 | L23: 3250196651 | N23: 36576 | O23: 1207 | P23: 893749498 | Q23: 392670668 | R23: 60040937 | U23: 446760432 | V23: -81377996 | W23: 3036697582 | X23: 3036697582 | Z23: 2531058616 | AA23: 0.56219567 | AB23: 158061.44
A24: 2003 | B24: P | C24: 2 | D24: Rev.3 | E24: 4020897277 | G24: 3041969189 | I24: 3041969189 | J24: 978928088 | L24: 2333305509 | N24: 30136 | O24: 795 | P24: 265611515 | Q24: 182986853 | R24: 6872122 | U24: 202734943 | V24: 1700570 | W24: 4535928555 | X24: 4535928555 | Z24: 708663680 | AA24: 0.76703785 | AB24: 100941.37
A25: 2003 | B25: Q | C25: 2 | D25: Rev.3 | E25: 20144437327 | G25: 10367277432 | I25: 10367277432 | J25: 9777159895 | L25: 8237357729 | N25: 54436 | O25: 726 | P25: 464436226 | Q25: 160670968 | R25: 16922814 | U25: 612598654 | V25: 532348671 | W25: 8950823549 | X25: 8950823549 | Z25: 2129919703 | AA25: 0.79455361 | AB25: 190448.92
A26: 2004 | B26: C | C26: 2 | D26: Rev.3 | E26: 179010449525 | G26: 52621053735 | I26: 4.3545139e+10 | J26: 1.3546531e+11 | K26: 2.0525047e+10 | L26: 12139435357 | M26: 1.8393084e+09 | N26: 88653 | O26: 3252 | P26: 6396127195 | Q26: 3154522472 | R26: 1599697016 | S26: 1743085329 | T26: 3342782345 | U26: 5136920717 | V26: 7039185004 | W26: 50525577181 | X26: 50525577181 | Y26: 7.2889933e+10 | Z26: 40481618378 | AA26: 0.23069541 | AB26: 593562.02
A27: 2004 | B27: D_E | C27: 2 | D27: Rev.3 | E27: 18970896638 | G27: 16452542193 | I27: 16452542193 | J27: 2518354445 | L27: 4318586343 | N27: 11278 | O27: 8 | P27: 1586645703 | Q27: 1391609954 | R27: 577445 | S27: 0 | T27: 577445 | U27: 3527584731 | V27: 193662937 | W27: 69005735625 | X27: 69005735625 | Z27: 12133955850 | AA27: 0.26248748 | AB27: 1458817.4
A28: 2004 | B28: G | C28: 2 | D28: Rev.3 | E28: 44736252618 | G28: 25542912801 | I28: 2.332908e+10 | J28: 2.1407173e+10 | L28: 8750816236 | N28: 80808 | O28: 5540 | P28: 2848082374 | Q28: 693786571 | R28: 168379555 | S28: 743240013 | T28: 911619568 | U28: 2071656593 | V28: 891739416 | W28: 14305115357 | X28: 14305115357 | Z28: 16792096565 | AA28: 0.34259273 | AB28: 316093.86
A29: 2004 | B29: H_J | C29: 2 | D29: Rev.3 | E29: 54138973445 | G29: 18769614747 | I29: 1.8766374e+10 | J29: 3.5372599e+10 | L29: 7257265654 | N29: 38895 | O29: 1403 | P29: 6988113014 | Q29: 4667216558 | R29: 443287668 | S29: 940736307 | T29: 1384023975 | U29: 4707582011 | V29: 180141199 | W29: 23318179581 | X29: 23318179581 | Z29: 11512349093 | AA29: 0.38664969 | AB29: 482571.4
A30: 2004 | B30: I | C30: 2 | D30: Rev.3 | E30: 7527262326 | G30: 3225745138 | I30: 3.2243505e+09 | J30: 4.3029118e+09 | L30: 1362647439 | N30: 14104 | O30: 810 | P30: 564815404 | Q30: 101735015 | R30: 0 | S30: 17194896 | T30: 17194896 | U30: 618478957 | V30: 151819588 | W30: 12857715294 | X30: 12857715294 | Z30: 1863097699 | AA30: 0.42242874 | AB30: 228711.37
A31: 2004 | B31: L_M_N | C31: 2 | D31: Rev.3 | E31: 12469844085 | G31: 6554832803 | I31: 6.5547399e+09 | J31: 5.9151042e+09 | L31: 3515024005 | N31: 33674 | O31: 1340 | P31: 1110214370 | Q31: 616807060 | R31: 128520209 | S31: 183666728 | T31: 312186937 | U31: 454902760 | V31: -111867613 | W31: 3709336385 | X31: 3709336385 | Z31: 3039808798 | AA31: 0.53624922 | AB31: 194655.6
A32: 2004 | B32: P | C32: 2 | D32: Rev.3 | E32: 4122763764 | G32: 3114011412 | I32: 3114011412 | J32: 1008752352 | L32: 2364813124 | N32: 28379 | O32: 850 | P32: 442468386 | Q32: 85104732 | R32: 12004244 | S32: 14446685 | T32: 26450929 | U32: 183943843 | V32: 1516610 | W32: 4097580261 | X32: 4097580261 | Z32: 749198288 | AA32: 0.75941055 | AB32: 109729.43
A33: 2004 | B33: Q | C33: 2 | D33: Rev.3 | E33: 21510528473 | G33: 10967962939 | I33: 10967962939 | J33: 10542565534 | L33: 8298900124 | N33: 52548 | O33: 790 | P33: 1020214687 | Q33: 370879850 | R33: 20163040 | S33: 147177599 | T33: 167340639 | U33: 640676128 | V33: 524173728 | W33: 9519982217 | X33: 9519982217 | Z33: 2669062815 | AA33: 0.75664918 | AB33: 208722.75
A34: 2005 | B34: C | C34: 2 | D34: Rev.3 | E34: 184862461743 | G34: 53991760706 | I34: 4.4679431e+10 | J34: 1.4018303e+11 | K34: 2.1239853e+10 | L34: 14615233399 | M34: 2.2144293e+09 | N34: 102414 | O34: 3445 | P34: 6464007473 | Q34: 2747259075 | R34: 2116008436 | S34: 2111494326 | T34: 4227502762 | U34: 5058292667 | V34: 7651885206 | W34: 52418214093 | X34: 52418214093 | Y34: 7.5872497e+10 | Z34: 39376527307 | AA34: 0.27069377 | AB34: 527191.21
A35: 2005 | B35: D_E | C35: 2 | D35: Rev.3 | E35: 21452171857 | G35: 17681330593 | I35: 17681330593 | J35: 3770841264 | L35: 3774749843 | N35: 10749 | O35: 9 | P35: 6130481812 | Q35: 157381971 | R35: 0 | S35: 10139634 | T35: 10139634 | U35: 3491133822 | V35: 258939881 | W35: 119415827794 | X35: 119415827794 | Z35: 13906580750 | AA35: 0.21348788 | AB35: 1644928
A36: 2005 | B36: G | C36: 2 | D36: Rev.3 | E36: 52055365572 | G36: 30604340361 | I36: 2.7951827e+10 | J36: 2.4103538e+10 | L36: 10891239572 | N36: 88696 | O36: 5425 | P36: 2485425948 | Q36: 476330674 | R36: 146988046 | S36: 501187302 | T36: 648175348 | U36: 1882974266 | V36: 1327172831 | W36: 14149463192 | X36: 14149463192 | Z36: 19713100789 | AA36: 0.35587238 | AB36: 345047.58
A37: 2005 | B37: H_J | C37: 2 | D37: Rev.3 | E37: 58995279052 | G37: 22019098542 | I37: 2.2015297e+10 | J37: 3.6979982e+10 | L37: 8354766526 | N37: 42234 | O37: 1451 | P37: 4434586962 | Q37: 1623564422 | R37: 1255663280 | S37: 822643912 | T37: 2078307192 | U37: 4755443419 | V37: 10796371 | W37: 23087450461 | X37: 23087450461 | Z37: 13664332016 | AA37: 0.37943272 | AB37: 521359.53
A38: 2005 | B38: I | C38: 2 | D38: Rev.3 | E38: 8281031530 | G38: 3767948397 | I38: 3.7663194e+09 | J38: 4.5147122e+09 | L38: 1616158132 | N38: 15568 | O38: 834 | P38: 238518748 | Q38: 157340735 | R38: 63255653 | S38: 52892693 | T38: 116148346 | U38: 681078239 | V38: 145165012 | W38: 11692776848 | X38: 11692776848 | Z38: 2151790265 | AA38: 0.42892258 | AB38: 242031.63
A39: 2005 | B39: L_M_N | C39: 2 | D39: Rev.3 | E39: 15934155356 | G39: 8374925674 | I39: 8.374807e+09 | J39: 7.5593483e+09 | L39: 5069118049 | N39: 41494 | O39: 1455 | P39: 1182629165 | Q39: 675555411 | R39: 168007029 | S39: 294530786 | T39: 462537815 | U39: 597692961 | V39: -97991671 | W39: 4032805057 | X39: 4032805057 | Z39: 3305807625 | AA39: 0.6052732 | AB39: 201834.62
A40: 2005 | B40: P | C40: 2 | D40: Rev.3 | E40: 4730612582 | G40: 3549115924 | I40: 3549115924 | J40: 1181496658 | L40: 2735589275 | N40: 32524 | O40: 873 | P40: 308786468 | Q40: 106489219 | R40: 14147369 | S40: 22900523 | T40: 37047892 | U40: 169154791 | V40: 3417836 | W40: 3699553497 | X40: 3699553497 | Z40: 813526649 | AA40: 0.77078048 | AB40: 109122.98
A41: 2005 | B41: Q | C41: 2 | D41: Rev.3 | E41: 23956912155 | G41: 12200114753 | I41: 12200114753 | J41: 11756797402 | L41: 9682480142 | N41: 57805 | O41: 846 | P41: 1064310535 | Q41: 298642530 | R41: 22668095 | S41: 169249039 | T41: 191917134 | U41: 660363415 | V41: 513505092 | W41: 10580163208 | X41: 10580163208 | Z41: 2517634611 | AA41: 0.79363845 | AB41: 211056.39
A42: 2006 | B42: C | C42: 3 | D42: Rev.3 | E42: 1.850396e+11 | G42: 5.4017528e+10 | I42: 4.4700754e+10 | J42: 1.4033884e+11 | K42: 2.1263461e+10 | L42: 1.3982311e+10 | M42: 2.118532e+09 | N42: 63928.853 | P42: 6.5161369e+09 | Q42: 4.2278276e+09 | R42: 2.1827562e+09 | S42: 1.4258711e+09 | T42: 3.6086273e+09 | U42: 4.2569136e+09 | V42: 8.4664645e+09 | W42: 5.7185677e+10 | X42: 5.7185677e+10 | Y42: 8.056767e+10 | Z42: 4.0035217e+10 | AA42: 0.25884767 | AB42: 844963.2
A43: 2006 | B43: D_E | C43: 3 | D43: Rev.3 | E43: 23627751445 | G43: 13864356824 | I43: 13864356824 | J43: 9763394621 | L43: 5083992799 | N43: 11021 | P43: 699869518 | Q43: -1419069479 | R43: 0 | S43: 0 | T43: 0 | U43: 3628599926 | V43: -111678818 | W43: 104426959200 | X43: 104426959200 | Z43: 8780364025 | AA43: 0.36669518 | AB43: 1257994.4
A44: 2006 | B44: G | C44: 3 | D44: Rev.3 | E44: 3.9597751e+10 | G44: 1.8057673e+10 | I44: 1.6492594e+10 | J44: 2.3105157e+10 | L44: 5.922563e+09 | N44: 30494.293 | P44: 1.4692727e+09 | Q44: 5.7624035e+08 | R44: 1.0798855e+08 | S44: 2.3263944e+08 | T44: 3.4062799e+08 | U44: 1.0539624e+09 | V44: 1.0967943e+09 | W44: 1.071423e+10 | X44: 1.071423e+10 | Z44: 1.213511e+10 | AA44: 0.32798041 | AB44: 592165.66
A45: 2006 | B45: H_J | C45: 3 | D45: Rev.3 | E45: 5.4381479e+10 | G45: 2.6401244e+10 | I45: 2.6396686e+10 | J45: 2.7984793e+10 | L45: 7.7625704e+09 | N45: 24730.437 | P45: 8.7966369e+09 | Q45: 5.846618e+09 | R45: 7.6380722e+08 | S45: 8.6074381e+08 | T45: 1.624551e+09 | U45: 6.6795963e+09 | V45: 3.2360602e+08 | W45: 3.3497341e+10 | X45: 3.3497341e+10 | Z45: 1.8638673e+10 | AA45: 0.29402291 | AB45: 1067560.7
A46: 2006 | B46: I | C46: 3 | D46: Rev.3 | E46: 4164254297 | G46: 2029545343 | I46: 2.0286679e+09 | J46: 2.1355864e+09 | L46: 974332309 | N46: 5944 | P46: 2.4359211e+08 | Q46: 1.2830898e+08 | R46: 76425378 | S46: 25205041 | T46: 1.0163042e+08 | U46: 628178378 | V46: 10663152 | W46: 1.1086285e+10 | X46: 1.1086285e+10 | Z46: 1055213034 | AA46: 0.48007418 | AB46: 341444.37
A47: 2006 | B47: L_M_N | C47: 3 | D47: Rev.3 | E47: 5.7595347e+09 | G47: 3.6054154e+09 | I47: 3.6053644e+09 | J47: 2.1541703e+09 | L47: 2.3848348e+09 | N47: 17724.655 | P47: 4.3441228e+08 | Q47: 3.5133253e+08 | R47: 65766764 | S47: 3.2798376e+08 | T47: 3.9375052e+08 | U47: 2.0765422e+08 | V47: 21562497 | W47: 2.1795857e+09 | X47: 2.1795857e+09 | Z47: 1.2205806e+09 | AA47: 0.66145909 | AB47: 203412.45
A48: 2006 | B48: P | C48: 3 | D48: Rev.3 | E48: 2.0060538e+09 | G48: 1.5016385e+09 | I48: 1.5016385e+09 | J48: 5.0441535e+08 | L48: 1.2810029e+09 | N48: 8781.4219 | P48: 1.0342907e+08 | Q48: 52021153 | R48: 7633798 | S48: 14769928 | T48: 22403726 | U48: 1.0731407e+08 | V48: -7579637.1 | W48: 2.2167561e+09 | X48: 2.2167561e+09 | Z48: 2.2063562e+08 | AA48: 0.85307008 | AB48: 171001.75
A49: 2006 | B49: Q | C49: 3 | D49: Rev.3 | E49: 2.1866393e+10 | G49: 1.1832753e+10 | I49: 1.1832753e+10 | J49: 1.003364e+10 | L49: 9.9706502e+09 | N49: 43328.302 | P49: 8.8737087e+08 | Q49: 2.9966087e+08 | R49: 27594052 | S49: 44400473 | T49: 71994526 | U49: 5.5425846e+08 | V49: 2.463042e+08 | W49: 1.0380365e+10 | X49: 1.0380365e+10 | Z49: 1.8621031e+09 | AA49: 0.84263146 | AB49: 273095.25
A50: 2007 | B50: C | C50: 3 | D50: Rev.3 | E50: 2.35394e+11 | G50: 7.0661648e+10 | I50: 5.8474148e+10 | J50: 1.7691985e+11 | K50: 2.6806038e+10 | L50: 1.9975832e+10 | M50: 3.0266412e+09 | N50: 100576.01 | P50: 1.735929e+10 | Q50: 5.9547781e+09 | R50: 2.0501427e+09 | S50: 2.5603315e+09 | T50: 4.6104742e+09 | U50: 5.9348309e+09 | V50: 8.4529852e+09 | W50: 8.8288213e+10 | X50: 8.8288213e+10 | Y50: 1.1812089e+11 | Z50: 5.0685816e+10 | AA50: 0.28269695 | AB50: 702569.59
A51: 2007 | B51: D_E | C51: 3 | D51: Rev.3 | E51: 29548256354 | G51: 17116101061 | I51: 17116101061 | J51: 12432155293 | L51: 5846200050 | N51: 10867 | P51: 3583664449 | Q51: 625710596 | R51: 0 | S51: 665800 | T51: 665800 | U51: 4330014480 | V51: -72308127 | W51: 99307451996 | X51: 99307451996 | Z51: 11269901011 | AA51: 0.34156144 | AB51: 1575053
A52: 2007 | B52: G | C52: 3 | D52: Rev.3 | E52: 7.3746746e+10 | G52: 3.8265123e+10 | I52: 3.4948641e+10 | J52: 3.8798105e+10 | L52: 1.3444886e+10 | N52: 79220.26 | P52: 4.100431e+09 | Q52: 1.8947747e+09 | R52: 7.1180557e+08 | S52: 7.0803227e+08 | T52: 1.4198378e+09 | U52: 1.8093649e+09 | V52: 1.5315409e+09 | W52: 1.9439331e+10 | X52: 1.9439331e+10 | Z52: 2.4820237e+10 | AA52: 0.35136137 | AB52: 483021.93
A53: 2007 | B53: H_J | C53: 3 | D53: Rev.3 | E53: 7.9851161e+10 | G53: 3.6125294e+10 | I53: 3.6119057e+10 | J53: 4.3732104e+10 | L53: 1.2273618e+10 | N53: 41934.093 | P53: 1.1396301e+10 | Q53: 7.5976979e+09 | R53: 1.0748806e+09 | S53: 1.5317799e+09 | T53: 2.6066605e+09 | U53: 7.6412471e+09 | V53: -3.6201068e+08 | W53: 4.322455e+10 | X53: 4.322455e+10 | Z53: 2.3851676e+10 | AA53: 0.33975137 | AB53: 861477.9
A54: 2007 | B54: I | C54: 3 | D54: Rev.3 | E54: 1.1163145e+10 | G54: 4.9527895e+09 | I54: 4.9506483e+09 | J54: 6.2124965e+09 | L54: 2.1799207e+09 | N54: 15648.667 | P54: 1.9580168e+08 | Q54: 1.5989014e+08 | R54: 59212612 | S54: 16900662 | T54: 76113274 | U54: 8.9239939e+08 | V54: 34311569 | W54: 1.9524074e+10 | X54: 1.9524074e+10 | Z54: 2.7728688e+09 | AA54: 0.44013999 | AB54: 316499.14
A55: 2007 | B55: L_M_N | C55: 3 | D55: Rev.3 | E55: 1.3090542e+10 | G55: 8.2475975e+09 | I55: 8.2474807e+09 | J55: 4.8430618e+09 | L55: 5.0217431e+09 | N55: 37538.496 | P55: 8.48226e+08 | Q55: 6.1328551e+08 | R55: 1.3210547e+08 | S55: 4.1702024e+08 | T55: 5.4912571e+08 | U55: 4.2830109e+08 | V55: 35587755 | W55: 3.9881431e+09 | X55: 3.9881431e+09 | Z55: 3.2258544e+09 | AA55: 0.60887345 | AB55: 219710.39
A56: 2007 | B56: P | C56: 3 | D56: Rev.3 | E56: 5.4435241e+09 | G56: 4.2688746e+09 | I56: 4.2688746e+09 | J56: 1.1746496e+09 | L56: 3.247047e+09 | N56: 31985.537 | P56: 2.7936398e+08 | Q56: 79171169 | R56: 11993855 | S56: 18362086 | T56: 30355941 | U56: 1.9253865e+08 | V56: -4924048.3 | W56: 3.7984793e+09 | X56: 3.7984793e+09 | Z56: 1.0218276e+09 | AA56: 0.76063302 | AB56: 133462.65
A57: 2007 | B57: Q | C57: 3 | D57: Rev.3 | E57: 3.3131744e+10 | G57: 1.7261273e+10 | I57: 1.7261273e+10 | J57: 1.587047e+10 | L57: 1.397635e+10 | N57: 66667.829 | P57: 1.0961827e+09 | Q57: 4.3713444e+08 | R57: 7091222.8 | S57: 1.3107242e+08 | T57: 1.3816364e+08 | U57: 7.222778e+08 | V57: 2.7974192e+08 | W57: 1.4385348e+10 | X57: 1.4385348e+10 | Z57: 3.2849227e+09 | AA57: 0.80969407 | AB57: 258914.58
A58: 2008 | B58: B | C58: 4 | D58: Rev.4 | E58: 776329531 | G58: 3.5476581e+08 | I58: 3.5476581e+08 | J58: 4.2156372e+08 | L58: 145858508 | N58: 868.2 | P58: 186931359 | Q58: 102860706 | R58: 741150 | S58: 9353236.4 | T58: 10094386 | U58: 23033390 | V58: 7369483 | W58: 3.3450459e+08 | X58: 3.3450459e+08 | Z58: 2.089073e+08 | AA58: 0.41114026 | AB58: 408622.22
A59: 2008 | B59: C | C59: 4 | D59: Rev.4 | E59: 2.8499569e+11 | G59: 8.0292211e+10 | I59: 6.6443662e+10 | J59: 2.1855203e+11 | K59: 3.3113944e+10 | L59: 2.4291156e+10 | M59: 3.6804782e+09 | N59: 103902.69 | P59: 1.7442926e+10 | Q59: 1.0194336e+10 | R59: 3.6551334e+09 | S59: 3.7460905e+09 | T59: 7.4012239e+09 | U59: 8.098413e+09 | V59: 7.35581e+09 | W59: 1.0797121e+11 | X59: 1.0797121e+11 | Y59: 1.4476563e+11 | Z59: 5.6001055e+10 | AA59: 0.3025344 | AB59: 772763.58
A60: 2008 | B60: D_E | C60: 4 | D60: Rev.4 | E60: 2.8302772e+10 | G60: 4.7297625e+09 | I60: 4.7297625e+09 | J60: 2.3573009e+10 | L60: 5.2566252e+09 | N60: 11916.476 | P60: 3.5596535e+09 | Q60: 1.6414345e+09 | R60: 733621.1 | S60: 632251.55 | T60: 1365872.6 | U60: 4.5992676e+09 | V60: 35414088 | W60: 8.9149482e+10 | X60: 8.9149482e+10 | Z60: -5.2686273e+08 | AA60: 1.1113931 | AB60: 396909.49
A61: 2008 | B61: G | C61: 4 | D61: Rev.4 | E61: 7.1883001e+10 | G61: 4.3372823e+10 | I61: 3.9613651e+10 | J61: 3.226935e+10 | L61: 1.6738003e+10 | N61: 92823.464 | P61: 5.221208e+09 | Q61: 2.5474513e+09 | R61: 9.7844809e+08 | S61: 8.2581775e+08 | T61: 1.8042658e+09 | U61: 2.2074893e+09 | V61: 1.8285322e+09 | W61: 2.4604614e+10 | X61: 2.4604614e+10 | Z61: 2.663482e+10 | AA61: 0.38590993 | AB61: 467261.41
A62: 2008 | B62: H_J | C62: 4 | D62: Rev.4 | E62: 9.1476064e+10 | G62: 3.6179998e+10 | I62: 3.6173751e+10 | J62: 5.5302312e+10 | L62: 1.7013e+10 | N62: 51846.564 | P62: 1.3636149e+10 | Q62: 1.0843727e+10 | R62: 4.1790646e+09 | S62: 2.1896794e+09 | T62: 6.368744e+09 | U62: 7.7306448e+09 | V62: -1.1518012e+09 | W62: 6.5044413e+10 | X62: 6.5044413e+10 | Z62: 1.9166997e+10 | AA62: 0.47023222 | AB62: 697828.27
A63: 2008 | B63: I | C63: 4 | D63: Rev.4 | E63: 1.1300027e+10 | G63: 4.8214878e+09 | I63: 4.8194033e+09 | J63: 6.4806237e+09 | L63: 2.6342635e+09 | N63: 18496.75 | P63: 3.7365444e+08 | Q63: 2.9354019e+08 | R63: 1.2213127e+08 | S63: 12680853 | T63: 1.3481212e+08 | U63: 9.3199967e+08 | V63: 27390410 | W63: 1.8028257e+10 | X63: 1.8028257e+10 | Z63: 2.1872243e+09 | AA63: 0.54635905 | AB63: 260666.76
A64: 2008 | B64: L_M_N | C64: 4 | D64: Rev.4 | E64: 2.3468428e+10 | G64: 9.4368917e+09 | I64: 9.4367579e+09 | J64: 1.403167e+10 | L64: 6.1006131e+09 | N64: 46616.446 | P64: 7.7788019e+08 | Q64: 6.1900975e+08 | R64: 37826465 | S64: 3.7164346e+08 | T64: 4.0946992e+08 | U64: 4.4620114e+08 | V64: 46938395 | W64: 4.2751627e+09 | X64: 4.2751627e+09 | Z64: 3.3362785e+09 | AA64: 0.64646425 | AB64: 202436.96
A65: 2008 | B65: P | C65: 4 | D65: Rev.4 | E65: 5.8653048e+09 | G65: 4.2709082e+09 | I65: 4.2709082e+09 | J65: 1.5943965e+09 | L65: 3.5666642e+09 | N65: 31795.136 | P65: 2.4644705e+08 | Q65: 97784995 | R65: 16904145 | S65: 25812337 | T65: 42716482 | U65: 2.1689978e+08 | V65: 2193644.8 | W65: 4.9238184e+09 | X65: 4.9238184e+09 | Z65: 7.04244e+08 | AA65: 0.83510674 | AB65: 134325.84
A66: 2008 | B66: Q | C66: 4 | D66: Rev.4 | E66: 3.5285336e+10 | G66: 1.9717369e+10 | I66: 1.9717369e+10 | J66: 1.5567967e+10 | L66: 1.6994716e+10 | N66: 69259.138 | P66: 1.6124988e+09 | Q66: 4.7528656e+08 | R66: 2657427.3 | S66: 1.7309548e+08 | T66: 1.7575291e+08 | U66: 7.0277096e+08 | V66: -22014456 | W66: 1.3739385e+10 | X66: 1.3739385e+10 | Z66: 2.7226533e+09 | AA66: 0.86191599 | AB66: 284689.78
A67: 2008 | B67: R_S | C67: 4 | D67: Rev.4 | E67: 5.791343e+09 | G67: 2.7140219e+09 | I67: 2.7140219e+09 | J67: 3.0773211e+09 | L67: 1.4754845e+09 | N67: 8919.4444 | P67: 2.528675e+08 | Q67: 1.0379432e+08 | R67: 20187249 | S67: 16320548 | T67: 36507797 | U67: 3.1993026e+08 | V67: -2745182.4 | W67: 5.3802295e+09 | X67: 5.3802295e+09 | Z67: 1.2385374e+09 | AA67: 0.5436524 | AB67: 304281.5
A68: 2009 | B68: C | C68: 4 | D68: Rev.4 | E68: 2.6234716e+11 | G68: 7.8234884e+10 | I68: 6.4741176e+10 | J68: 1.9760598e+11 | K68: 2.9940301e+10 | L68: 2.9743371e+10 | M68: 4.5065713e+09 | N68: 104036.65 | P68: 7.9610854e+09 | Q68: 5.8014096e+09 | R68: 2.4158472e+09 | S68: 1.4778565e+09 | T68: 3.8937037e+09 | U68: 7.8032167e+09 | V68: 9.1759088e+09 | W68: 9.3192118e+10 | X68: 9.3192118e+10 | Y68: 1.2763899e+11 | Z68: 4.8491513e+10 | AA68: 0.38018041 | AB68: 751993.51
A69: 2009 | B69: D_E | C69: 4 | D69: Rev.4 | E69: 3.4162044e+10 | G69: 1.229918e+10 | I69: 1.229918e+10 | J69: 21862864522 | L69: 6.0687981e+09 | N69: 12290.2 | P69: 4.7604933e+09 | Q69: 1.6735134e+09 | R69: 216686724 | S69: 78460242 | T69: 2.9514697e+08 | U69: 4863765968 | V69: 1.1467452e+08 | W69: 9.2363394e+10 | X69: 9.2363394e+10 | Z69: 6.2303818e+09 | AA69: 0.49343112 | AB69: 1000730.7
A70: 2009 | B70: G | C70: 4 | D70: Rev.4 | E70: 7.8812299e+10 | G70: 4.6924257e+10 | I70: 4.2857278e+10 | J70: 3.5955021e+10 | L70: 2.1123383e+10 | N70: 99621.607 | P70: 6.9180316e+09 | Q70: 2.202287e+09 | R70: 3.0542925e+09 | S70: 9.483549e+08 | T70: 4.0026474e+09 | U70: 2.4649169e+09 | V70: 1.3039566e+09 | W70: 2.906237e+10 | X70: 2.906237e+10 | Z70: 2.5800874e+10 | AA70: 0.45015913 | AB70: 471024.89
A71: 2009 | B71: H_J | C71: 4 | D71: Rev.4 | E71: 9.421975e+10 | G71: 4.4677051e+10 | I71: 4.4669338e+10 | J71: 4.9550413e+10 | L71: 2.059324e+10 | N71: 54292.735 | P71: 1.3488357e+10 | Q71: 9.6574113e+09 | R71: 3.6641461e+09 | S71: 7.5665542e+08 | T71: 4.4208015e+09 | U71: 8.877255e+09 | V71: -2.1402447e+09 | W71: 8.5729337e+10 | X71: 8.5729337e+10 | Z71: 2.4083811e+10 | AA71: 0.46093553 | AB71: 822891.88
A72: 2009 | B72: I | C72: 4 | D72: Rev.4 | E72: 1.2674114e+10 | G72: 5.4364114e+09 | I72: 5.434061e+09 | J72: 7.2400532e+09 | L72: 2.9652052e+09 | N72: 17697.471 | P72: 7.8036587e+08 | Q72: 3.2043378e+08 | R72: 102402211 | S72: 21020468 | T72: 1.2342268e+08 | U72: 7.3729613e+08 | V72: 15094091 | W72: 1.5824518e+10 | X72: 1.5824518e+10 | Z72: 2.4712062e+09 | AA72: 0.54543429 | AB72: 307185.78
A73: 2009 | B73: L_M_N | C73: 4 | D73: Rev.4 | E73: 3.1888504e+10 | G73: 1.45577e+10 | I73: 1.4557493e+10 | J73: 1.733101e+10 | L73: 9.8178031e+09 | N73: 61772.261 | P73: 1.0928305e+09 | Q73: 8.2847435e+08 | R73: 1.3550681e+08 | S73: 6.0722328e+08 | T73: 7.4273008e+08 | U73: 6.0606919e+08 | V73: -2.2390963e+08 | W73: 5.6362652e+09 | X73: 5.6362652e+09 | Z73: 4.7398965e+09 | AA73: 0.67440622 | AB73: 235667.26
A74: 2009 | B74: P | C74: 4 | D74: Rev.4 | E74: 7.0240628e+09 | G74: 5.4739327e+09 | I74: 5.4739327e+09 | J74: 1.5501301e+09 | L74: 4.3306309e+09 | N74: 30152.827 | P74: 3.9685707e+08 | Q74: 1.0734819e+08 | R74: 3129009.7 | S74: 16498482 | T74: 19627492 | U74: 1.9108306e+08 | V74: -4797672 | W74: 4.4201673e+09 | X74: 4.4201673e+09 | Z74: 1.1433018e+09 | AA74: 0.79113703 | AB74: 181539.62
A75: 2009 | B75: Q | C75: 4 | D75: Rev.4 | E75: 3.9651081e+10 | G75: 2.192746e+10 | I75: 2.192746e+10 | J75: 1.772362e+10 | L75: 1.9081212e+10 | N75: 74044.771 | P75: 1.7221042e+09 | Q75: 7.9498932e+08 | R75: 11132202 | S75: 2.7858658e+08 | T75: 2.8971878e+08 | U75: 7.5735936e+08 | V75: -3846200.9 | W75: 1.4648937e+10 | X75: 1.4648937e+10 | Z75: 2.8462482e+09 | AA75: 0.87019709 | AB75: 296137.87
A76: 2009 | B76: R_S | C76: 4 | D76: Rev.4 | E76: 1.1746279e+10 | G76: 5.1215281e+09 | I76: 5.1215281e+09 | J76: 6.6247513e+09 | L76: 3.3852699e+09 | N76: 23552.492 | P76: 3.7520934e+08 | Q76: 1.9563092e+08 | R76: 76243318 | S76: 39270109 | T76: 1.1551343e+08 | U76: 3.872378e+08 | V76: -11281477 | W76: 5.5168866e+09 | X76: 5.5168866e+09 | Z76: 1.7362583e+09 | AA76: 0.66098824 | AB76: 217451.64
A77: 2010 | B77: C | C77: 4 | D77: Rev.4 | E77: 2.9861469e+11 | G77: 9.5564091e+10 | I77: 7.9081496e+10 | J77: 2.1953319e+11 | K77: 3.3262604e+10 | L77: 3.413185e+10 | M77: 5.1714925e+09 | N77: 112274.19 | P77: 1.0581329e+10 | Q77: 6.5272666e+09 | R77: 2.6329602e+09 | S77: 1.8229898e+09 | T77: 4.45595e+09 | U77: 8.1548456e+09 | V77: 1.2317166e+10 | W77: 9.973781e+10 | X77: 9.973781e+10 | Y77: 1.3817191e+11 | Z77: 6.1432241e+10 | AA77: 0.35716188 | AB77: 851167.02
A78: 2010 | B78: D_E | C78: 4 | D78: Rev.4 | E78: 3.8994624e+10 | G78: 2.639003e+10 | I78: 2.639003e+10 | J78: 1.2604595e+10 | L78: 7026644454 | N78: 12607.25 | P78: 9171112853 | Q78: 1551406864 | R78: 908300 | S78: 6714257 | T78: 7622557 | U78: 5.6781742e+09 | V78: 56662309 | W78: 1.0972106e+11 | X78: 1.0972106e+11 | Z78: 1.9363385e+10 | AA78: 0.26626133 | AB78: 2093242.3
A79: 2010 | B79: G | C79: 4 | D79: Rev.4 | E79: 1.1483766e+11 | G79: 6.4321142e+10 | I79: 5.8746356e+10 | J79: 5.6091307e+10 | L79: 2.6747076e+10 | N79: 112666.91 | P79: 8.0769359e+09 | Q79: 4.6497414e+09 | R79: 3.3509352e+08 | S79: 3.1695816e+09 | T79: 3.5046751e+09 | U79: 3.2689597e+09 | V79: 1.8133373e+09 | W79: 3.9049175e+10 | X79: 3.9049175e+10 | Z79: 3.7574066e+10 | AA79: 0.41583646 | AB79: 570896.48
A80: 2010 | B80: H_J | C80: 4 | D80: Rev.4 | E80: 1.1605595e+11 | G80: 5.2926001e+10 | I80: 5.2916863e+10 | J80: 6.3139086e+10 | L80: 2.4322396e+10 | N80: 59920.013 | P80: 1.5474183e+10 | Q80: 1.1653055e+10 | R80: 6.0036648e+09 | S80: 1.0245228e+09 | T80: 7.0281876e+09 | U80: 1.0453299e+10 | V80: -2.347559e+09 | W80: 1.1221557e+11 | X80: 1.1221557e+11 | Z80: 2.8603604e+10 | AA80: 0.45955477 | AB80: 883277.52
A81: 2010 | B81: I | C81: 4 | D81: Rev.4 | E81: 2.3403987e+10 | G81: 7.6458596e+09 | I81: 7.642554e+09 | J81: 1.5761433e+10 | L81: 4.5441847e+09 | N81: 24412.392 | P81: 2.2948786e+09 | Q81: 1.2938718e+09 | R81: 64677873 | S81: 4.6392454e+08 | T81: 5.2860241e+08 | U81: 1.3529966e+09 | V81: 49613909 | W81: 3.5928437e+10 | X81: 3.5928437e+10 | Z81: 3.1016749e+09 | AA81: 0.59433274 | AB81: 313195.84
A82: 2010 | B82: L_M_N | C82: 4 | D82: Rev.4 | E82: 4.4407587e+10 | G82: 2.0477576e+10 | I82: 2.0477286e+10 | J82: 2.3930302e+10 | L82: 1.5123684e+10 | N82: 73624.331 | P82: 1.8644156e+09 | Q82: 1.1688068e+09 | R82: 2.7860239e+08 | S82: 6.4883309e+08 | T82: 9.2743547e+08 | U82: 1.1349037e+09 | V82: 69904849 | W82: 8.788434e+09 | X82: 8.788434e+09 | Z82: 5.3538917e+09 | AA82: 0.73854856 | AB82: 278135.98
A83: 2010 | B83: P | C83: 4 | D83: Rev.4 | E83: 9.3076636e+09 | G83: 6.7444923e+09 | I83: 6.7444923e+09 | J83: 2.5631713e+09 | L83: 5.1077591e+09 | N83: 31457.154 | P83: 4.7342094e+08 | Q83: 1.0650205e+08 | R83: 11199775 | S83: 59287417 | T83: 70487192 | U83: 2.1436763e+08 | V83: 793234.65 | W83: 5.610572e+09 | X83: 5.610572e+09 | Z83: 1.6367332e+09 | AA83: 0.75732299 | AB83: 214402.5
A84: 2010 | B84: Q | C84: 4 | D84: Rev.4 | E84: 4.7873424e+10 | G84: 2.8110573e+10 | I84: 2.8110573e+10 | J84: 1.9762851e+10 | L84: 2.3647227e+10 | N84: 75954.12 | P84: 1.2635303e+10 | Q84: 7.8860874e+09 | R84: 9310425.1 | S84: 7.4907087e+09 | T84: 7.5000191e+09 | U84: 1.0997774e+09 | V84: -50890166 | W84: 3.1147915e+10 | X84: 3.1147915e+10 | Z84: 4.4633463e+09 | AA84: 0.8412218 | AB84: 370099.38
A85: 2010 | B85: R_S | C85: 4 | D85: Rev.4 | E85: 1.5929304e+10 | G85: 6.1254962e+09 | I85: 6.1254962e+09 | J85: 9.8038081e+09 | L85: 4.0349221e+09 | N85: 19366.406 | P85: 5.052205e+08 | Q85: 2.3361866e+08 | R85: 8978822.9 | S85: 84005653 | T85: 92984476 | U85: 4.2295249e+08 | V85: -3827397.8 | W85: 6.8972281e+09 | X85: 6.8972281e+09 | Z85: 2.0905741e+09 | AA85: 0.65870943 | AB85: 316294.94
A86: 2011 | B86: C | C86: 4 | D86: Rev.4 | E86: 3.2272011e+11 | G86: 9.770659e+10 | I86: 8.0854464e+10 | J86: 2.4186565e+11 | K86: 3.664631e+10 | L86: 3.8240757e+10 | M86: 5.7940541e+09 | N86: 109399.62 | O86: 2202 | U86: 8.1848116e+09 | V86: 1.8825379e+10 | X86: 1.2215015e+11 | Y86: 1.6459051e+11 | Z86: 5.9465833e+10 | AA86: 0.3913836 | AB86: 893116.33
A87: 2011 | B87: D_E | C87: 4 | D87: Rev.4 | E87: 3.957822e+10 | G87: 1.9218415e+10 | I87: 1.9218415e+10 | J87: 2.0359805e+10 | L87: 7.8356415e+09 | N87: 14529.585 | O87: 135 | U87: 6.1147226e+09 | V87: 1.4582153e+09 | X87: 1.2577402e+11 | Z87: 1.1382774e+10 | AA87: 0.40771528 | AB87: 1322709.1
A88: 2011 | B88: G | C88: 4 | D88: Rev.4 | E88: 1.2104423e+11 | G88: 7.323163e+10 | I88: 6.6884562e+10 | J88: 5.4159664e+10 | L88: 3.1869388e+10 | N88: 114837.62 | O88: 3512 | U88: 3.339585e+09 | V88: 3.2272713e+09 | X88: 3.6946814e+10 | Z88: 4.1362242e+10 | AA88: 0.43518611 | AB88: 637697.22
A89: 2011 | B89: H_J | C89: 4 | D89: Rev.4 | E89: 1.4633239e+11 | G89: 6.588198e+10 | I89: 6.5870606e+10 | J89: 8.0461789e+10 | L89: 3.5431447e+10 | N89: 74688.449 | O89: 1327 | U89: 1.018264e+10 | V89: -1.2033511e+09 | X89: 1.3084131e+11 | Z89: 3.0450532e+10 | AA89: 0.5378018 | AB89: 882090.61
A90: 2011 | B90: I | C90: 4 | D90: Rev.4 | E90: 1.4288171e+10 | G90: 5.8447899e+09 | I90: 5.8422629e+09 | J90: 8.4459081e+09 | L90: 3.6673898e+09 | N90: 20434.278 | O90: 817 | U90: 6.1377922e+08 | V90: 1.1191188e+08 | X90: 1.1831367e+10 | Z90: 2.1774001e+09 | AA90: 0.62746307 | AB90: 286028.69
A91: 2011 | B91: L_M_N | C91: 4 | D91: Rev.4 | E91: 4.5797083e+10 | G91: 2.2095562e+10 | I91: 2.2095248e+10 | J91: 2.3701834e+10 | L91: 1.6480028e+10 | N91: 74963.794 | O91: 1344 | U91: 1.2043832e+09 | V91: -2.6072877e+08 | X91: 1.3744329e+10 | Z91: 5.6155334e+09 | AA91: 0.74585242 | AB91: 294749.78
A92: 2011 | B92: P | C92: 4 | D92: Rev.4 | E92: 9.7962133e+09 | G92: 7.3871854e+09 | I92: 7.3871854e+09 | J92: 2.4090279e+09 | L92: 6.3495843e+09 | N92: 32998.554 | O92: 457 | U92: 2.4595155e+08 | V92: 1601961.1 | X92: 7.2507391e+09 | Z92: 1.0376011e+09 | AA92: 0.8595404 | AB92: 223863.91
A93: 2011 | B93: Q | C93: 4 | D93: Rev.4 | E93: 5.2814829e+10 | G93: 3.0273156e+10 | I93: 3.0273156e+10 | J93: 2.2541673e+10 | L93: 2.771731e+10 | N93: 79386.789 | O93: 740 | U93: 9.7944401e+08 | V93: 97359386 | X93: 1.8849191e+10 | Z93: 2.5558464e+09 | AA93: 0.91557384 | AB93: 381337.46
A94: 2011 | B94: R_S | C94: 4 | D94: Rev.4 | E94: 1.9127335e+10 | G94: 8.0698098e+09 | I94: 8.0698098e+09 | J94: 1.1057525e+10 | L94: 5.3790439e+09 | N94: 21219.08 | O94: 623 | U94: 6.281936e+08 | V94: 1.9961589e+08 | X94: 1.2617373e+10 | Z94: 2.6907659e+09 | AA94: 0.6665639 | AB94: 380309.13
A95: 2012 | B95: B | C95: 4 | D95: Rev.4 | E95: 2.070794e+09 | G95: 9.6572613e+08 | I95: 9.6572613e+08 | J95: 1.1050679e+09 | L95: 3.5214265e+08 | N95: 1006.679 | P95: 3.0065551e+08 | Q95: 1.5157094e+08 | R95: 25535654 | S95: 1.2381911e+08 | T95: 1.4935477e+08 | U95: 1.3495536e+08 | V95: 3971492.2 | W95: 1.9673107e+09 | X95: 1.9673107e+09 | Z95: 6.1358348e+08 | AA95: 0.36464028 | AB95: 959318.81
A96: 2012 | B96: C | C96: 4 | D96: Rev.4 | E96: 3.6649548e+11 | G96: 9.9292175e+10 | I96: 8.2166571e+10 | J96: 2.8432891e+11 | K96: 4.3080137e+10 | L96: 4.3787875e+10 | M96: 6.6345265e+09 | N96: 110138.75 | P96: 1.7144628e+10 | Q96: 1.186762e+10 | R96: 5.9741866e+09 | S96: 3.1526135e+09 | T96: 9.1268001e+09 | U96: 9.2006411e+09 | V96: 1.6525007e+10 | W96: 1.1807022e+11 | X96: 1.1807022e+11 | Y96: 1.6778489e+11 | Z96: 5.55043e+10 | AA96: 0.44100026 | AB96: 901518.99
A97: 2012 | B97: D_E | C97: 4 | D97: Rev.4 | E97: 4.7162072e+10 | G97: 1.1576279e+10 | I97: 1.1576279e+10 | J97: 3.5585793e+10 | L97: 9.9070712e+09 | N97: 15343.036 | P97: 8.6423028e+09 | Q97: 5.8231891e+09 | R97: 15001790 | S97: 1.2633896e+08 | T97: 1.4134075e+08 | U97: 6.4593939e+09 | V97: 1.236264e+08 | W97: 1.3315494e+11 | X97: 1.3315494e+11 | Z97: 1.6692078e+09 | AA97: 0.85580791 | AB97: 754497.29
A98: 2012 | B98: G | C98: 4 | D98: Rev.4 | E98: 1.6578184e+11 | G98: 1.0651103e+11 | I98: 9.7279602e+10 | J98: 6.8502235e+10 | L98: 3.9444684e+10 | N98: 122466.61 | P98: 1.6208013e+10 | Q98: 6.5486695e+09 | R98: 5.2870961e+09 | S98: 1.6528972e+09 | T98: 6.9399932e+09 | U98: 4.0801179e+09 | V98: 4.5614483e+09 | W98: 5.0911294e+10 | X98: 5.0911294e+10 | Z98: 6.706635e+10 | AA98: 0.37033425 | AB98: 869714.89
A99: 2012 | B99: H_J | C99: 4 | D99: Rev.4 | E99: 1.4307109e+11 | G99: 6.2543395e+10 | I99: 6.2532598e+10 | J99: 8.0538488e+10 | L99: 3.381898e+10 | N99: 67775.477 | P99: 1.685623e+10 | Q99: 1.1814252e+10 | R99: 4.8504144e+09 | S99: 3.4822946e+09 | T99: 8.332709e+09 | U99: 1.0924763e+10 | V99: -1.5787808e+09 | W99: 9.7676324e+10 | X99: 9.7676324e+10 | Z99: 2.8724416e+10 | AA99: 0.54072823 | AB99: 922802.73
A100: 2012 | B100: I | C100: 4 | D100: Rev.4 | E100: 1.5859124e+10 | G100: 6.7198576e+09 | I100: 6.7169524e+09 | J100: 9.1421713e+09 | L100: 4.3518163e+09 | N100: 21646.754 | P100: 1.5383881e+09 | Q100: 6.0511097e+08 | R100: 3948239.3 | S100: 1.1925628e+08 | T100: 1.2320452e+08 | U100: 6.9535508e+08 | V100: 84870844 | W100: 1.348703e+10 | X100: 1.348703e+10 | Z100: 2.3680414e+09 | AA100: 0.64760543 | AB100: 310432.57
...

Sheet rama-C
A1: anno | B1: seccion | C1: epoca | D1: ciiu_version | E1: vbp_pp | F1: vbp_pb | G1: vab_pp | H1: vab_pb | I1: vab_pb_estimado | J1: consumo_intermedio_estimado | K1: capital_circulante_constante_adelantado | L1: remuneraciones | M1: capital_variable_adelantado | N1: puestos_trabajo | O1: n_empresas | P1: fbcf | Q1: fbkf_maq_eq | R1: adquisiciones_importadas | S1: adquisiciones_origen_importado | T1: importaciones_maquinaria | U1: consumo_capital_fijo | V1: impuestos_netos | W1: stock_capital | X1: stock_capital_imputado | Y1: capital_total_adelantado | Z1: excedente_bruto | AA1: part_salarial | AB1: productividad | AC1: Ganancia desp de impuestos
A2: 2001 | B2: C | C2: 1 | D2: Rev.3 | E2: 89240215000 | G2: 32030854000 | I2: 2.6506273e+10 | J2: 6.2733942e+10 | K2: 9.5051428e+09 | L2: 11462459000 | M2: 1.7367362e+09 | N2: 113817 | O2: 12367 | P2: 3539644000 | Q2: 2057120000 | R2: 1075519000 | U2: 3127411000 | V2: 6829485000 | W2: 28622363000 | X2: 28622363000 | Y2: 3.9864242e+10 | Z2: 20568395000 | AA2: 0.3578568 | AB2: 281424.16 | AC2: =I2-L2-U2-V2 -> 5.0869177e+09 | AD2: =AC2/Y2 -> 0.12760603
A3: 2002 | B3: C | C3: 2 | D3: Rev.3 | E3: 104934883446 | G3: 39381506784 | I3: 3.2589108e+10 | J3: 7.2345776e+10 | K3: 1.0961481e+10 | L3: 9421078355 | M3: 1.4274361e+09 | N3: 76575 | O3: 2884 | U3: 3758469943 | V3: 5924169665 | X3: 3.808799e+10 | Y3: 5.0476907e+10 | Z3: 29960428429 | AA3: 0.23922595 | AB3: 514286.74 | AC3: =I3-L3-U3-V3 -> 1.348539e+10 | AD3: =AC3/Y3 -> 0.26715959
A4: 2003 | B4: C | C4: 2 | D4: Rev.3 | E4: 139349946300 | G4: 41497361974 | I4: 3.4340027e+10 | J4: 1.0500992e+11 | K4: 1.5910594e+10 | L4: 10878789626 | M4: 1.6483015e+09 | N4: 83356 | O4: 2884 | P4: 6899547696 | Q4: 5558448986 | R4: 5256351292 | U4: 4714590576 | V4: 6090823735 | W4: 48103564060 | X4: 48103564060 | Y4: 6.5662459e+10 | Z4: 30618572348 | AA4: 0.26215617 | AB4: 497832.93 | AC4: =I4-L4-U4-V4 -> 1.2655823e+10 | AD4: =AC4/Y4 -> 0.19274062
A5: 2004 | B5: C | C5: 2 | D5: Rev.3 | E5: 179010449525 | G5: 52621053735 | I5: 4.3545139e+10 | J5: 1.3546531e+11 | K5: 2.0525047e+10 | L5: 12139435357 | M5: 1.8393084e+09 | N5: 88653 | O5: 3252 | P5: 6396127195 | Q5: 3154522472 | R5: 1599697016 | S5: 1743085329 | T5: 3342782345 | U5: 5136920717 | V5: 7039185004 | W5: 50525577181 | X5: 50525577181 | Y5: 7.2889933e+10 | Z5: 40481618378 | AA5: 0.23069541 | AB5: 593562.02 | AC5: =I5-L5-U5-V5 -> 1.9229598e+10 | AD5: =AC5/Y5 -> 0.26381693
A6: 2005 | B6: C | C6: 2 | D6: Rev.3 | E6: 184862461743 | G6: 53991760706 | I6: 4.4679431e+10 | J6: 1.4018303e+11 | K6: 2.1239853e+10 | L6: 14615233399 | M6: 2.2144293e+09 | N6: 102414 | O6: 3445 | P6: 6464007473 | Q6: 2747259075 | R6: 2116008436 | S6: 2111494326 | T6: 4227502762 | U6: 5058292667 | V6: 7651885206 | W6: 52418214093 | X6: 52418214093 | Y6: 7.5872497e+10 | Z6: 39376527307 | AA6: 0.27069377 | AB6: 527191.21 | AC6: =I6-L6-U6-V6 -> 1.735402e+10 | AD6: =AC6/Y6 -> 0.22872609
A7: 2006 | B7: C | C7: 3 | D7: Rev.3 | E7: 1.850396e+11 | G7: 5.4017528e+10 | I7: 4.4700754e+10 | J7: 1.4033884e+11 | K7: 2.1263461e+10 | L7: 1.3982311e+10 | M7: 2.118532e+09 | N7: 63928.853 | P7: 6.5161369e+09 | Q7: 4.2278276e+09 | R7: 2.1827562e+09 | S7: 1.4258711e+09 | T7: 3.6086273e+09 | U7: 4.2569136e+09 | V7: 8.4664645e+09 | W7: 5.7185677e+10 | X7: 5.7185677e+10 | Y7: 8.056767e+10 | Z7: 4.0035217e+10 | AA7: 0.25884767 | AB7: 844963.2 | AC7: =I7-L7-U7-V7 -> 1.7995065e+10 | AD7: =AC7/Y7 -> 0.22335342
A8: 2007 | B8: C | C8: 3 | D8: Rev.3 | E8: 2.35394e+11 | G8: 7.0661648e+10 | I8: 5.8474148e+10 | J8: 1.7691985e+11 | K8: 2.6806038e+10 | L8: 1.9975832e+10 | M8: 3.0266412e+09 | N8: 100576.01 | P8: 1.735929e+10 | Q8: 5.9547781e+09 | R8: 2.0501427e+09 | S8: 2.5603315e+09 | T8: 4.6104742e+09 | U8: 5.9348309e+09 | V8: 8.4529852e+09 | W8: 8.8288213e+10 | X8: 8.8288213e+10 | Y8: 1.1812089e+11 | Z8: 5.0685816e+10 | AA8: 0.28269695 | AB8: 702569.59 | AC8: =I8-L8-U8-V8 -> 2.41105e+10 | AD8: =AC8/Y8 -> 0.20411715
A9: 2008 | B9: C | C9: 4 | D9: Rev.4 | E9: 2.8499569e+11 | G9: 8.0292211e+10 | I9: 6.6443662e+10 | J9: 2.1855203e+11 | K9: 3.3113944e+10 | L9: 2.4291156e+10 | M9: 3.6804782e+09 | N9: 103902.69 | P9: 1.7442926e+10 | Q9: 1.0194336e+10 | R9: 3.6551334e+09 | S9: 3.7460905e+09 | T9: 7.4012239e+09 | U9: 8.098413e+09 | V9: 7.35581e+09 | W9: 1.0797121e+11 | X9: 1.0797121e+11 | Y9: 1.4476563e+11 | Z9: 5.6001055e+10 | AA9: 0.3025344 | AB9: 772763.58 | AC9: =I9-L9-U9-V9 -> 2.6698283e+10 | AD9: =AC9/Y9 -> 0.18442418
A10: 2009 | B10: C | C10: 4 | D10: Rev.4 | E10: 2.6234716e+11 | G10: 7.8234884e+10 | I10: 6.4741176e+10 | J10: 1.9760598e+11 | K10: 2.9940301e+10 | L10: 2.9743371e+10 | M10: 4.5065713e+09 | N10: 104036.65 | P10: 7.9610854e+09 | Q10: 5.8014096e+09 | R10: 2.4158472e+09 | S10: 1.4778565e+09 | T10: 3.8937037e+09 | U10: 7.8032167e+09 | V10: 9.1759088e+09 | W10: 9.3192118e+10 | X10: 9.3192118e+10 | Y10: 1.2763899e+11 | Z10: 4.8491513e+10 | AA10: 0.38018041 | AB10: 751993.51 | AC10: =I10-L10-U10-V10 -> 1.801868e+10 | AD10: =AC10/Y10 -> 0.14116909
A11: 2010 | B11: C | C11: 4 | D11: Rev.4 | E11: 2.9861469e+11 | G11: 9.5564091e+10 | I11: 7.9081496e+10 | J11: 2.1953319e+11 | K11: 3.3262604e+10 | L11: 3.413185e+10 | M11: 5.1714925e+09 | N11: 112274.19 | P11: 1.0581329e+10 | Q11: 6.5272666e+09 | R11: 2.6329602e+09 | S11: 1.8229898e+09 | T11: 4.45595e+09 | U11: 8.1548456e+09 | V11: 1.2317166e+10 | W11: 9.973781e+10 | X11: 9.973781e+10 | Y11: 1.3817191e+11 | Z11: 6.1432241e+10 | AA11: 0.35716188 | AB11: 851167.02 | AC11: =I11-L11-U11-V11 -> 2.4477634e+10 | AD11: =AC11/Y11 -> 0.17715348
A12: 2011 | B12: C | C12: 4 | D12: Rev.4 | E12: 3.2272011e+11 | G12: 9.770659e+10 | I12: 8.0854464e+10 | J12: 2.4186565e+11 | K12: 3.664631e+10 | L12: 3.8240757e+10 | M12: 5.7940541e+09 | N12: 109399.62 | O12: 2202 | U12: 8.1848116e+09 | V12: 1.8825379e+10 | X12: 1.2215015e+11 | Y12: 1.6459051e+11 | Z12: 5.9465833e+10 | AA12: 0.3913836 | AB12: 893116.33 | AC12: =I12-L12-U12-V12 -> 1.5603516e+10 | AD12: =AC12/Y12 -> 0.094802037
A13: 2012 | B13: C | C13: 4 | D13: Rev.4 | E13: 3.6649548e+11 | G13: 9.9292175e+10 | I13: 8.2166571e+10 | J13: 2.8432891e+11 | K13: 4.3080137e+10 | L13: 4.3787875e+10 | M13: 6.6345265e+09 | N13: 110138.75 | P13: 1.7144628e+10 | Q13: 1.186762e+10 | R13: 5.9741866e+09 | S13: 3.1526135e+09 | T13: 9.1268001e+09 | U13: 9.2006411e+09 | V13: 1.6525007e+10 | W13: 1.1807022e+11 | X13: 1.1807022e+11 | Y13: 1.6778489e+11 | Z13: 5.55043e+10 | AA13: 0.44100026 | AB13: 901518.99 | AC13: =I13-L13-U13-V13 -> 1.2653049e+10 | AD13: =AC13/Y13 -> 0.075412326
A14: 2013 | B14: C | C14: 4 | D14: Rev.4 | E14: 3.9349558e+11 | G14: 1.1189604e+11 | I14: 9.2596558e+10 | J14: 3.0089902e+11 | K14: 4.5590761e+10 | L14: 5.0186679e+10 | M14: 7.6040423e+09 | N14: 109797.75 | P14: 2.8790673e+10 | Q14: 1.8295653e+10 | R14: 2.4797926e+09 | S14: 1.6298812e+10 | T14: 1.8778604e+10 | U14: 9.6344566e+09 | V14: 2.0496674e+10 | W14: 1.3030327e+11 | X14: 1.3030327e+11 | Y14: 1.8349807e+11 | Z14: 6.1709356e+10 | AA14: 0.44851168 | AB14: 1019110.5 | AC14: =I14-L14-U14-V14 -> 1.2278747e+10 | AD14: =AC14/Y14 -> 0.066914858
A15: 2014 | B15: C | C15: 4 | D15: Rev.4 | E15: 4.5364092e+11 | G15: 1.3078013e+11 | I15: 1.0822358e+11 | J15: 3.4541733e+11 | K15: 5.233596e+10 | L15: 5.6837646e+10 | M15: 8.6117646e+09 | N15: 107700.43 | P15: 7.8176629e+10 | Q15: 5.2611955e+10 | R15: 2.2171191e+09 | S15: 4.8143911e+10 | T15: 5.036103e+10 | U15: 1.2235322e+10 | V15: 2.2082789e+10 | W15: 1.9842942e+11 | X15: 1.9842942e+11 | Y15: 2.5937714e+11 | Z15: 7.3942486e+10 | AA15: 0.4346046 | AB15: 1214295.4 | AC15: =I15-L15-U15-V15 -> 1.7067828e+10 | AD15: =AC15/Y15 -> 0.06580313
A16: 2015 | B16: C | C16: 4 | D16: Rev.4 | E16: 4.7809497e+11 | G16: 1.5193967e+11 | I16: 1.257336e+11 | J16: 3.5236137e+11 | K16: 5.3388087e+10 | L16: 6.1103873e+10 | M16: 9.2581625e+09 | N16: 103791.21 | P16: 2.6806672e+10 | Q16: 1.6410901e+10 | R16: 1.3932607e+09 | S16: 6.2827403e+09 | T16: 7.676001e+09 | U16: 1.4988601e+10 | V16: 2.4800676e+10 | W16: 2.0781379e+11 | X16: 2.0781379e+11 | Y16: 2.7046004e+11 | Z16: 9.0835801e+10 | AA16: 0.40215877 | AB16: 1463897.3 | AC16: =I16-L16-U16-V16 -> 2.4840445e+10 | AD16: =AC16/Y16 -> 0.091845157
A17: 2016 | B17: C | C17: 4 | D17: Rev.4 | E17: 4.8828286e+11 | G17: 1.5538284e+11 | I17: 1.2858289e+11 | J17: 3.5969996e+11 | K17: 5.4499994e+10 | L17: 6.5854042e+10 | M17: 9.9778851e+09 | N17: 100240.45 | P17: 1.7409372e+10 | Q17: 7.9574019e+09 | R17: 1.6947138e+09 | S17: 4.3099059e+09 | T17: 6.0046197e+09 | U17: 1.6145912e+10 | V17: 2.6902001e+10 | W17: 2.188245e+11 | X17: 2.188245e+11 | Y17: 2.8330238e+11 | Z17: 8.9528797e+10 | AA17: 0.42381799 | AB17: 1550101.2 | AC17: =I17-L17-U17-V17 -> 1.9680939e+10 | AD17: =AC17/Y17 -> 0.069469729
A18: 2017 | B18: C | C18: 5 | D18: Rev.4 | E18: 4.8414153e+11 | F18: 4.5578209e+11 | G18: 1.6442457e+11 | H18: 1.3606514e+11 | I18: 1.3606514e+11 | J18: 3.4807639e+11 | K18: 5.2738847e+10 | L18: 7.0584977e+10 | M18: 1.0694694e+10 | N18: 97466.997 | P18: 1.703624e+10 | Q18: 8.4810375e+09 | R18: 1.7263034e+09 | S18: 2.8971526e+09 | T18: 4.623456e+09 | U18: 1.5918677e+10 | V18: 1.9633084e+09 | W18: 2.097731e+11 | X18: 2.097731e+11 | Y18: 2.7320664e+11 | Z18: 9.3839595e+10 | AA18: 0.42928485 | AB18: 1686976.9 | AC18: =I18-L18-U18-V18 -> 4.7598175e+10 | AD18: =AC18/Y18 -> 0.17422042
A19: 2018 | B19: C | C19: 5 | D19: Rev.4 | E19: 5.7003685e+11 | F19: 5.3964224e+11 | G19: 1.9788533e+11 | H19: 1.6749072e+11 | I19: 1.6749072e+11 | J19: 4.0254613e+11 | K19: 6.0991837e+10 | L19: 7.6120685e+10 | M19: 1.1533437e+10 | N19: 94566.086 | P19: 2.1403884e+10 | Q19: 9.3987612e+09 | R19: 2.3443011e+09 | S19: 3.8755945e+09 | T19: 6.2198956e+09 | U19: 1.6454136e+10 | V19: 1.2152229e+09 | W19: 2.3094465e+11 | X19: 2.3094465e+11 | Y19: 303469927276 | Z19: 1.2176465e+11 | AA19: 0.38467068 | AB19: 2092561.3 | AC19: =I19-L19-U19-V19 -> 7.3700681e+10 | AD19: =AC19/Y19 -> 0.24285992
A20: 2019 | B20: C | C20: 5 | D20: Rev.4 | E20: 601651424497 | F20: 569209962569 | G20: 190772526038 | H20: 158331064110 | I20: 158331064110 | J20: 443320360387 | K20: 6.7169752e+10 | L20: 80999471228 | M20: 1.2272647e+10 | N20: 90481 | P20: 30759048024 | Q20: 10582877554 | R20: 10715087960 | S20: 3917218825 | T20: 14632306785 | U20: 1.8470371e+10 | V20: 1.7013764e+09 | W20: 259048160897 | X20: 259048160897 | Y20: 3.3849056e+11 | Z20: 109773054810 | AA20: 0.42458667 | AB20: 2108426.4 | AC20: =I20-L20-U20-V20 -> 5.7159846e+10 | AD20: =AC20/Y20 -> 0.16886688
A21: 2020 | B21: C | C21: 5 | D21: Rev.4 | E21: 6.0081753e+11 | F21: 5.6925511e+11 | G21: 1.8296311e+11 | H21: 1.5140069e+11 | I21: 1.5140069e+11 | J21: 4.4941684e+11 | K21: 6.809346e+10 | L21: 7.8278216e+10 | M21: 1.1860336e+10 | N21: 84764.465 | O21: 1759 | P21: 4.094156e+10 | Q21: 9.808505e+09 | R21: 3.2754489e+09 | S21: 2.7093516e+09 | T21: 5.9848005e+09 | U21: 1.9749526e+10 | V21: -1.8273468e+09 | W21: 2.963226e+11 | X21: 2.963226e+11 | Y21: 3.762764e+11 | Z21: 1.0468489e+11 | AA21: 0.42783606 | AB21: 2158488.4 | AC21: =I21-L21-U21-V21 -> 5.5200295e+10 | AD21: =AC21/Y21 -> 0.14670146
A22: 2021 | B22: C | C22: 5 | D22: Rev.4 | E22: 7.404514e+11 | F22: 7.2951903e+11 | G22: 2.2497468e+11 | H22: 2.1404231e+11 | I22: 2.1404231e+11 | J22: 5.2640909e+11 | K22: 7.9758953e+10 | L22: 8.4122099e+10 | M22: 1.2745773e+10 | N22: 86333.094 | P22: 8.3942984e+10 | Q22: 1.8626904e+10 | R22: 3.3123653e+09 | S22: 6.0037884e+09 | T22: 9.3161537e+09 | U22: 2.1739334e+10 | V22: -1.1586107e+09 | W22: 3.7719399e+11 | X22: 3.7719399e+11 | Y22: 4.6969871e+11 | Z22: 1.4085258e+11 | AA22: 0.37391807 | AB22: 2605891.5 | AC22: =I22-L22-U22-V22 -> 1.0933949e+11 | AD22: =AC22/Y22 -> 0.23278643
A23: 2022 | B23: C | C23: 5 | D23: Rev.4 | E23: 8.8744811e+11 | F23: 8.472213e+11 | G23: 2.6553605e+11 | H23: 2.2530924e+11 | I23: 2.2530924e+11 | J23: 6.6213887e+11 | K23: 1.0032407e+11 | L23: 9.5609914e+10 | M23: 1.4486351e+10 | N23: 89467.506 | P23: 6.9687014e+10 | Q23: 1.724295e+10 | R23: 4.1405769e+09 | S23: 5.18038e+09 | T23: 9.320957e+09 | U23: 2.1523442e+10 | V23: -2.7008478e+09 | W23: 3.9260348e+11 | X23: 3.9260348e+11 | Y23: 5.074139e+11 | Z23: 1.6992614e+11 | AA23: 0.36006378 | AB23: 2967960.8 | AC23: =I23-L23-U23-V23 -> 1.1087673e+11 | AD23: =AC23/Y23 -> 0.21851339
A24: 2023 | B24: C | C24: 5 | D24: Rev.4 | E24: 8.095925e+11 | F24: 7.6790402e+11 | G24: 2.4012716e+11 | H24: 1.9843867e+11 | I24: 1.9843867e+11 | J24: 6.1115383e+11 | K24: 9.2599065e+10 | L24: 1.046198e+11 | M24: 1.5851485e+10 | N24: 89501.941 | P24: 5.6457789e+10 | Q24: 3.8688156e+10 | R24: 3.0484519e+09 | S24: 4.9906452e+09 | T24: 8.0390971e+09 | U24: 2.4684324e+10 | V24: -1.909039e+09 | W24: 4.0246279e+11 | X24: 4.0246279e+11 | Y24: 5.1091334e+11 | Z24: 1.3550736e+11 | AA24: 0.43568499 | AB24: 2682926.8 | AC24: =I24-L24-U24-V24 -> 7.1043588e+10 | AD24: =AC24/Y24 -> 0.13905213
A25: 2024 | B25: C | C25: 5 | D25: Rev.4 | E25: 8.5807161e+11 | F25: 8.12702e+11 | G25: 2.6397033e+11 | H25: 2.1860072e+11 | I25: 2.1860072e+11 | J25: 6.3947089e+11 | K25: 9.6889529e+10 | L25: 1.1292427e+11 | M25: 1.7109737e+10 | N25: 90863.927 | P25: 4.3801058e+10 | Q25: 2.2430814e+10 | R25: 2.2133014e+09 | S25: 6.1907634e+09 | T25: 8.4040648e+09 | U25: 2.7515759e+10 | V25: -2.0029493e+09 | W25: 4.3696596e+11 | X25: 4.3696596e+11 | Y25: 5.5096522e+11 | Z25: 1.5104606e+11 | AA25: 0.42779152 | AB25: 2905116.8 | AC25: =I25-L25-U25-V25 -> 8.0163643e+10 | AD25: =AC25/Y25 -> 0.14549674

Sheet check-calidad-C
A1: anno | B1: vab_vbp | C1: consumo_intermedio_estimado | D1: remuneraciones_vab | E1: stock_vab
A2: 2001 | B2: 0.35892847 | C2: 6.2733942e+10 | D2: 0.3578568 | E2: 0.89358726
A3: 2002 | B3: 0.37529471 | C3: 7.2345776e+10 | D3: 0.23922595 | E3: 0.96715421
A4: 2003 | B4: 0.29779245 | C4: 1.0500992e+11 | D4: 0.26215617 | E4: 1.1591957
A5: 2004 | B5: 0.29395521 | C5: 1.3546531e+11 | D5: 0.23069541 | E5: 0.96017798
A6: 2005 | B6: 0.29206449 | C6: 1.4018303e+11 | D6: 0.27069377 | E6: 0.9708558
A7: 2006 | B7: 0.29192415 | C7: 1.4033884e+11 | D7: 0.25884767 | E7: 1.0586504
A8: 2007 | B8: 0.30018457 | C8: 1.7691985e+11 | D8: 0.28269695 | E8: 1.2494502
A9: 2008 | B9: 0.28173131 | C9: 2.1855203e+11 | D9: 0.3025344 | E9: 1.3447283
A10: 2009 | B10: 0.29821129 | C10: 1.9760598e+11 | D10: 0.38018041 | E10: 1.1911837
A11: 2010 | B11: 0.32002475 | C11: 2.1953319e+11 | D11: 0.35716188 | E11: 1.0436746
A12: 2011 | B12: 0.30275953 | C12: 2.4186565e+11 | D12: 0.3913836 | E12: 1.2501731
A13: 2012 | B13: 0.27092333 | C13: 2.8432891e+11 | D13: 0.44100026 | E13: 1.1891191
... A25: 2024 | B25: 0.30763205 | C25: 6.3947089e+11 | D25: 0.42779152 | E25: 1.6553602

Sheet economia_total
A1: anno | B1: seccion | C1: epoca | D1: ciiu_version | E1: vbp_pp | F1: vbp_pb | G1: vab_pp | H1: vab_pb | I1: vab_pb_estimado | J1: consumo_intermedio_estimado | K1: capital_circulante_constante_adelantado | L1: remuneraciones | M1: capital_variable_adelantado | N1: puestos_trabajo | O1: n_empresas | P1: fbcf | Q1: fbkf_maq_eq | R1: adquisiciones_importadas | S1: adquisiciones_origen_importado | T1: importaciones_maquinaria | U1: consumo_capital_fijo | V1: impuestos_netos | W1: stock_capital | X1: stock_capital_imputado | Y1: capital_total_adelantado | Z1: excedente_bruto | AA1: part_salarial | AB1: productividad
A2: 2001 | B2: economia_total | C2: 1 | D2: Rev.3 | E2: 224795374000 | G2: 105965497000 | I2: 9.827438e+10 | J2: 1.2652099e+11 | K2: 3.0124046e+10 | L2: 48921033000 | M2: 11647865000 | N2: 538624 | O2: 93366 | P2: 15584526000 | Q2: 5236788000 | R2: 3176411000 | U2: 9474344000 | V2: 8228656000 | W2: 123851491000 | X2: 123851491000 | Y2: 1.656234e+11 | Z2: 57044464000 | AA2: 0.46166945 | AB2: 196733.71
A3: 2002 | B3: economia_total | C3: 2 | D3: Rev.3 | E3: 228293239248 | G3: 106353797467 | I3: 9.7981986e+10 | J3: 1.3031125e+11 | K3: 3.1026489e+10 | L3: 42622839206 | M3: 1.0148295e+10 | N3: 339997 | O3: 12298 | U3: 11163880916 | V3: 7193975850 | X3: 1.2279995e+11 | Y3: 1.6397473e+11 | Z3: 63730958261 | AA3: 0.40076462 | AB3: 312808.05
A4: 2003 | B4: economia_total | C4: 2 | D4: Rev.3 | E4: 282760554719 | G4: 117480701268 | I4: 1.0844936e+11 | J4: 1.7431119e+11 | K4: 4.1502665e+10 | L4: 44485282167 | M4: 1.0591734e+10 | N4: 345219 | O4: 12298 | P4: 14939026955 | Q4: 9558775510 | R4: 5765671714 | U4: 15388019830 | V4: 7667299026 | W4: 128858476811 | X4: 128858476811 | Y4: 1.8095288e+11 | Z4: 72995419101 | AA4: 0.37866034 | AB4: 340307.75
A5: 2004 | B5: economia_total | C5: 2 | D5: Rev.3 | E5: 342486970874 | G5: 137248675768 | I5: 1.259542e+11 | J5: 2.1653277e+11 | K5: 5.1555422e+10 | L5: 48007488282 | M5: 1.1430354e+10 | N5: 348339 | O5: 13993 | P5: 20956681133 | Q5: 11081662212 | R5: 2372629177 | S5: 3789547557 | T5: 6162176734 | U5: 17341745740 | V5: 8870370869 | W5: 187339221901 | X5: 187339221901 | Y5: 2.50325e+11 | Z5: 89241187486 | AA5: 0.34978471 | AB5: 394008.93
A6: 2005 | B6: economia_total | C6: 2 | D6: Rev.3 | E6: 370267989847 | G6: 152188634950 | I6: 1.4021824e+11 | J6: 2.3004975e+11 | K6: 5.4773749e+10 | L6: 56739334938 | M6: 1.3509365e+10 | N6: 391484 | O6: 14338 | P6: 22308747111 | Q6: 6242564037 | R6: 3786737908 | S6: 3985038215 | T6: 7771776123 | U6: 17296133580 | V6: 9812890558 | W6: 239076254150 | X6: 239076254150 | Y6: 3.0735937e+11 | Z6: 95449300012 | AA6: 0.37282242 | AB6: 388748.03
A7: 2006 | B7: economia_total | C7: 3 | D7: Rev.3 | E7: 3.3644282e+11 | G7: 1.3131015e+11 | I7: 1.2042281e+11 | J7: 2.1602e+11 | K7: 5.1433334e+10 | L7: 4.7362257e+10 | M7: 1.1276728e+10 | N7: 205952.96 | P7: 1.915072e+10 | Q7: 1.006294e+10 | R7: 3.231972e+09 | S7: 2.9316136e+09 | T7: 6.1635855e+09 | U7: 1.7116477e+10 | V7: 1.0046136e+10 | W7: 2.316872e+11 | X7: 2.316872e+11 | Y7: 2.9439726e+11 | Z7: 8.3947897e+10 | AA7: 0.36068998 | AB7: 637573.52
A8: 2007 | B8: economia_total | C8: 3 | D8: Rev.3 | E8: 4.8136912e+11 | G8: 1.968987e+11 | I8: 1.8138622e+11 | J8: 2.9998289e+11 | K8: 7.1424499e+10 | L8: 7.5965598e+10 | M8: 1.8087047e+10 | N8: 384437.89 | P8: 3.885926e+10 | Q8: 1.7362443e+10 | R8: 4.047232e+09 | S8: 5.3841649e+09 | T8: 9.4313969e+09 | U8: 2.1950974e+10 | V8: 9.8949244e+09 | W8: 2.9195559e+11 | X8: 2.9195559e+11 | Y8: 3.8146713e+11 | Z8: 1.209331e+11 | AA8: 0.38581056 | AB8: 512172.98
A9: 2008 | B9: economia_total | C9: 4 | D9: Rev.4 | E9: 5.591443e+11 | G9: 2.0589024e+11 | I9: 1.8827405e+11 | J9: 3.7087024e+11 | K9: 8.8302439e+10 | L9: 9.4216384e+10 | M9: 2.2432472e+10 | N9: 436444.3 | P9: 4.3310216e+10 | Q9: 2.6919226e+10 | R9: 9.0138274e+09 | S9: 7.3711258e+09 | T9: 1.6384953e+10 | U9: 2.527665e+10 | V9: 8.1270874e+09 | W9: 3.3345108e+11 | X9: 3.3345108e+11 | Y9: 4.4418599e+11 | Z9: 1.1167385e+11 | AA9: 0.45760491 | AB9: 471744.59
A10: 2009 | B10: economia_total | C10: 4 | D10: Rev.4 | E10: 5.7252529e+11 | G10: 2.346524e+11 | I10: 2.1708145e+11 | J10: 3.5544385e+11 | K10: 8.4629487e+10 | L10: 1.1710891e+11 | M10: 2.7883075e+10 | N10: 477461.01 | P10: 3.7495334e+10 | Q10: 2.1581498e+10 | R10: 9.6793861e+09 | S10: 4.223926e+09 | T10: 1.3903312e+10 | U10: 2.66882e+10 | V10: 8.2255544e+09 | W10: 3.4639399e+11 | X10: 3.4639399e+11 | Y10: 4.5890656e+11 | Z10: 1.1754349e+11 | AA10: 0.499074 | AB10: 491458.78
A11: 2010 | B11: economia_total | C11: 4 | D11: Rev.4 | E11: 7.0942489e+11 | G11: 3.0830526e+11 | I11: 2.8623515e+11 | J11: 4.2318974e+11 | K11: 1.0075946e+11 | L11: 1.4468574e+11 | M11: 3.4448987e+10 | N11: 522282.77 | P11: 6.1076799e+10 | Q11: 3.5070356e+10 | R11: 9.3453961e+09 | S11: 1.4770568e+10 | T11: 2.4115964e+10 | U11: 3.1780277e+10 | V11: 1.1905201e+10 | W11: 4.4909621e+11 | X11: 4.4909621e+11 | Y11: 5.8430465e+11 | Z11: 1.6361952e+11 | AA11: 0.46929379 | AB11: 590303.34
A12: 2011 | B12: economia_total | C12: 4 | D12: Rev.4 | E12: 7.7149858e+11 | G12: 3.2970912e+11 | I12: 3.0649571e+11 | J12: 4.6500287e+11 | K12: 1.1071497e+11 | L12: 1.7297059e+11 | M12: 4.1183474e+10 | N12: 542457.77 | O12: 11157 | U12: 3.1493511e+10 | V12: 2.2457275e+10 | X12: 4.6528233e+11 | Y12: 6.1718078e+11 | Z12: 1.5673853e+11 | AA12: 0.52461573 | AB12: 607806.06
A13: 2012 | B13: economia_total | C13: 4 | D13: Rev.4 | E13: 9.0871608e+11 | G13: 3.8080398e+11 | I13: 3.5443286e+11 | J13: 5.5428322e+11 | K13: 1.319722e+11 | L13: 2.0437987e+11 | M13: 4.8661873e+10 | N13: 564843.8 | P13: 7.0402577e+10 | Q13: 3.9914784e+10 | R13: 1.6418463e+10 | S13: 1.0196186e+10 | T13: 2.6614649e+10 | U13: 3.5113807e+10 | V13: 1.9479252e+10 | W13: 4.9028704e+11 | X13: 4.9028704e+11 | Y13: 6.7092111e+11 | Z13: 1.7642411e+11 | AA13: 0.53670623 | AB13: 674175.73
A14: 2013 | B14: economia_total | C14: 4 | D14: Rev.4 | E14: 1.0296306e+12 | G14: 4.4643853e+11 | I14: 4.1664136e+11 | J14: 6.1298921e+11 | K14: 1.4594981e+11 | L14: 2.3971732e+11 | M14: 5.7075553e+10 | N14: 592299.21 | P14: 9.563226e+10 | Q14: 5.3002735e+10 | R14: 1.4065687e+10 | S14: 2.5576873e+10 | T14: 3.964256e+10 | U14: 3.7001352e+10 | V14: 2.4693359e+10 | W14: 5.5187675e+11 | X14: 5.5187675e+11 | Y14: 7.5490212e+11 | Z14: 2.0672121e+11 | AA14: 0.53695482 | AB14: 753738.19
A15: 2014 | B15: economia_total | C15: 4 | D15: Rev.4 | E15: 1.199314e+12 | G15: 5.2532185e+11 | I15: 4.9047465e+11 | J15: 7.0883934e+11 | K15: 1.6877127e+11 | L15: 2.8092664e+11 | M15: 6.6887294e+10 | N15: 616859.35 | P15: 1.5922797e+11 | Q15: 1.0591236e+11 | R15: 1.6710162e+10 | S15: 6.0562625e+10 | T15: 7.7272787e+10 | U15: 4.4318808e+10 | V15: 2.6736847e+10 | W15: 6.764145e+11 | X15: 6.764145e+11 | Y15: 9.1207306e+11 | Z15: 2.4439521e+11 | AA15: 0.53477051 | AB15: 851607.18
A16: 2015 | B16: economia_total | C16: 4 | D16: Rev.4 | E16: 1.3388148e+12 | G16: 6.0720755e+11 | I16: 5.6711566e+11 | J16: 7.7169915e+11 | K16: 1.8373789e+11 | L16: 3.1807998e+11 | M16: 7.5733327e+10 | N16: 618979.93 | P16: 1.0522485e+11 | Q16: 5.8717066e+10 | R16: 1.2495622e+10 | S16: 1.5923038e+10 | T16: 2.841866e+10 | U16: 5.339056e+10 | V16: 3.5268317e+10 | W16: 7.3606147e+11 | X16: 7.3606147e+11 | Y16: 9.9553269e+11 | Z16: 2.8912757e+11 | AA16: 0.52384062 | AB16: 980980.99
A17: 2016 | B17: economia_total | C17: 4 | D17: Rev.4 | E17: 1.4026078e+12 | G17: 6.5167676e+11 | I17: 6.0988181e+11 | J17: 7.9272596e+11 | K17: 1.8874428e+11 | L17: 3.5093764e+11 | M17: 8.3556581e+10 | N17: 614484.09 | P17: 1.0398437e+11 | Q17: 4.9358984e+10 | R17: 9.7301337e+09 | S17: 1.5913459e+10 | T17: 2.5643593e+10 | U17: 5.4852592e+10 | V17: 4.029588e+10 | W17: 8.0602147e+11 | X17: 8.0602147e+11 | Y17: 1.0783223e+12 | Z17: 3.0073912e+11 | AA17: 0.53851489 | AB17: 1060526.7
A18: 2017 | B18: economia_total | C18: 5 | D18: Rev.4 | E18: 1.4879026e+12 | F18: 1.4431962e+12 | G18: 7.1889963e+11 | H18: 6.741932e+11 | I18: 6.741932e+11 | J18: 8.1370943e+11 | K18: 1.9374034e+11 | L18: 3.8513188e+11 | M18: 9.1698067e+10 | N18: 619826.2 | P18: 9.5576489e+10 | Q18: 4.4909449e+10 | R18: 1.0298175e+10 | S18: 1.5627193e+10 | T18: 2.5925368e+10 | U18: 6.0215994e+10 | V18: 1.7621205e+09 | W18: 8.4196603e+11 | X18: 8.4196603e+11 | Y18: 1.1274044e+12 | Z18: 3.3376775e+11 | AA18: 0.53572413 | AB18: 1159840.7
A19: 2018 | B19: economia_total | C19: 5 | D19: Rev.4 | E19: 1.6586837e+12 | F19: 1.6141557e+12 | G19: 7.8992151e+11 | H19: 7.4539355e+11 | I19: 7.4539355e+11 | J19: 9.1329013e+11 | K19: 2.1745003e+11 | L19: 4.2259044e+11 | M19: 1.0061677e+11 | N19: 620093.7 | P19: 9.763821e+10 | Q19: 4.9538064e+10 | R19: 1.2591274e+10 | S19: 1.3728873e+10 | T19: 2.6320147e+10 | U19: 6.2139743e+10 | V19: 2.2498883e+09 | W19: 8.9833026e+11 | X19: 8.9833026e+11 | Y19: 1.2163971e+12 | Z19: 3.6733107e+11 | AA19: 0.53497775 | AB19: 1273874.4
A20: 2019 | B20: economia_total | C20: 5 | D20: Rev.4 | E20: 1790503155926 | F20: 1742328722361 | G20: 824315284444 | H20: 776140850879 | I20: 776140850879 | J20: 1014362305047 | K20: 241514834535 | L20: 456264699852 | M20: 1.0863445e+11 | N20: 611937 | P20: 128886507624 | Q20: 44907885633 | R20: 16497801681 | S20: 14837811020 | T20: 31335612701 | U20: 6.8724455e+10 | V20: 3.5127922e+09 | W20: 995997166119 | X20: 995997166119 | Y20: 1.3461465e+12 | Z20: 368050584592 | AA20: 0.55350751 | AB20: 1347059.1
A21: 2020 | B21: economia_total | C21: 5 | D21: Rev.4 | E21: 1.8050941e+12 | F21: 1.7521347e+12 | G21: 8.3832609e+11 | H21: 7.8536664e+11 | I21: 7.8536664e+11 | J21: 1.0197275e+12 | K21: 2.4279226e+11 | L21: 4.4576854e+11 | M21: 1.0613537e+11 | N21: 570247.16 | O21: 11776 | P21: 1.1696859e+11 | Q21: 4.5261492e+10 | R21: 1.1107721e+10 | S21: 1.3055787e+10 | T21: 2.4163508e+10 | U21: 7.2470064e+10 | V21: 23526226 | W21: 1.0429583e+12 | X21: 1.0429583e+12 | Y21: 1.3918859e+12 | Z21: 3.9255755e+11 | AA21: 0.53173645 | AB21: 1470110.1
A22: 2021 | B22: economia_total | C22: 5 | D22: Rev.4 | E22: 2.173653e+12 | F22: 2.1563994e+12 | G22: 1.0161528e+12 | H22: 9.9889918e+11 | I22: 9.9889918e+11 | J22: 1.1747538e+12 | K22: 2.7970329e+11 | L22: 4.7019982e+11 | M22: 1.1195234e+11 | N22: 602974.92 | P22: 1.8732153e+11 | Q22: 6.588971e+10 | R22: 1.9537004e+10 | S22: 2.1886135e+10 | T22: 4.1423138e+10 | U22: 7.3799557e+10 | V22: -4.2918891e+08 | W22: 1.1733908e+12 | X22: 1.1733908e+12 | Y22: 1.5650464e+12 | Z22: 5.4595295e+11 | AA22: 0.46272552 | AB22: 1685232.2
A23: 2022 | B23: economia_total | C23: 5 | D23: Rev.4 | E23: 2.441897e+12 | F23: 2.3951109e+12 | G23: 1.0825796e+12 | H23: 1.0357935e+12 | I23: 1.0357935e+12 | J23: 1.4061035e+12 | K23: 3.3478656e+11 | L23: 5.2225466e+11 | M23: 1.2434635e+11 | N23: 627085.34 | P23: 1.8303333e+11 | Q23: 7.6871282e+10 | R23: 1.7797192e+10 | S23: 2.025743e+10 | T23: 3.8054622e+10 | U23: 7.4486121e+10 | V23: -2.5757033e+09 | W23: 1.205661e+12 | X23: 1.205661e+12 | Y23: 1664793951570 | Z23: 5.6032498e+11 | AA23: 0.48241685 | AB23: 1726367.3
A24: 2023 | B24: economia_total | C24: 5 | D24: Rev.4 | E24: 2.5188768e+12 | F24: 2.4698218e+12 | G24: 1.1437588e+12 | H24: 1.0947039e+12 | I24: 1.0947039e+12 | J24: 1.4241729e+12 | K24: 3.3908878e+11 | L24: 6.1232644e+11 | M24: 1.4579201e+11 | N24: 664124.7 | P24: 1.8984186e+11 | Q24: 1.0009763e+11 | R24: 1.5278812e+10 | S24: 2.6551542e+10 | T24: 4.1830353e+10 | U24: 8.5762171e+10 | V24: -2.2134906e+08 | W24: 1.2847424e+12 | X24: 1.2847424e+12 | Y24: 1.7696232e+12 | Z24: 5.3143234e+11 | AA24: 0.53536327 | AB24: 1722204.9
A25: 2024 | B25: economia_total | C25: 5 | D25: Rev.4 | E25: 2.7235721e+12 | F25: 2.6707771e+12 | G25: 1.257043e+12 | H25: 1.204248e+12 | I25: 1.204248e+12 | J25: 1.5193242e+12 | K25: 3.6174386e+11 | L25: 6.7234629e+11 | M25: 1.6008245e+11 | N25: 680610.4 | P25: 1.6743766e+11 | Q25: 8.820956e+10 | R25: 1.5575384e+10 | S25: 2.4083777e+10 | T25: 3.9659161e+10 | U25: 9.2718688e+10 | V25: 2.7471819e+08 | W25: 1.3954387e+12 | X25: 1.3954387e+12 | Y25: 1.917265e+12 | Z25: 5.8469666e+11 | AA25: 0.53486342 | AB25: 1846934.7

Sheet check-calidad-total
A1: anno | B1: vab_vbp | C1: consumo_intermedio_estimado | D1: remuneraciones_vab | E1: stock_vab
A2: 2001 | B2: 0.47138647 | C2: 1.2652099e+11 | D2: 0.46166945 | E2: 1.1687907
A3: 2002 | B3: 0.46586486 | C3: 1.3031125e+11 | D3: 0.40076462 | E3: 1.1546362
A4: 2003 | B4: 0.41547769 | C4: 1.7431119e+11 | D4: 0.37866034 | E4: 1.096848
A5: 2004 | B5: 0.40074131 | C5: 2.1653277e+11 | D5: 0.34978471 | E5: 1.364962
A6: 2005 | B6: 0.41102293 | C6: 2.3004975e+11 | D6: 0.37282242 | E6: 1.5709206
A7: 2006 | B7: 0.39028967 | C7: 2.1602e+11 | D7: 0.36068998 | E7: 1.7644271
A8: 2007 | B8: 0.40903891 | C8: 2.9998289e+11 | D8: 0.38581056 | E8: 1.4827705
A9: 2008 | B9: 0.3682238 | C9: 3.7087024e+11 | D9: 0.45760491 | E9: 1.6195575
A10: 2009 | B10: 0.40985509 | C10: 3.5544385e+11 | D10: 0.499074 | E10: 1.4762005
A11: 2010 | B11: 0.43458478 | C11: 4.2318974e+11 | D11: 0.46929379 | E11: 1.4566609
A12: 2011 | B12: 0.42736192 | C12: 4.6500287e+11 | D12: 0.52461573 | E12: 1.4111904
A13: 2012 | B13: 0.41905716 | C13: 5.5428322e+11 | D13: 0.53670623 | E13: 1.287505
... A25: 2024 | B25: 0.46154201 | C25: 1.5193242e+12 | D25: 0.53486342 | E25: 1.1100963

Sheet resultados-total-corrientes
A1: anno | B1: ambito | C1: seccion | D1: rotacion | E1: vbp_pp | F1: vab_pp | G1: vab_pb_estimado | H1: vab_bcu_corriente | I1: vab_eaae_bcu_pct | J1: consumo_capital_fijo | K1: costo_laboral | L1: stock_capital | M1: stock_capital_imputado | N1: fbcf | O1: fbkf_maq_eq | P1: adquisiciones_importadas | Q1: adquisiciones_origen_importado | R1: importaciones_maquinaria | S1: puestos_trabajo | T1: ganancia_pb | U1: ganancia_pp | V1: consumo_intermedio | W1: capital_circulante_adelantado | X1: capital_total_adelantado | Y1: tasa_ganancia_pb | Z1: tasa_ganancia_pp
A2: 2001 | B2: economia_total | C2: economia_total | D2: 4.2 | E2: 224795374000 | F2: 105965497000 | G2: 9.827438e+10 | J2: 9474344000 | K2: 48921033000 | L2: 123851491000 | M2: 123851491000 | N2: 15584526000 | O2: 5236788000 | P2: 3176411000 | S2: 538624 | T2: 3.9879003e+10 | U2: 47570120000 | V2: 118829877000 | W2: 3.9940693e+10 | X2: 1.6379218e+11 | Y2: 0.24347317 | Z2: 0.29042973
A3: 2002 | B3: economia_total | C3: economia_total | D3: 4.2 | E3: 228293239248 | F3: 106353797467 | G3: 9.7981986e+10 | J3: 11163880916 | K3: 42622839206 | M3: 1.2279995e+11 | S3: 339997 | T3: 4.4195265e+10 | U3: 52567077345 | V3: 121939441781 | W3: 3.9181495e+10 | X3: 1.6198144e+11 | Y3: 0.27284154 | Z3: 0.32452531
A4: 2003 | B4: economia_total | C4: economia_total | D4: 4.2 | E4: 282760554719 | F4: 117480701268 | G4: 1.0844936e+11 | J4: 15388019830 | K4: 44485282167 | L4: 128858476811 | M4: 128858476811 | N4: 14939026955 | O4: 9558775510 | P4: 5765671714 | S4: 345219 | T4: 4.857606e+10 | U4: 57607399271 | V4: 165279853451 | W4: 4.994408e+10 | X4: 1.7880256e+11 | Y4: 0.2716743 | Z4: 0.32218443
A5: 2004 | B5: economia_total | C5: economia_total | D5: 4.2 | E5: 342486970874 | F5: 137248675768 | G5: 1.259542e+11 | J5: 17341745740 | K5: 48007488282 | L5: 187339221901 | M5: 187339221901 | N5: 20956681133 | O5: 11081662212 | P5: 2372629177 | Q5: 3789547557 | R5: 6162176734 | S5: 348339 | T5: 6.0604966e+10 | U5: 71899441746 | V5: 205238295106 | W5: 6.0296615e+10 | X5: 2.4763584e+11 | Y5: 0.24473423 | Z5: 0.29034344
A6: 2005 | B6: economia_total | C6: economia_total | D6: 4.2 | E6: 370267989847 | F6: 152188634950 | G6: 1.4021824e+11 | H6: 3.7926041e+11 | I6: 40.127741 | J6: 17296133580 | K6: 56739334938 | L6: 239076254150 | M6: 239076254150 | N6: 22308747111 | O6: 6242564037 | P6: 3786737908 | Q6: 3985038215 | R6: 7771776123 | S6: 391484 | T6: 6.6182775e+10 | U6: 78153166432 | V6: 218079354897 | W6: 6.5433021e+10 | X6: 3.0450928e+11 | Y6: 0.21734239 | Z6: 0.25665283
A7: 2006 | B7: economia_total | C7: economia_total | D7: 4.2 | E7: 3.3644282e+11 | F7: 1.3131015e+11 | G7: 1.2042281e+11 | H7: 4.1762733e+11 | I7: 31.441945 | J7: 1.7116477e+10 | K7: 4.7362257e+10 | L7: 2.316872e+11 | M7: 2.316872e+11 | N7: 1.915072e+10 | O7: 1.006294e+10 | P7: 3.231972e+09 | Q7: 2.9316136e+09 | R7: 6.1635855e+09 | S7: 205952.96 | T7: 5.594408e+10 | U7: 6.6831419e+10 | V7: 2.0513266e+11 | W7: 6.0117838e+10 | X7: 2.9180504e+11 | Y7: 0.19171732 | Z7: 0.22902764
A8: 2007 | B8: economia_total | C8: economia_total | D8: 4.2 | E8: 4.8136912e+11 | F8: 1.968987e+11 | G8: 1.8138622e+11 | H8: 4.8913265e+11 | I8: 40.254664 | J8: 2.1950974e+10 | K8: 7.5965598e+10 | L8: 2.9195559e+11 | M8: 2.9195559e+11 | N8: 3.885926e+10 | O8: 1.7362443e+10 | P8: 4.047232e+09 | Q8: 5.3841649e+09 | R8: 9.4313969e+09 | S8: 384437.89 | T8: 8.3469653e+10 | U8: 9.8982129e+10 | V8: 2.8447042e+11 | W8: 8.5818099e+10 | X8: 3.7777369e+11 | Y8: 0.22095147 | Z8: 0.26201435
A9: 2008 | B9: economia_total | C9: economia_total | D9: 4.2 | E9: 5.591443e+11 | F9: 2.0589024e+11 | G9: 1.8827405e+11 | H9: 5.6983919e+11 | I9: 36.131288 | J9: 2.527665e+10 | K9: 9.4216384e+10 | L9: 3.3345108e+11 | M9: 3.3345108e+11 | N9: 4.3310216e+10 | O9: 2.6919226e+10 | P9: 9.0138274e+09 | Q9: 7.3711258e+09 | R9: 1.6384953e+10 | S9: 436444.3 | T9: 6.8781019e+10 | U9: 8.6397204e+10 | V9: 3.5325406e+11 | W9: 1.0654058e+11 | X9: 4.3999166e+11 | Y9: 0.15632346 | Z9: 0.196361
A10: 2009 | B10: economia_total | C10: economia_total | D10: 4.2 | E10: 5.7252529e+11 | F10: 2.346524e+11 | G10: 2.1708145e+11 | H10: 6.4550448e+11 | I10: 36.351786 | J10: 2.66882e+10 | K10: 1.1710891e+11 | L10: 3.4639399e+11 | M10: 3.4639399e+11 | N10: 3.7495334e+10 | O10: 2.1581498e+10 | P10: 9.6793861e+09 | Q10: 4.223926e+09 | R10: 1.3903312e+10 | S10: 477461.01 | T10: 7.3284335e+10 | U10: 9.0855291e+10 | V10: 3.3787289e+11 | W10: 1.08329e+11 | X10: 4.5472299e+11 | Y10: 0.16116259 | Z10: 0.1998036
A11: 2010 | B11: economia_total | C11: economia_total | D11: 4.2 | E11: 7.0942489e+11 | F11: 3.0830526e+11 | G11: 2.8623515e+11 | H11: 7.2707016e+11 | I11: 42.403784 | J11: 3.1780277e+10 | K11: 1.4468574e+11 | L11: 4.4909621e+11 | M11: 4.4909621e+11 | N11: 6.1076799e+10 | O11: 3.5070356e+10 | P11: 9.3453961e+09 | Q11: 1.4770568e+10 | R11: 2.4115964e+10 | S11: 522282.77 | T11: 1.0976913e+11 | U11: 1.3183924e+11 | V11: 4.0111963e+11 | W11: 1.2995366e+11 | X11: 5.7904987e+11 | Y11: 0.18956765 | Z11: 0.22768201
A12: 2011 | B12: economia_total | C12: economia_total | D12: 4.2 | E12: 7.7149858e+11 | F12: 3.2970912e+11 | G12: 3.0649571e+11 | H12: 8.3210193e+11 | I12: 39.623645 | J12: 3.1493511e+10 | K12: 1.7297059e+11 | M12: 4.6528233e+11 | S12: 542457.77 | T12: 1.0203161e+11 | U12: 1.2524502e+11 | V12: 4.4178946e+11 | W12: 1.4637144e+11 | X12: 6.1165377e+11 | Y12: 0.16681269 | Z12: 0.20476456
A13: 2012 | B13: economia_total | C13: economia_total | D13: 4.2 | E13: 9.0871608e+11 | F13: 3.8080398e+11 | G13: 3.5443286e+11 | H13: 9.4045314e+11 | I13: 40.491542 | J13: 3.5113807e+10 | K13: 2.0437987e+11 | L13: 4.9028704e+11 | M13: 4.9028704e+11 | N13: 7.0402577e+10 | O13: 3.9914784e+10 | P13: 1.6418463e+10 | Q13: 1.0196186e+10 | R13: 2.6614649e+10 | S13: 564843.8 | T13: 1.1493919e+11 | U13: 1.413103e+11 | V13: 5.279121e+11 | W13: 1.7435523e+11 | X13: 6.6464227e+11 | Y13: 0.17293391 | Z13: 0.21261107
A14: 2013 | B14: economia_total | C14: economia_total | D14: 4.2 | E14: 1.0296306e+12 | F14: 4.4643853e+11 | G14: 4.1664136e+11 | H14: 1.065074e+12 | I14: 41.9162 | J14: 3.7001352e+10 | K14: 2.3971732e+11 | L14: 5.5187675e+11 | M14: 5.5187675e+11 | N14: 9.563226e+10 | O14: 5.3002735e+10 | P14: 1.4065687e+10 | Q14: 2.5576873e+10 | R14: 3.964256e+10 | S14: 592299.21 | T14: 1.3992268e+11 | U14: 1.6971986e+11 | V14: 5.8319204e+11 | W14: 1.959308e+11 | X14: 7.4780755e+11 | Y14: 0.18711055 | Z14: 0.2269566
A15: 2014 | B15: economia_total | C15: economia_total | D15: 4.2 | E15: 1.199314e+12 | F15: 5.2532185e+11 | G15: 4.9047465e+11 | H15: 1.2045326e+12 | I15: 43.61209 | J15: 4.4318808e+10 | K15: 2.8092664e+11 | L15: 6.764145e+11 | M15: 6.764145e+11 | N15: 1.5922797e+11 | O15: 1.0591236e+11 | P15: 1.6710162e+10 | Q15: 6.0562625e+10 | R15: 7.7272787e+10 | S15: 616859.35 | T15: 1.652292e+11 | U15: 2.0007641e+11 | V15: 6.7399213e+11 | W15: 2.2736161e+11 | X15: 9.0377611e+11 | Y15: 0.18282094 | Z15: 0.22137829
A16: 2015 | B16: economia_total | C16: economia_total | D16: 4.2 | E16: 1.3388148e+12 | F16: 6.0720755e+11 | G16: 5.6711566e+11 | H16: 1.3233467e+12 | I16: 45.884238 | J16: 5.339056e+10 | K16: 3.1807998e+11 | L16: 7.3606147e+11 | M16: 7.3606147e+11 | N16: 1.0522485e+11 | O16: 5.8717066e+10 | P16: 1.2495622e+10 | Q16: 1.5923038e+10 | R16: 2.841866e+10 | S16: 618979.93 | T16: 1.9564512e+11 | U16: 2.3573701e+11 | V16: 7.3160726e+11 | W16: 2.4992553e+11 | X16: 9.85987e+11 | Y16: 0.19842566 | Z16: 0.23908734
A17: 2016 | B17: economia_total | C17: economia_total | D17: 4.2 | E17: 1.4026078e+12 | F17: 6.5167676e+11 | G17: 6.0988181e+11 | H17: 1.4481339e+12 | I17: 45.001138 | J17: 5.4852592e+10 | K17: 3.5093764e+11 | L17: 8.0602147e+11 | M17: 8.0602147e+11 | N17: 1.0398437e+11 | O17: 4.9358984e+10 | P17: 9.7301337e+09 | Q17: 1.5913459e+10 | R17: 2.5643593e+10 | S17: 614484.09 | T17: 2.0409158e+11 | U17: 2.4588653e+11 | V17: 7.5093101e+11 | W17: 2.6234968e+11 | X17: 1.0683711e+12 | Y17: 0.1910306 | Z17: 0.23015085
A18: 2017 | B18: economia_total | C18: economia_total | D18: 4.2 | E18: 1.4879026e+12 | F18: 7.1889963e+11 | G18: 6.741932e+11 | H18: 1.5507703e+12 | I18: 46.357584 | J18: 6.0215994e+10 | K18: 3.8513188e+11 | L18: 8.4196603e+11 | M18: 8.4196603e+11 | N18: 9.5576489e+10 | O18: 4.4909449e+10 | P18: 1.0298175e+10 | Q18: 1.5627193e+10 | R18: 2.5925368e+10 | S18: 619826.2 | T18: 2.2884532e+11 | U18: 2.7355176e+11 | V18: 7.6900299e+11 | W18: 2.7479402e+11 | X18: 1.11676e+12 | Y18: 0.20491897 | Z18: 0.24495124
A19: 2018 | B19: economia_total | C19: economia_total | D19: 4.2 | E19: 1.6586837e+12 | F19: 7.8992151e+11 | G19: 7.4539355e+11 | H19: 1.6647833e+12 | I19: 47.44891 | J19: 6.2139743e+10 | K19: 4.2259044e+11 | L19: 8.9833026e+11 | M19: 8.9833026e+11 | N19: 9.763821e+10 | O19: 4.9538064e+10 | P19: 1.2591274e+10 | Q19: 1.3728873e+10 | R19: 2.6320147e+10 | S19: 620093.7 | T19: 2.6066337e+11 | U19: 3.0519133e+11 | V19: 8.6876218e+11 | W19: 3.0746491e+11 | X19: 1.2057952e+12 | Y19: 0.2161755 | Z19: 0.25310379
A20: 2019 | B20: economia_total | C20: economia_total | D20: 4.2 | E20: 1790503155926 | F20: 824315284444 | G20: 776140850879 | H20: 1.7977736e+12 | I20: 45.852007 | J20: 6.8724455e+10 | K20: 456264699852 | L20: 995997166119 | M20: 995997166119 | N20: 128886507624 | O20: 44907885633 | P20: 16497801681 | Q20: 14837811020 | R20: 31335612701 | S20: 611937 | T20: 2.511517e+11 | U20: 2.9932613e+11 | V20: 966187871482 | W20: 3.3867918e+11 | X20: 1.3346763e+12 | Y20: 0.18817423 | Z20: 0.2242687
A21: 2020 | B21: economia_total | C21: economia_total | D21: 4.2 | E21: 1.8050941e+12 | F21: 8.3832609e+11 | G21: 7.8536664e+11 | J21: 7.2470064e+10 | K21: 4.4576854e+11 | L21: 1.0429583e+12 | M21: 1.0429583e+12 | N21: 1.1696859e+11 | O21: 4.5261492e+10 | P21: 1.1107721e+10 | Q21: 1.3055787e+10 | R21: 2.4163508e+10 | S21: 570247.16 | T21: 2.6712804e+11 | U21: 3.2008749e+11 | V21: 9.6676804e+11 | W21: 3.3631823e+11 | X21: 1.3792766e+12 | Y21: 0.19367257 | Z21: 0.23206911
A22: 2021 | B22: economia_total | C22: economia_total | D22: 4.2 | E22: 2.173653e+12 | F22: 1.0161528e+12 | G22: 9.9889918e+11 | J22: 7.3799557e+10 | K22: 4.7019982e+11 | L22: 1.1733908e+12 | M22: 1.1733908e+12 | N22: 1.8732153e+11 | O22: 6.588971e+10 | P22: 1.9537004e+10 | Q22: 2.1886135e+10 | R22: 4.1423138e+10 | S22: 602974.92 | T22: 4.548998e+11 | U22: 4.721534e+11 | V22: 1.1575002e+12 | W22: 3.8754763e+11 | X22: 1.5609384e+12 | Y22: 0.29142712 | Z22: 0.30248047
A23: 2022 | B23: economia_total | C23: economia_total | D23: 4.2 | E23: 2.441897e+12 | F23: 1.0825796e+12 | G23: 1.0357935e+12 | J23: 7.4486121e+10 | K23: 5.2225466e+11 | L23: 1.205661e+12 | M23: 1.205661e+12 | N23: 1.8303333e+11 | O23: 7.6871282e+10 | P23: 1.7797192e+10 | Q23: 2.025743e+10 | R23: 3.8054622e+10 | S23: 627085.34 | T23: 4.390527e+11 | U23: 4.8583886e+11 | V23: 1.3593174e+12 | W23: 4.4799334e+11 | X23: 1.6536544e+12 | Y23: 0.26550451 | Z23: 0.2937971
A24: 2023 | B24: economia_total | C24: economia_total | D24: 4.2 | E24: 2.5188768e+12 | F24: 1.1437588e+12 | G24: 1.0947039e+12 | J24: 8.5762171e+10 | K24: 6.1232644e+11 | L24: 1.2847424e+12 | M24: 1.2847424e+12 | N24: 1.8984186e+11 | O24: 1.0009763e+11 | P24: 1.5278812e+10 | Q24: 2.6551542e+10 | R24: 4.1830353e+10 | S24: 664124.7 | T24: 3.9661525e+11 | U24: 4.4567017e+11 | V24: 1.375118e+12 | W24: 4.7320105e+11 | X24: 1.7579435e+12 | Y24: 0.2256132 | Z24: 0.25351792
A25: 2024 | B25: economia_total | C25: economia_total | D25: 4.2 | E25: 2.7235721e+12 | F25: 1.257043e+12 | G25: 1.204248e+12 | J25: 9.2718688e+10 | K25: 6.7234629e+11 | L25: 1.3954387e+12 | M25: 1.3954387e+12 | N25: 1.6743766e+11 | O25: 8.820956e+10 | P25: 1.5575384e+10 | Q25: 2.4083777e+10 | R25: 3.9659161e+10 | S25: 680610.4 | T25: 4.3918297e+11 | U25: 4.9197797e+11 | V25: 1.4665292e+12 | W25: 5.0925607e+11 | X25: 1.9046948e+12 | Y25: 0.23057919 | Z25: 0.25829754

Sheet resultados-industrial-corriente
A1: anno | B1: ambito | C1: seccion | D1: rotacion | E1: vbp_pp | F1: vab_pp | G1: vab_pp_total | H1: vab_pb_estimado | I1: vab_bcu_corriente | J1: vab_eaae_bcu_pct | K1: consumo_capital_fijo | L1: costo_laboral | M1: stock_capital | N1: stock_capital_imputado | O1: fbcf | P1: fbkf_maq_eq | Q1: adquisiciones_importadas | R1: adquisiciones_origen_importado | S1: importaciones_maquinaria | T1: puestos_trabajo | U1: ganancia_pb | V1: ganancia_pp | W1: consumo_intermedio | X1: capital_circulante_adelantado | Y1: capital_total_adelantado | Z1: tasa_ganancia_pb | AA1: tasa_ganancia_pp | AB1: vab_pp_participacion_total
A2: 2001 | B2: rama_industrial | C2: C | D2: 6.6 | E2: 89240215000 | F2: 32030854000 | G2: 105965497000 | H2: 2.6506273e+10 | K2: 3127411000 | L2: 11462459000 | M2: 28622363000 | N2: 28622363000 | O2: 3539644000 | P2: 2057120000 | Q2: 1075519000 | T2: 113817 | U2: 1.1916403e+10 | V2: 17440984000 | W2: 57209361000 | X2: 1.0404821e+10 | Y2: 3.9027184e+10 | Z2: 0.30533596 | AA2: 0.44689322 | AB2: 0.30227626
A3: 2002 | B3: rama_industrial | C3: C | D3: 6.6 | E3: 104934883446 | F3: 39381506784 | G3: 106353797467 | H3: 3.2589108e+10 | K3: 3758469943 | L3: 9421078355 | N3: 3.808799e+10 | T3: 76575 | U3: 1.940956e+10 | V3: 26201958486 | W3: 65553376662 | X3: 1.1359766e+10 | Y3: 4.9447756e+10 | Z3: 0.3925266 | AA3: 0.52989176 | AB3: 0.37028774
A4: 2003 | B4: rama_industrial | C4: C | D4: 6.6 | E4: 139349946300 | F4: 41497361974 | G4: 117480701268 | H4: 3.4340027e+10 | K4: 4714590576 | L4: 10878789626 | M4: 48103564060 | N4: 48103564060 | O4: 6899547696 | P4: 5558448986 | Q4: 5256351292 | T4: 83356 | U4: 1.8746647e+10 | V4: 25903981772 | W4: 97852584326 | X4: 1.6474451e+10 | Y4: 6.4578015e+10 | Z4: 0.29029457 | AA4: 0.40112695 | AB4: 0.35322705
A5: 2004 | B5: rama_industrial | C5: C | D5: 6.6 | E5: 179010449525 | F5: 52621053735 | G5: 137248675768 | H5: 4.3545139e+10 | K5: 5136920717 | L5: 12139435357 | M5: 50525577181 | N5: 50525577181 | O5: 6396127195 | P5: 3154522472 | Q5: 1599697016 | R5: 1743085329 | S5: 3342782345 | T5: 88653 | U5: 2.6268783e+10 | V5: 35344697661 | W5: 126389395790 | X5: 2.0989217e+10 | Y5: 7.1514794e+10 | Z5: 0.36731957 | AA5: 0.49422918 | AB5: 0.38339935
A6: 2005 | B6: rama_industrial | C6: C | D6: 6.6 | E6: 184862461743 | F6: 53991760706 | G6: 152188634950 | H6: 4.4679431e+10 | I6: 6.3125725e+10 | J6: 85.530519 | K6: 5058292667 | L6: 14615233399 | M6: 52418214093 | N6: 52418214093 | O6: 6464007473 | P6: 2747259075 | Q6: 2116008436 | R6: 2111494326 | S6: 4227502762 | T6: 102414 | U6: 2.5005905e+10 | V6: 34318234640 | W6: 130870701037 | X6: 2.2043323e+10 | Y6: 7.4461537e+10 | Z6: 0.33582311 | AA6: 0.46088539 | AB6: 0.35476868
A7: 2006 | B7: rama_industrial | C7: C | D7: 6.6 | E7: 1.850396e+11 | F7: 5.4017528e+10 | G7: 1.3131015e+11 | H7: 4.4700754e+10 | I7: 6.8549418e+10 | J7: 78.800856 | K7: 4.2569136e+09 | L7: 1.3982311e+10 | M7: 5.7185677e+10 | N7: 5.7185677e+10 | O7: 6.5161369e+09 | P7: 4.2278276e+09 | Q7: 2.1827562e+09 | R7: 1.4258711e+09 | S7: 3.6086273e+09 | T7: 63928.853 | U7: 2.6461529e+10 | V7: 3.5778303e+10 | W7: 1.3102207e+11 | X7: 2.1970361e+10 | Y7: 7.9156038e+10 | Z7: 0.33429578 | AA7: 0.45199715 | AB7: 0.41137358
A8: 2007 | B8: rama_industrial | C8: C | D8: 6.6 | E8: 2.35394e+11 | F8: 7.0661648e+10 | G8: 1.968987e+11 | H8: 5.8474148e+10 | I8: 7.5470434e+10 | J8: 93.628251 | K8: 5.9348309e+09 | L8: 1.9975832e+10 | M8: 8.8288213e+10 | N8: 8.8288213e+10 | O8: 1.735929e+10 | P8: 5.9547781e+09 | Q8: 2.0501427e+09 | R8: 2.5603315e+09 | S8: 4.6104742e+09 | T8: 100576.01 | U8: 3.2563485e+10 | V8: 4.4750985e+10 | W8: 1.6473235e+11 | X8: 2.7986089e+10 | Y8: 1.162743e+11 | Z8: 0.28005746 | AA8: 0.38487425 | AB8: 0.3588731
A9: 2008 | B9: rama_industrial | C9: C | D9: 6.6 | E9: 2.8499569e+11 | F9: 8.0292211e+10 | G9: 2.0589024e+11 | H9: 6.6443662e+10 | I9: 9.5084731e+10 | J9: 84.442802 | K9: 8.098413e+09 | L9: 2.4291156e+10 | M9: 1.0797121e+11 | N9: 1.0797121e+11 | O9: 1.7442926e+10 | P9: 1.0194336e+10 | Q9: 3.6551334e+09 | R9: 3.7460905e+09 | S9: 7.4012239e+09 | T9: 103902.69 | U9: 3.4054093e+10 | V9: 4.7902642e+10 | W9: 2.0470348e+11 | X9: 3.4696157e+10 | Y9: 1.4266737e+11 | Z9: 0.23869574 | AA9: 0.33576453 | AB9: 0.3899758
A10: 2009 | B10: rama_industrial | C10: C | D10: 6.6 | E10: 2.6234716e+11 | F10: 7.8234884e+10 | G10: 2.346524e+11 | H10: 6.4741176e+10 | I10: 1.0588238e+11 | J10: 73.888485 | K10: 7.8032167e+09 | L10: 2.9743371e+10 | M10: 9.3192118e+10 | N10: 9.3192118e+10 | O10: 7.9610854e+09 | P10: 5.8014096e+09 | Q10: 2.4158472e+09 | R10: 1.4778565e+09 | S10: 3.8937037e+09 | T10: 104036.65 | U10: 2.7194589e+10 | V10: 4.0688297e+10 | W10: 1.8411228e+11 | X10: 3.2402371e+10 | Y10: 1.2559449e+11 | Z10: 0.21652693 | AA10: 0.32396562 | AB10: 0.33340755
A11: 2010 | B11: rama_industrial | C11: C | D11: 6.6 | E11: 2.9861469e+11 | F11: 9.5564091e+10 | G11: 3.0830526e+11 | H11: 7.9081496e+10 | I11: 1.0931947e+11 | J11: 87.417261 | K11: 8.1548456e+09 | L11: 3.413185e+10 | M11: 9.973781e+10 | N11: 9.973781e+10 | O11: 1.0581329e+10 | P11: 6.5272666e+09 | Q11: 2.6329602e+09 | R11: 1.8229898e+09 | S11: 4.45595e+09 | T11: 112274.19 | U11: 3.67948e+10 | V11: 5.3277395e+10 | W11: 2.0305059e+11 | X11: 3.5936734e+10 | Y11: 1.3567454e+11 | Z11: 0.271199 | AA11: 0.39268527 | AB11: 0.30996581
A12: 2011 | B12: rama_industrial | C12: C | D12: 6.6 | E12: 3.2272011e+11 | F12: 9.770659e+10 | G12: 3.2970912e+11 | H12: 8.0854464e+10 | I12: 1.1795667e+11 | J12: 82.832609 | K12: 8.1848116e+09 | L12: 3.8240757e+10 | N12: 1.2215015e+11 | T12: 109399.62 | U12: 3.4428895e+10 | V12: 5.1281022e+10 | W12: 2.2501352e+11 | X12: 3.9887012e+10 | Y12: 1.6203716e+11 | Z12: 0.21247531 | AA12: 0.31647692 | AB12: 0.29634179
A13: 2012 | B13: rama_industrial | C13: C | D13: 6.6 | E13: 3.6649548e+11 | F13: 9.9292175e+10 | G13: 3.8080398e+11 | H13: 8.2166571e+10 | I13: 1.2674819e+11 | J13: 78.33814 | K13: 9.2006411e+09 | L13: 4.3787875e+10 | M13: 1.1807022e+11 | N13: 1.1807022e+11 | O13: 1.7144628e+10 | P13: 1.186762e+10 | Q13: 5.9741866e+09 | R13: 3.1526135e+09 | S13: 9.1268001e+09 | T13: 110138.75 | U13: 2.9178056e+10 | V13: 4.6303659e+10 | W13: 2.672033e+11 | X13: 4.7119875e+10 | Y13: 1.651901e+11 | Z13: 0.1766332 | AA13: 0.28030529 | AB13: 0.26074353
A14: 2013 | B14: rama_industrial | C14: C | D14: 6.6 | E14: 3.9349558e+11 | F14: 1.1189604e+11 | G14: 4.4643853e+11 | H14: 9.2596558e+10 | I14: 1.3275353e+11 | J14: 84.288555 | K14: 9.6344566e+09 | L14: 5.0186679e+10 | M14: 1.3030327e+11 | N14: 1.3030327e+11 | O14: 2.8790673e+10 | P14: 1.8295653e+10 | Q14: 2.4797926e+09 | R14: 1.6298812e+10 | S14: 1.8778604e+10 | T14: 109797.75 | U14: 3.2775422e+10 | V14: 5.2074899e+10 | W14: 2.8159954e+11 | X14: 5.027064e+10 | Y14: 1.8057391e+11 | Z14: 0.18150696 | AA14: 0.28838551 | AB14: 0.25064153
A15: 2014 | B15: rama_industrial | C15: C | D15: 6.6 | E15: 4.5364092e+11 | F15: 1.3078013e+11 | G15: 5.2532185e+11 | H15: 1.0822358e+11 | I15: 1.6156765e+11 | J15: 80.944503 | K15: 1.2235322e+10 | L15: 5.6837646e+10 | M15: 1.9842942e+11 | N15: 1.9842942e+11 | O15: 7.8176629e+10 | P15: 5.2611955e+10 | Q15: 2.2171191e+09 | R15: 4.8143911e+10 | S15: 5.036103e+10 | T15: 107700.43 | U15: 3.9150616e+10 | V15: 6.1707164e+10 | W15: 3.2286079e+11 | X15: 5.7530066e+10 | Y15: 2.5595948e+11 | Z15: 0.1529563 | AA15: 0.24108176 | AB15: 0.24895239
A16: 2015 | B16: rama_industrial | C16: C | D16: 6.6 | E16: 4.7809497e+11 | F16: 1.5193967e+11 | G16: 6.0720755e+11 | H16: 1.257336e+11 | I16: 1.9279305e+11 | J16: 78.809726 | K16: 1.4988601e+10 | L16: 6.1103873e+10 | M16: 2.0781379e+11 | N16: 2.0781379e+11 | O16: 2.6806672e+10 | P16: 1.6410901e+10 | Q16: 1.3932607e+09 | R16: 6.2827403e+09 | S16: 7.676001e+09 | T16: 103791.21 | U16: 4.9641122e+10 | V16: 7.58472e+10 | W16: 3.2615529e+11 | X16: 5.8675631e+10 | Y16: 2.6648942e+11 | Z16: 0.18627802 | AA16: 0.28461617 | AB16: 0.25022692
A17: 2016 | B17: rama_industrial | C17: C | D17: 6.6 | E17: 4.8828286e+11 | F17: 1.5538284e+11 | G17: 6.5167676e+11 | H17: 1.2858289e+11 | I17: 2.0370414e+11 | J17: 76.278685 | K17: 1.6145912e+10 | L17: 6.5854042e+10 | M17: 2.188245e+11 | N17: 2.188245e+11 | O17: 1.7409372e+10 | P17: 7.9574019e+09 | Q17: 1.6947138e+09 | R17: 4.3099059e+09 | S17: 6.0046197e+09 | T17: 100240.45 | U17: 4.658294e+10 | V17: 7.3382885e+10 | W17: 3.3290002e+11 | X17: 6.0417282e+10 | Y17: 2.7924178e+11 | Z17: 0.16681938 | AA17: 0.26279336 | AB17: 0.23843545
A18: 2017 | B18: rama_industrial | C18: C | D18: 6.6 | E18: 4.8414153e+11 | F18: 1.6442457e+11 | G18: 7.1889963e+11 | H18: 1.3606514e+11 | I18: 1.9979616e+11 | J18: 82.29616 | K18: 1.5918677e+10 | L18: 7.0584977e+10 | M18: 2.097731e+11 | N18: 2.097731e+11 | O18: 1.703624e+10 | P18: 8.4810375e+09 | Q18: 1.7263034e+09 | R18: 2.8971526e+09 | S18: 4.623456e+09 | T18: 97466.997 | U18: 4.9561483e+10 | V18: 7.7920918e+10 | W18: 3.1971695e+11 | X18: 5.9136656e+10 | Y18: 2.6890975e+11 | Z18: 0.18430526 | AA18: 0.28976605 | AB18: 0.22871701
A19: 2018 | B19: rama_industrial | C19: C | D19: 6.6 | E19: 5.7003685e+11 | F19: 1.9788533e+11 | G19: 7.8992151e+11 | H19: 1.6749072e+11 | I19: 2.133637e+11 | J19: 92.745545 | K19: 1.6454136e+10 | L19: 7.6120685e+10 | M19: 2.3094465e+11 | N19: 2.3094465e+11 | O19: 2.1403884e+10 | P19: 9.3987612e+09 | Q19: 2.3443011e+09 | R19: 3.8755945e+09 | S19: 6.2198956e+09 | T19: 94566.086 | U19: 7.4915904e+10 | V19: 1.0531051e+11 | W19: 3.7215152e+11 | X19: 6.7920031e+10 | Y19: 2.9886468e+11 | Z19: 0.25066831 | AA19: 0.35236853 | AB19: 0.25051265
A20: 2019 | B20: rama_industrial | C20: C | D20: 6.6 | E20: 601651424497 | F20: 190772526038 | G20: 824315284444 | H20: 158331064110 | I20: 2.3193207e+11 | J20: 82.253622 | K20: 1.8470371e+10 | L20: 80999471228 | M20: 259048160897 | N20: 259048160897 | O20: 30759048024 | P20: 10582877554 | Q20: 10715087960 | R20: 3917218825 | S20: 14632306785 | T20: 90481 | U20: 5.8861222e+10 | V20: 9.1302684e+10 | W20: 410878898459 | X20: 7.4527026e+10 | Y20: 3.3357519e+11 | Z20: 0.17645564 | AA20: 0.27370946 | AB20: 0.2314315
A21: 2020 | B21: rama_industrial | C21: C | D21: 6.6 | E21: 6.0081753e+11 | F21: 1.8296311e+11 | G21: 8.3832609e+11 | H21: 1.5140069e+11 | K21: 1.9749526e+10 | L21: 7.8278216e+10 | M21: 2.963226e+11 | N21: 2.963226e+11 | O21: 4.094156e+10 | P21: 9.808505e+09 | Q21: 3.2754489e+09 | R21: 2.7093516e+09 | S21: 5.9848005e+09 | T21: 84764.465 | U21: 5.3372949e+10 | V21: 8.4935368e+10 | W21: 4.1785442e+11 | X21: 7.5171611e+10 | Y21: 3.7149421e+11 | Z21: 0.14367101 | AA21: 0.22863174 | AB21: 0.21824814
A22: 2021 | B22: rama_industrial | C22: C | D22: 6.6 | E22: 7.404514e+11 | F22: 2.2497468e+11 | G22: 1.0161528e+12 | H22: 2.1404231e+11 | K22: 2.1739334e+10 | L22: 8.4122099e+10 | M22: 3.7719399e+11 | N22: 3.7719399e+11 | O22: 8.3942984e+10 | P22: 1.8626904e+10 | Q22: 3.3123653e+09 | R22: 6.0037884e+09 | S22: 9.3161537e+09 | T22: 86333.094 | U22: 1.0818088e+11 | V22: 1.1911325e+11 | W22: 5.1547672e+11 | X22: 9.0848306e+10 | Y22: 4.6804229e+11 | Z22: 0.23113483 | AA22: 0.25449249 | AB22: 0.22139848
A23: 2022 | B23: rama_industrial | C23: C | D23: 6.6 | E23: 8.8744811e+11 | F23: 2.6553605e+11 | G23: 1.0825796e+12 | H23: 2.2530924e+11 | K23: 2.1523442e+10 | L23: 9.5609914e+10 | M23: 3.9260348e+11 | N23: 3.9260348e+11 | O23: 6.9687014e+10 | P23: 1.724295e+10 | Q23: 4.1405769e+09 | R23: 5.18038e+09 | S23: 9.320957e+09 | T23: 89467.506 | U23: 1.0817588e+11 | V23: 1.4840269e+11 | W23: 6.2191206e+11 | X23: 1.0871545e+11 | Y23: 5.0131893e+11 | Z23: 0.21578256 | AA23: 0.29602452 | AB23: 0.24528084
A24: 2023 | B24: rama_industrial | C24: C | D24: 6.6 | E24: 8.095925e+11 | F24: 2.4012716e+11 | G24: 1.1437588e+12 | H24: 1.9843867e+11 | K24: 2.4684324e+10 | L24: 1.046198e+11 | M24: 4.0246279e+11 | N24: 4.0246279e+11 | O24: 5.6457789e+10 | P24: 3.8688156e+10 | Q24: 3.0484519e+09 | R24: 4.9906452e+09 | S24: 8.0390971e+09 | T24: 89501.941 | U24: 6.9134549e+10 | V24: 1.1082304e+11 | W24: 5.6946534e+11 | X24: 1.0213411e+11 | Y24: 5.045969e+11 | Z24: 0.13700946 | AA24: 0.21962686 | AB24: 0.20994563
A25: 2024 | B25: rama_industrial | C25: C | D25: 6.6 | E25: 8.5807161e+11 | F25: 2.6397033e+11 | G25: 1.257043e+12 | H25: 2.1860072e+11 | K25: 2.7515759e+10 | L25: 1.1292427e+11 | M25: 4.3696596e+11 | N25: 4.3696596e+11 | O25: 4.3801058e+10 | P25: 2.2430814e+10 | Q25: 2.2133014e+09 | R25: 6.1907634e+09 | S25: 8.4040648e+09 | T25: 90863.927 | U25: 7.8160693e+10 | V25: 1.235303e+11 | W25: 5.9410128e+11 | X25: 1.0712508e+11 | Y25: 5.4409104e+11 | Z25: 0.1436537 | AA25: 0.22703976 | AB25: 0.20999308

Sheet resultados-total-constante
A1: anno | B1: ambito | C1: seccion | D1: rotacion | E1: gdp_price_index_base_2005 | F1: ipc_index_2005 | G1: vbp_pp | H1: vab_pp | I1: vab_pb_estimado | J1: consumo_capital_fijo | K1: costo_laboral | L1: stock_capital | M1: stock_capital_imputado | N1: fbcf | O1: fbkf_maq_eq | P1: adquisiciones_importadas | Q1: adquisiciones_origen_importado | R1: importaciones_maquinaria | S1: puestos_trabajo | T1: ganancia_pb | U1: ganancia_pp | V1: consumo_intermedio | W1: capital_circulante_adelantado | X1: capital_total_adelantado | Y1: tasa_ganancia_pb | Z1: tasa_ganancia_pp | AA1: productividad_trabajo
A2: 2001 | B2: economia_total | C2: economia_total | D2: 4.2 | E2: 0.68734765 | F2: 0.64312533 | G2: 3.2704756e+11 | H2: 1.5416579e+11 | I2: 1.4297623e+11 | J2: 1.3783918e+10 | K2: 7.6067651e+10 | L2: 1.8018755e+11 | M2: 1.8018755e+11 | N2: 2.2673426e+10 | O2: 7.6188345e+09 | P2: 4.6212582e+09 | S2: 538624 | T2: 5.3124665e+10 | U2: 6.4314225e+10 | V2: 1.7288177e+11 | W2: 5.9273671e+10 | X2: 2.3946122e+11 | Y2: 0.22185081 | Z2: 0.26857887 | AA2: 286221.55
A3: 2002 | B3: economia_total | C3: economia_total | D3: 4.2 | E3: 0.77406533 | F3: 0.73294995 | G3: 2.9492761e+11 | H3: 1.3739641e+11 | I3: 1.2658103e+11 | J3: 1.4422401e+10 | K3: 5.8152455e+10 | M3: 1.5864287e+11 | S3: 339997 | T3: 5.4006171e+10 | U3: 6.4821553e+10 | V3: 1.575312e+11 | W3: 5.1353251e+10 | X3: 2.0999612e+11 | Y3: 0.25717699 | Z3: 0.30867976 | AA3: 404110.65
A4: 2003 | B4: economia_total | C4: economia_total | D4: 4.2 | E4: 0.9021084 | F4: 0.87495841 | G4: 3.134441e+11 | H4: 1.3022903e+11 | I4: 1.2021766e+11 | J4: 1.7057839e+10 | K4: 5.0842739e+10 | L4: 1.4284146e+11 | M4: 1.4284146e+11 | N4: 1.6560124e+10 | O4: 1.0596039e+10 | P4: 6.3913292e+09 | S4: 345219 | T4: 5.2317083e+10 | U4: 6.2328452e+10 | V4: 1.8321507e+11 | W4: 5.572805e+10 | X4: 1.9856951e+11 | Y4: 0.26346988 | Z4: 0.31388733 | AA4: 377235.99
A5: 2004 | B5: economia_total | C5: economia_total | D5: 4.2 | E5: 0.99326696 | F5: 0.95508769 | G5: 3.4480858e+11 | H5: 1.3817904e+11 | I5: 1.26808e+11 | J5: 1.74593e+10 | K5: 5.0265006e+10 | L5: 1.8860914e+11 | M5: 1.8860914e+11 | N5: 2.109874e+10 | O5: 1.1156781e+10 | P5: 2.3887125e+09 | Q5: 3.8152357e+09 | R5: 6.2039482e+09 | S5: 348339 | T5: 5.9083698e+10 | U5: 7.0454735e+10 | V5: 2.0662954e+11 | W5: 6.1165368e+10 | X5: 2.497745e+11 | Y5: 0.23654815 | Z5: 0.28207337 | AA5: 396679.79
A6: 2005 | B6: economia_total | C6: economia_total | D6: 4.2 | E6: 1 | F6: 1 | G6: 370267989847 | H6: 152188634950 | I6: 1.4021824e+11 | J6: 17296133580 | K6: 56739334938 | L6: 239076254150 | M6: 239076254150 | N6: 22308747111 | O6: 6242564037 | P6: 3786737908 | Q6: 3985038215 | R6: 7771776123 | S6: 391484 | T6: 6.6182775e+10 | U6: 78153166432 | V6: 218079354897 | W6: 6.5433021e+10 | X6: 3.0450928e+11 | Y6: 0.21734239 | Z6: 0.25665283 | AA6: 388748.03
A7: 2006 | B7: economia_total | C7: economia_total | D7: 4.2 | E7: 1.0653333 | F7: 1.0639703 | G7: 3.158099e+11 | H7: 1.2325734e+11 | I7: 1.1303768e+11 | J7: 1.6066781e+10 | K7: 4.4514641e+10 | L7: 2.1747859e+11 | M7: 2.1747859e+11 | N7: 1.797627e+10 | O7: 9.4458134e+09 | P7: 3.0337659e+09 | Q7: 2.7518275e+09 | R7: 5.7855934e+09 | S7: 205952.96 | T7: 5.2456263e+10 | U7: 6.2675918e+10 | V7: 1.9255256e+11 | W7: 5.6444571e+10 | X7: 2.7392317e+11 | Y7: 0.19149992 | Z7: 0.22880839 | AA7: 598473.26
A8: 2007 | B8: economia_total | C8: economia_total | D8: 4.2 | E8: 1.1656608 | F8: 1.1503256 | G8: 4.1295813e+11 | H8: 1.6891595e+11 | I8: 1.5560806e+11 | J8: 1.8831356e+10 | K8: 6.6038347e+10 | L8: 2.5046358e+11 | M8: 2.5046358e+11 | N8: 3.3336678e+10 | O8: 1.4894935e+10 | P8: 3.4720494e+09 | Q8: 4.6189807e+09 | R8: 8.0910301e+09 | S8: 384437.89 | T8: 7.0738361e+10 | U8: 8.4046242e+10 | V8: 2.4404219e+11 | W8: 7.3828699e+10 | X8: 3.2429228e+11 | Y8: 0.2181315 | Z8: 0.25916818 | AA8: 439384.22
A9: 2008 | B9: economia_total | C9: economia_total | D9: 4.2 | E9: 1.2591881 | F9: 1.2409106 | G9: 4.4405146e+11 | H9: 1.6351032e+11 | I9: 1.495202e+11 | J9: 2.0073769e+10 | K9: 7.5925199e+10 | L9: 2.6481436e+11 | M9: 2.6481436e+11 | N9: 3.4395351e+10 | O9: 2.1378241e+10 | P9: 7.1584442e+09 | Q9: 5.8538721e+09 | R9: 1.3012316e+10 | S9: 436444.3 | T9: 5.3521235e+10 | U9: 6.751135e+10 | V9: 2.8054115e+11 | W9: 8.4872939e+10 | X9: 3.496873e+11 | Y9: 0.15305456 | Z9: 0.19306206 | AA9: 374641.89
A10: 2009 | B10: economia_total | C10: economia_total | D10: 4.2 | E10: 1.3567442 | F10: 1.328549 | G10: 4.2198471e+11 | H10: 1.7295258e+11 | I10: 1.6000175e+11 | J10: 1.9670768e+10 | K10: 8.814798e+10 | L10: 2.5531268e+11 | M10: 2.5531268e+11 | N10: 2.763626e+10 | O10: 1.5906829e+10 | P10: 7.134275e+09 | Q10: 3.1132811e+09 | R10: 1.0247556e+10 | S10: 477461.01 | T10: 5.2183006e+10 | U10: 6.5133831e+10 | V10: 2.4903213e+11 | W10: 8.0280978e+10 | X10: 3.3559366e+11 | Y10: 0.15549461 | Z10: 0.1940854 | AA10: 362233.93
A11: 2010 | B11: economia_total | C11: economia_total | D11: 4.2 | E11: 1.42332 | F11: 1.4175182 | G11: 4.9842966e+11 | H11: 2.1660995e+11 | I11: 2.0110387e+11 | J11: 2.2328273e+10 | K11: 1.0206976e+11 | L11: 3.1552723e+11 | M11: 3.1552723e+11 | N11: 4.2911503e+10 | O11: 2.4639826e+10 | P11: 6.5659138e+09 | Q11: 1.0377546e+10 | R11: 1.6943459e+10 | S11: 522282.77 | T11: 7.670583e+10 | U11: 9.2211911e+10 | V11: 2.8181972e+11 | W11: 9.1402257e+10 | X11: 4.0692949e+11 | Y11: 0.18849907 | Z11: 0.22660415 | AA11: 414736.92
A12: 2011 | B12: economia_total | C12: economia_total | D12: 4.2 | E12: 1.5515565 | F12: 1.5322466 | G12: 4.972417e+11 | H12: 2.1250217e+11 | I12: 1.975408e+11 | J12: 2.0298011e+10 | K12: 1.1288692e+11 | M12: 2.9988102e+11 | S12: 542457.77 | T12: 6.4355875e+10 | U12: 7.9317244e+10 | V12: 2.8473953e+11 | W12: 9.4672964e+10 | X12: 3.9455398e+11 | Y12: 0.16311044 | Z12: 0.20103014 | AA12: 391739.57
A13: 2012 | B13: economia_total | C13: economia_total | D13: 4.2 | E13: 1.6843317 | F13: 1.6563376 | G13: 5.3951135e+11 | H13: 2.2608609e+11 | I13: 2.1042937e+11 | J13: 2.0847323e+10 | K13: 1.2339264e+11 | L13: 2.9108698e+11 | M13: 2.9108698e+11 | N13: 4.1798522e+10 | O13: 2.3697698e+10 | P13: 9.7477609e+09 | Q13: 6.0535497e+09 | R13: 1.5801311e+10 | S13: 564843.8 | T13: 6.6189411e+10 | U13: 8.1846134e+10 | V13: 3.1342526e+11 | W13: 1.0400426e+11 | X13: 3.9509125e+11 | Y13: 0.16752943 | Z13: 0.20715755 | AA13: 400263.04
A14: 2013 | B14: economia_total | C14: economia_total | D14: 4.2 | E14: 1.8216676 | F14: 1.7983936 | G14: 5.6521321e+11 | H14: 2.4507135e+11 | I14: 2.2871426e+11 | J14: 2.0311803e+10 | K14: 1.3329525e+11 | L14: 3.0295141e+11 | M14: 3.0295141e+11 | N14: 5.2497097e+10 | O14: 2.9095723e+10 | P14: 7.7213247e+09 | Q14: 1.4040362e+10 | R14: 2.1761687e+10 | S14: 592299.21 | T14: 7.5107214e+10 | U14: 9.14643e+10 | V14: 3.2014186e+11 | W14: 1.0796122e+11 | X14: 4.1091262e+11 | Y14: 0.18278147 | Z14: 0.2225882 | AA14: 413762.75
A15: 2014 | B15: economia_total | C15: economia_total | D15: 4.2 | E15: 1.9923987 | F15: 1.9580343 | G15: 6.0194476e+11 | H15: 2.6366301e+11 | I15: 2.4617293e+11 | J15: 2.2243945e+10 | K15: 1.4347381e+11 | L15: 3.3949755e+11 | M15: 3.3949755e+11 | N15: 7.9917724e+10 | O15: 5.3158212e+10 | P15: 8.3869565e+09 | Q15: 3.039684e+10 | R15: 3.8783796e+10 | S15: 616859.35 | T15: 8.0455183e+10 | U15: 9.7945258e+10 | V15: 3.3828175e+11 | W15: 1.147037e+11 | X15: 4.5420126e+11 | Y15: 0.17713554 | Z15: 0.21564286 | AA15: 427428.09
A16: 2015 | B16: economia_total | C16: economia_total | D16: 4.2 | E16: 2.172039 | F16: 2.1277031 | G16: 6.1638617e+11 | H16: 2.7955646e+11 | I16: 2.6109828e+11 | J16: 2.4580848e+10 | K16: 1.4949453e+11 | L16: 3.3888041e+11 | M16: 3.3888041e+11 | N16: 4.8445195e+10 | O16: 2.7033155e+10 | P16: 5.7529456e+09 | Q16: 7.3309173e+09 | R16: 1.3083863e+10 | S16: 618979.93 | T16: 8.7022904e+10 | U16: 1.0548108e+11 | V16: 3.3682971e+11 | W16: 1.1579149e+11 | X16: 4.546719e+11 | Y16: 0.19139715 | Z16: 0.23199385 | AA16: 451640.59
A17: 2016 | B17: economia_total | C17: economia_total | D17: 4.2 | E17: 2.3315859 | F17: 2.3328264 | G17: 6.0156812e+11 | H17: 2.7949935e+11 | I17: 2.6157381e+11 | J17: 2.3525872e+10 | K17: 1.5043453e+11 | L17: 3.4569666e+11 | M17: 3.4569666e+11 | N17: 4.4598129e+10 | O17: 2.1169704e+10 | P17: 4.1731826e+09 | Q17: 6.8251651e+09 | R17: 1.0998348e+10 | S17: 614484.09 | T17: 8.7613407e+10 | U17: 1.0553895e+11 | V17: 3.2206877e+11 | W17: 1.1250079e+11 | X17: 4.5819744e+11 | Y17: 0.19121322 | Z17: 0.23033509 | AA17: 454852.06
A18: 2017 | B18: economia_total | C18: economia_total | D18: 4.2 | E18: 2.4413194 | F18: 2.4779241 | G18: 6.0946661e+11 | H18: 2.9447177e+11 | I18: 2.7615936e+11 | J18: 2.4665349e+10 | K18: 1.5542522e+11 | L18: 3.4488156e+11 | M18: 3.4488156e+11 | N18: 3.9149523e+10 | O18: 1.8395565e+10 | P18: 4.2182827e+09 | Q18: 6.4011261e+09 | R18: 1.0619409e+10 | S18: 619826.2 | T18: 9.6068796e+10 | U18: 1.1438121e+11 | V18: 3.1499484e+11 | W18: 1.1200477e+11 | X18: 4.5688633e+11 | Y18: 0.21026848 | Z18: 0.25034937 | AA18: 475087.64
A19: 2018 | B19: economia_total | C19: economia_total | D19: 4.2 | E19: 2.5769357 | F19: 2.6663657 | G19: 6.4366514e+11 | H19: 3.065352e+11 | I19: 2.8925578e+11 | J19: 2.4113812e+10 | K19: 1.584893e+11 | L19: 3.4860407e+11 | M19: 3.4860407e+11 | N19: 3.7889269e+10 | O19: 1.9223632e+10 | P19: 4.8861422e+09 | Q19: 5.3275962e+09 | R19: 1.0213738e+10 | S19: 620093.7 | T19: 1.0665267e+11 | U19: 1.2393209e+11 | V19: 3.3712994e+11 | W19: 1.1800458e+11 | X19: 4.6660865e+11 | Y19: 0.22856985 | Z19: 0.26560178 | AA19: 494336.91
A20: 2019 | B20: economia_total | C20: economia_total | D20: 4.2 | E20: 2.774533 | F20: 2.8765268 | G20: 6.4533497e+11 | H20: 2.9710055e+11 | I20: 2.7973748e+11 | J20: 2.4769738e+10 | K20: 1.5861653e+11 | L20: 3.5897831e+11 | M20: 3.5897831e+11 | N20: 4.6453406e+10 | O20: 1.6185746e+10 | P20: 5.9461545e+09 | Q20: 5.3478589e+09 | R20: 1.1294013e+10 | S20: 611937 | T20: 9.6351206e+10 | U20: 1.1371428e+11 | V20: 3.4823442e+11 | W20: 1.206788e+11 | X20: 4.7965711e+11 | Y20: 0.20087518 | Z20: 0.23707411 | AA20: 485508.4
A21: 2020 | B21: economia_total | C21: economia_total | D21: 4.2 | E21: 3.0720571 | F21: 3.1471888 | G21: 5.8758483e+11 | H21: 2.7288754e+11 | I21: 2.5564845e+11 | J21: 2.3590077e+10 | K21: 1.4164023e+11 | L21: 3.3949835e+11 | M21: 3.3949835e+11 | N21: 3.8075007e+10 | O21: 1.4733285e+10 | P21: 3.6157275e+09 | Q21: 4.2498517e+09 | R21: 7.8655791e+09 | S21: 570247.16 | T21: 9.0418149e+10 | U21: 1.0765723e+11 | V21: 3.1469729e+11 | W21: 1.0865179e+11 | X21: 4.4815014e+11 | Y21: 0.20175861 | Z21: 0.24022581 | AA21: 478542.57
A22: 2021 | B22: economia_total | C22: economia_total | D22: 4.2 | E22: 3.4122569 | F22: 3.3976997 | G22: 6.3701329e+11 | H22: 2.9779492e+11 | I22: 2.9273856e+11 | J22: 2.1627784e+10 | K22: 1.3838769e+11 | L22: 3.4387528e+11 | M22: 3.4387528e+11 | N22: 5.4896667e+10 | O22: 1.9309715e+10 | P22: 5.7255371e+09 | Q22: 6.4139761e+09 | R22: 1.2139513e+10 | S22: 602974.92 | T22: 1.3272308e+11 | U22: 1.3777944e+11 | V22: 3.3921837e+11 | W22: 1.1371573e+11 | X22: 4.5759101e+11 | Y22: 0.2900474 | Z22: 0.30109736 | AA22: 493876.13
A23: 2022 | B23: economia_total | C23: economia_total | D23: 4.2 | E23: 3.6166177 | F23: 3.7001093 | G23: 6.7518805e+11 | H23: 2.9933483e+11 | I23: 2.8639839e+11 | J23: 2.059552e+10 | K23: 1.4114574e+11 | L23: 3.3336702e+11 | M23: 3.3336702e+11 | N23: 5.060898e+10 | O23: 2.125502e+10 | P23: 4.9209491e+09 | Q23: 5.6012087e+09 | R23: 1.0522158e+10 | S23: 627085.34 | T23: 1.2465713e+11 | U23: 1.3759358e+11 | V23: 3.7585321e+11 | W23: 1.2309499e+11 | X23: 4.5646201e+11 | Y23: 0.27309421 | Z23: 0.30143489 | AA23: 477343.06
A24: 2023 | B24: economia_total | C24: economia_total | D24: 4.2 | E24: 3.7632011 | F24: 3.8887886 | G24: 6.6934418e+11 | H24: 3.0393241e+11 | I24: 2.9089699e+11 | J24: 2.2789686e+10 | K24: 1.5745943e+11 | L24: 3.4139616e+11 | M24: 3.4139616e+11 | N24: 5.0446908e+10 | O24: 2.6599065e+10 | P24: 4.0600571e+09 | Q24: 7.0555734e+09 | R24: 1.111563e+10 | S24: 664124.7 | T24: 1.1064787e+11 | U24: 1.2368329e+11 | V24: 3.6541177e+11 | W24: 1.2449314e+11 | X24: 4.658893e+11 | Y24: 0.23749819 | Z24: 0.26547785 | AA24: 457643.59
A25: 2024 | B25: economia_total | C25: economia_total | D25: 4.2 | E25: 3.9207675 | F25: 4.102324 | G25: 6.946528e+11 | H25: 3.2061145e+11 | I25: 3.0714597e+11 | J25: 2.3648096e+10 | K25: 1.63894e+11 | L25: 3.5590957e+11 | M25: 3.5590957e+11 | N25: 4.2705328e+10 | O25: 2.2498034e+10 | P25: 3.9725344e+09 | Q25: 6.142618e+09 | R25: 1.0115152e+10 | S25: 680610.4 | T25: 1.1960388e+11 | U25: 1.3306935e+11 | V25: 3.7404135e+11 | W25: 1.2807985e+11 | X25: 4.8398942e+11 | Y25: 0.24712085 | Z25: 0.27494269 | AA25: 471064.57

Sheet resultados-industrial-constante
A1: anno | B1: ambito | C1: seccion | D1: rotacion | E1: gdp_price_index_base_2005 | F1: ipc_index_2005 | G1: vbp_pp | H1: vab_pp | I1: vab_pp_total | J1: vab_pb_estimado | K1: consumo_capital_fijo | L1: costo_laboral | M1: stock_capital | N1: stock_capital_imputado | O1: fbcf | P1: fbkf_maq_eq | Q1: adquisiciones_importadas | R1: adquisiciones_origen_importado | S1: importaciones_maquinaria | T1: puestos_trabajo | U1: ganancia_pb | V1: ganancia_pp | W1: consumo_intermedio | X1: capital_circulante_adelantado | Y1: capital_total_adelantado | Z1: tasa_ganancia_pb | AA1: tasa_ganancia_pp | AB1: vab_pp_participacion_total | AC1: productividad_trabajo
A2: 2001 | B2: rama_industrial | C2: C | D2: 6.6 | E2: 0.68734765 | F2: 0.64312533 | G2: 1.2983272e+11 | H2: 4.660066e+10 | I2: 1.5416579e+11 | J2: 3.8563124e+10 | K2: 4.5499697e+09 | L2: 1.7823056e+10 | M2: 4.1641756e+10 | N2: 4.1641756e+10 | O2: 5.1497142e+09 | P2: 2.9928377e+09 | Q2: 1.564738e+09 | T2: 113817 | U2: 1.6190098e+10 | V2: 2.4227633e+10 | W2: 8.323206e+10 | X2: 1.5311381e+10 | Y2: 5.6953137e+10 | Z2: 0.28427052 | AA2: 0.42539594 | AB2: 0.30227626 | AC2: 409434.97
A3: 2002 | B3: rama_industrial | C3: C | D3: 6.6 | E3: 0.77406533 | F3: 0.73294995 | G3: 1.3556334e+11 | H3: 5.0876205e+10 | I3: 1.3739641e+11 | J3: 4.2101237e+10 | K3: 4.8554945e+09 | L3: 1.2853645e+10 | N3: 4.9205136e+10 | T3: 76575 | U3: 2.4392097e+10 | V3: 3.3167066e+10 | W3: 8.4687136e+10 | X3: 1.4778906e+10 | Y3: 6.3984042e+10 | Z3: 0.38122158 | AA3: 0.51836465 | AB3: 0.37028774 | AC3: 664397.06
A4: 2003 | B4: rama_industrial | C4: C | D4: 6.6 | E4: 0.9021084 | F4: 0.87495841 | G4: 1.544714e+11 | H4: 4.6000416e+10 | I4: 1.3022903e+11 | J4: 3.8066409e+10 | K4: 5.2261908e+09 | L4: 1.2433493e+10 | M4: 5.3323485e+10 | N4: 5.3323485e+10 | O4: 7.6482468e+09 | P4: 6.1616198e+09 | Q4: 5.8267402e+09 | T4: 83356 | U4: 2.0406725e+10 | V4: 2.8340732e+10 | W4: 1.0847098e+11 | X4: 1.831886e+10 | Y4: 7.1642345e+10 | Z4: 0.28484166 | AA4: 0.39558633 | AB4: 0.35322705 | AC4: 551854.89
A5: 2004 | B5: rama_industrial | C5: C | D5: 6.6 | E5: 0.99326696 | F5: 0.95508769 | G5: 1.802239e+11 | H5: 5.2977755e+10 | I5: 1.3817904e+11 | J5: 4.3840318e+10 | K5: 5.1717423e+09 | L5: 1.2710284e+10 | M5: 5.0868074e+10 | N5: 5.0868074e+10 | O5: 6.4394845e+09 | P5: 3.175906e+09 | Q5: 1.6105409e+09 | R5: 1.7549012e+09 | S5: 3.365442e+09 | T5: 88653 | U5: 2.5958292e+10 | V5: 3.5095729e+10 | W5: 1.2724615e+11 | X5: 2.120552e+10 | Y5: 7.2073594e+10 | Z5: 0.3601637 | AA5: 0.48694296 | AB5: 0.38339935 | AC5: 597585.59
A6: 2005 | B6: rama_industrial | C6: C | D6: 6.6 | E6: 1 | F6: 1 | G6: 184862461743 | H6: 53991760706 | I6: 152188634950 | J6: 4.4679431e+10 | K6: 5058292667 | L6: 14615233399 | M6: 52418214093 | N6: 52418214093 | O6: 6464007473 | P6: 2747259075 | Q6: 2116008436 | R6: 2111494326 | S6: 4227502762 | T6: 102414 | U6: 2.5005905e+10 | V6: 34318234640 | W6: 130870701037 | X6: 2.2043323e+10 | Y6: 7.4461537e+10 | Z6: 0.33582311 | AA6: 0.46088539 | AB6: 0.35476868 | AC6: 527191.21
A7: 2006 | B7: rama_industrial | C7: C | D7: 6.6 | E7: 1.0653333 | F7: 1.0639703 | G7: 1.7369174e+11 | H7: 5.0704813e+10 | I7: 1.2325734e+11 | J7: 4.1959405e+10 | K7: 3.9958513e+09 | L7: 1.3141636e+10 | M7: 5.367867e+10 | N7: 5.367867e+10 | O7: 6.1165239e+09 | P7: 3.968549e+09 | Q7: 2.048895e+09 | R7: 1.3384272e+09 | S7: 3.3873222e+09 | T7: 63928.853 | U7: 2.4821918e+10 | V7: 3.3567325e+10 | W7: 1.2298692e+11 | X7: 2.0625539e+10 | Y7: 7.4304209e+10 | Z7: 0.33405804 | AA7: 0.45175537 | AB7: 0.41137358 | AC7: 793144.42
A8: 2007 | B8: rama_industrial | C8: C | D8: 6.6 | E8: 1.1656608 | F8: 1.1503256 | G8: 2.0194039e+11 | H8: 6.061939e+10 | I8: 1.6891595e+11 | J8: 5.0163947e+10 | K8: 5.0913875e+09 | L8: 1.7365373e+10 | M8: 7.574091e+10 | N8: 7.574091e+10 | O8: 1.489223e+10 | P8: 5.1084998e+09 | Q8: 1.7587815e+09 | R8: 2.1964635e+09 | S8: 3.955245e+09 | T8: 100576.01 | U8: 2.7707187e+10 | V8: 3.8162629e+10 | W8: 1.41321e+11 | X8: 2.404339e+10 | Y8: 9.97843e+10 | Z8: 0.2776708 | AA8: 0.38245124 | AB8: 0.3588731 | AC8: 602722.14
A9: 2008 | B9: rama_industrial | C9: C | D9: 6.6 | E9: 1.2591881 | F9: 1.2409106 | G9: 2.2633291e+11 | H9: 6.3765068e+10 | I9: 1.6351032e+11 | J9: 5.2767069e+10 | K9: 6.4314564e+09 | L9: 1.9575267e+10 | M9: 8.5746694e+10 | N9: 8.5746694e+10 | O9: 1.3852519e+10 | P9: 8.09596e+09 | Q9: 2.90277e+09 | R9: 2.9750048e+09 | S9: 5.8777748e+09 | T9: 103902.69 | U9: 2.6760345e+10 | V9: 3.7758344e+10 | W9: 1.6256784e+11 | X9: 2.759744e+10 | Y9: 1.1334413e+11 | Z9: 0.23609819 | AA9: 0.33313011 | AB9: 0.3899758 | AC9: 613699.9
A10: 2009 | B10: rama_industrial | C10: C | D10: 6.6 | E10: 1.3567442 | F10: 1.328549 | G10: 1.9336524e+11 | H10: 5.7663696e+10 | I10: 1.7295258e+11 | J10: 4.7718042e+10 | K10: 5.7514282e+09 | L10: 2.2387861e+10 | M10: 6.8688054e+10 | N10: 6.8688054e+10 | O10: 5.8677867e+09 | P10: 4.275979e+09 | Q10: 1.780621e+09 | R10: 1.0892669e+09 | S10: 2.8698879e+09 | T10: 104036.65 | U10: 1.9578753e+10 | V10: 2.9524407e+10 | W10: 1.3570154e+11 | X10: 2.395294e+10 | Y10: 9.2640994e+10 | Z10: 0.21134006 | AA10: 0.318697 | AB10: 0.33340755 | AC10: 554263.3
A11: 2010 | B11: rama_industrial | C11: C | D11: 6.6 | E11: 1.42332 | F11: 1.4175182 | G11: 2.0980152e+11 | H11: 6.7141678e+10 | I11: 2.1660995e+11 | J11: 5.5561292e+10 | K11: 5.7294536e+09 | L11: 2.4078598e+10 | M11: 7.0074061e+10 | N11: 7.0074061e+10 | O11: 7.4342587e+09 | P11: 4.5859447e+09 | Q11: 1.8498724e+09 | R11: 1.2808011e+09 | S11: 3.1306735e+09 | T11: 112274.19 | U11: 2.5753241e+10 | V11: 3.7333627e+10 | W11: 1.4265984e+11 | X11: 2.5263399e+10 | Y11: 9.5337461e+10 | Z11: 0.27012719 | AA11: 0.39159452 | AB11: 0.30996581 | AC11: 598015.24
A12: 2011 | B12: rama_industrial | C12: C | D12: 6.6 | E12: 1.5515565 | F12: 1.5322466 | G12: 2.0799766e+11 | H12: 6.2973274e+10 | I12: 2.1250217e+11 | J12: 5.2111841e+10 | K12: 5.2752264e+09 | L12: 2.4957313e+10 | N12: 7.8727492e+10 | T12: 109399.62 | U12: 2.1879302e+10 | V12: 3.2740735e+10 | W12: 1.4502438e+11 | X12: 2.5754803e+10 | Y12: 1.0448229e+11 | Z12: 0.20940679 | AA12: 0.31336156 | AB12: 0.29634179 | AC12: 575626.06
A13: 2012 | B13: rama_industrial | C13: C | D13: 6.6 | E13: 1.6843317 | F13: 1.6563376 | G13: 2.1759103e+11 | H13: 5.8950487e+10 | I13: 2.2608609e+11 | J13: 4.8782892e+10 | K13: 5.4624876e+09 | L13: 2.6436563e+10 | M13: 7.0099152e+10 | N13: 7.0099152e+10 | O13: 1.0178891e+10 | P13: 7.0458927e+09 | Q13: 3.5469181e+09 | R13: 1.8717296e+09 | S13: 5.4186477e+09 | T13: 110138.75 | U13: 1.6883841e+10 | V13: 2.7051436e+10 | W13: 1.5864055e+11 | X13: 2.8041986e+10 | Y13: 9.8141138e+10 | Z13: 0.17203632 | AA13: 0.27563809 | AB13: 0.26074353 | AC13: 535238.39
A14: 2013 | B14: rama_industrial | C14: C | D14: 6.6 | E14: 1.8216676 | F14: 1.7983936 | G14: 2.1600845e+11 | H14: 6.1425057e+10 | I14: 2.4507135e+11 | J14: 5.0830656e+10 | K14: 5.2888116e+09 | L14: 2.7906393e+10 | M14: 7.1529663e+10 | N14: 7.1529663e+10 | O14: 1.580457e+10 | P14: 1.0043355e+10 | Q14: 1.3612761e+09 | R14: 8.9471932e+09 | S14: 1.0308469e+10 | T14: 109797.75 | U14: 1.7635451e+10 | V14: 2.8229853e+10 | W14: 1.5458339e+11 | X14: 2.7649967e+10 | Y14: 9.917963e+10 | Z14: 0.17781324 | AA14: 0.28463357 | AB14: 0.25064153 | AC14: 559438.22
A15: 2014 | B15: rama_industrial | C15: C | D15: 6.6 | E15: 1.9923987 | F15: 1.9580343 | G15: 2.2768581e+11 | H15: 6.5639537e+10 | I15: 2.6366301e+11 | J15: 5.4318236e+10 | K15: 6.1410006e+09 | L15: 2.9027911e+10 | M15: 9.9593226e+10 | N15: 9.9593226e+10 | O15: 3.9237442e+10 | P15: 2.6406338e+10 | Q15: 1.1127888e+09 | R15: 2.4163793e+10 | S15: 2.5276582e+10 | T15: 107700.43 | U15: 1.9149324e+10 | V15: 3.0470626e+10 | W15: 1.6204627e+11 | X15: 2.8950634e+10 | Y15: 1.2854386e+11 | Z15: 0.14897113 | AA15: 0.23704458 | AB15: 0.24895239 | AC15: 609464.04
A16: 2015 | B16: rama_industrial | C16: C | D16: 6.6 | E16: 2.172039 | F16: 2.1277031 | G16: 2.2011343e+11 | H16: 6.9952553e+10 | I16: 2.7955646e+11 | J16: 5.7887356e+10 | K16: 6.9007052e+09 | L16: 2.8718233e+10 | M16: 9.5676824e+10 | N16: 9.5676824e+10 | O16: 1.2341709e+10 | P16: 7.5555276e+09 | Q16: 6.4145291e+08 | R16: 2.8925541e+09 | S16: 3.534007e+09 | T16: 103791.21 | U16: 2.2268418e+10 | V16: 3.4333615e+10 | W16: 1.5016088e+11 | X16: 2.7102896e+10 | Y16: 1.2277972e+11 | Z16: 0.18136886 | AA16: 0.27963588 | AB16: 0.25022692 | AC16: 673973.78
A17: 2016 | B17: rama_industrial | C17: C | D17: 6.6 | E17: 2.3315859 | F17: 2.3328264 | G17: 2.0942091e+11 | H17: 6.6642553e+10 | I17: 2.7949935e+11 | J17: 5.5148254e+10 | K17: 6.9248624e+09 | L17: 2.8229294e+10 | M17: 9.3852212e+10 | N17: 9.3852212e+10 | O17: 7.4667511e+09 | P17: 3.4128709e+09 | Q17: 7.2685024e+08 | R17: 1.8484868e+09 | S17: 2.5753371e+09 | T17: 100240.45 | U17: 1.9994098e+10 | V17: 3.1488397e+10 | W17: 1.4277836e+11 | X17: 2.5910251e+10 | Y17: 1.1976246e+11 | Z17: 0.16694795 | AA17: 0.26292376 | AB17: 0.23843545 | AC17: 664826.98
A18: 2017 | B18: rama_industrial | C18: C | D18: 6.6 | E18: 2.4413194 | F18: 2.4779241 | G18: 1.9831143e+11 | H18: 6.7350702e+10 | I18: 2.9447177e+11 | J18: 5.5734264e+10 | K18: 6.520522e+09 | L18: 2.8485529e+10 | M18: 8.5926119e+10 | N18: 8.5926119e+10 | O18: 6.9782922e+09 | P18: 3.4739566e+09 | Q18: 7.0711904e+08 | R18: 1.1867159e+09 | S18: 1.893835e+09 | T18: 97466.997 | U18: 2.0728213e+10 | V18: 3.2344651e+10 | W18: 1.3096072e+11 | X18: 2.4158523e+10 | Y18: 1.1008464e+11 | Z18: 0.18829341 | AA18: 0.2938162 | AB18: 0.22871701 | AC18: 691010.33
A19: 2018 | B19: rama_industrial | C19: C | D19: 6.6 | E19: 2.5769357 | F19: 2.6663657 | G19: 2.2120725e+11 | H19: 7.6790946e+10 | I19: 3.065352e+11 | J19: 6.4996082e+10 | K19: 6.3851558e+09 | L19: 2.8548479e+10 | M19: 8.9619874e+10 | N19: 8.9619874e+10 | O19: 8.305944e+09 | P19: 3.6472626e+09 | Q19: 9.0972434e+08 | R19: 1.5039547e+09 | S19: 2.413679e+09 | T19: 94566.086 | U19: 3.0062447e+10 | V19: 4.1857311e+10 | W19: 1.444163e+11 | X19: 2.6206785e+10 | Y19: 1.1582666e+11 | Z19: 0.25954687 | AA19: 0.3613789 | AB19: 0.25051265 | AC19: 812034.73
A20: 2019 | B20: rama_industrial | C20: C | D20: 6.6 | E20: 2.774533 | F20: 2.8765268 | G20: 2.1684782e+11 | H20: 6.8758428e+10 | I20: 2.9710055e+11 | J20: 5.7065843e+10 | K20: 6.6571098e+09 | L20: 2.8158775e+10 | M20: 9.3366402e+10 | N20: 9.3366402e+10 | O20: 1.1086207e+10 | P20: 3.8142915e+09 | Q20: 3.8619429e+09 | R20: 1.411848e+09 | S20: 5.2737909e+09 | T20: 90481 | U20: 2.2249958e+10 | V20: 3.3942543e+10 | W20: 1.4808939e+11 | X20: 2.6704268e+10 | Y20: 1.2007067e+11 | Z20: 0.18530719 | AA20: 0.28268805 | AB20: 0.2314315 | AC20: 759921.18
A21: 2020 | B21: rama_industrial | C21: C | D21: 6.6 | E21: 3.0720571 | F21: 3.1471888 | G21: 1.9557499e+11 | H21: 5.9557198e+10 | I21: 2.7288754e+11 | J21: 4.9283163e+10 | K21: 6.4287626e+09 | L21: 2.4872425e+10 | M21: 9.6457388e+10 | N21: 9.6457388e+10 | O21: 1.3327083e+10 | P21: 3.1928134e+09 | Q21: 1.0662071e+09 | R21: 8.81934e+08 | S21: 1.9481411e+09 | T21: 84764.465 | U21: 1.7981976e+10 | V21: 2.825601e+10 | W21: 1.3601779e+11 | X21: 2.4377305e+10 | Y21: 1.2083469e+11 | Z21: 0.14881468 | AA21: 0.23384021 | AB21: 0.21824814 | AC21: 702619.88
A22: 2021 | B22: rama_industrial | C22: C | D22: 6.6 | E22: 3.4122569 | F22: 3.3976997 | G22: 2.1699755e+11 | H22: 6.5931342e+10 | I22: 2.9779492e+11 | J22: 6.2727489e+10 | K22: 6.3709545e+09 | L22: 2.4758544e+10 | M22: 1.1054091e+11 | N22: 1.1054091e+11 | O22: 2.4600429e+10 | P22: 5.4588223e+09 | Q22: 9.7072565e+08 | R22: 1.7594772e+09 | S22: 2.7302029e+09 | T22: 86333.094 | U22: 3.1597991e+10 | V22: 3.4801844e+10 | W22: 1.5106621e+11 | X22: 2.6640114e+10 | Y22: 1.3718102e+11 | Z22: 0.23033791 | AA22: 0.25369284 | AB22: 0.22139848 | AC22: 763685.62
A23: 2022 | B23: rama_industrial | C23: C | D23: 6.6 | E23: 3.6166177 | F23: 3.7001093 | G23: 2.4538068e+11 | H23: 7.3421101e+10 | I23: 2.9933483e+11 | J23: 6.2298329e+10 | K23: 5.9512627e+09 | L23: 2.5839754e+10 | M23: 1.0855543e+11 | N23: 1.0855543e+11 | O23: 1.926856e+10 | P23: 4.7677005e+09 | Q23: 1.1448755e+09 | R23: 1.4323826e+09 | S23: 2.5772581e+09 | T23: 89467.506 | U23: 3.0507313e+10 | V23: 4.1630084e+10 | W23: 1.7195958e+11 | X23: 2.9969596e+10 | Y23: 1.3852502e+11 | Z23: 0.22022961 | AA23: 0.30052393 | AB23: 0.24528084 | AC23: 820645.44
A24: 2023 | B24: rama_industrial | C24: C | D24: 6.6 | E24: 3.7632011 | F24: 3.8887886 | G24: 2.15134e+11 | H24: 6.3809281e+10 | I24: 3.0393241e+11 | J24: 5.2731349e+10 | K24: 6.5593953e+09 | L24: 2.6902928e+10 | M24: 1.0694693e+11 | N24: 1.0694693e+11 | O24: 1.5002597e+10 | P24: 1.0280651e+10 | Q24: 8.1006881e+08 | R24: 1.3261702e+09 | S24: 2.136239e+09 | T24: 89501.941 | U24: 1.9269026e+10 | V24: 3.0346958e+10 | W24: 1.5132472e+11 | X24: 2.7004189e+10 | Y24: 1.3395111e+11 | Z24: 0.14385118 | AA24: 0.22655248 | AB24: 0.20994563 | AC24: 712937.4
A25: 2024 | B25: rama_industrial | C25: C | D25: 6.6 | E25: 3.9207675 | F25: 4.102324 | G25: 2.1885297e+11 | H25: 6.7326186e+10 | I25: 3.2061145e+11 | J25: 5.5754573e+10 | K25: 7.0179522e+09 | L25: 2.7526901e+10 | M25: 1.1144909e+11 | N25: 1.1144909e+11 | O25: 1.1171552e+10 | P25: 5.7210264e+09 | Q25: 5.6450718e+08 | R25: 1.5789672e+09 | S25: 2.1434744e+09 | T25: 90863.927 | U25: 2.120972e+10 | V25: 3.2781334e+10 | W25: 1.5152678e+11 | X25: 2.7129346e+10 | Y25: 1.3857843e+11 | Z25: 0.1530521 | AA25: 0.23655437 | AB25: 0.20999308 | AC25: 740956.16

Sheet resultados-total-var-pct
A1: anno | B1: ambito | C1: seccion | D1: vbp_pp_var_pct | E1: vab_pp_var_pct | F1: vab_pb_estimado_var_pct | G1: consumo_capital_fijo_var_pct | H1: costo_laboral_var_pct | I1: stock_capital_var_pct | J1: stock_capital_imputado_var_pct | K1: fbcf_var_pct | L1: fbkf_maq_eq_var_pct | M1: adquisiciones_importadas_var_pct | N1: adquisiciones_origen_importado_var_pct | O1: importaciones_maquinaria_var_pct | P1: puestos_trabajo_var_pct | Q1: ganancia_pb_var_pct | R1: ganancia_pp_var_pct | S1: consumo_intermedio_var_pct | T1: capital_circulante_adelantado_var_pct | U1: capital_total_adelantado_var_pct | V1: tasa_ganancia_pb_var_pct | W1: tasa_ganancia_pp_var_pct | X1: productividad_trabajo_var_pct
A2: 2001 | B2: economia_total | C2: economia_total
A3: 2002 | B3: economia_total | C3: economia_total | D3: -9.8211866 | E3: -10.877501 | F3: -11.467086 | G3: 4.6320855 | H3: -23.551662 | J3: -11.956809 | P3: -36.876745 | Q3: 1.659316 | R3: 0.7888273 | S3: -8.879228 | T3: -13.362458 | U3: -12.304748 | V3: 15.923398 | W3: 14.930769 | X3: 41.188061
A4: 2003 | B4: economia_total | C4: economia_total | D4: 6.2783168 | E4: -5.2165698 | F4: -5.0271092 | G4: 18.273224 | H4: -12.569918 | J4: -9.9603691 | P4: 1.5358959 | Q4: -3.1275835 | R4: -3.8460992 | S4: 16.303989 | T4: 8.519029 | U4: -5.4413467 | V4: 2.4469079 | W4: 1.6870455 | X4: -6.6503237
A5: 2004 | B5: economia_total | C5: economia_total | D5: 10.006404 | E5: 6.1046386 | F5: 5.4820087 | G5: 2.3535276 | H5: -1.1363133 | I5: 32.040894 | J5: 32.040894 | K5: 27.406895 | L5: 5.2920021 | M5: -62.625732 | P5: 0.90377413 | Q5: 12.933853 | R5: 13.037839 | S5: 12.779773 | T5: 9.7568792 | U5: 25.786939 | V5: -10.218141 | W5: -10.135472 | X5: 5.1542814
A6: 2005 | B6: economia_total | C6: economia_total | D6: 7.3836353 | E6: 10.138726 | F6: 10.575231 | G6: -0.93455277 | H6: 12.88039 | I6: 26.757516 | J6: 26.757516 | K6: 5.7349741 | L6: -44.046909 | M6: 58.526317 | N6: 4.4506428 | O6: 25.271454 | P6: 12.385923 | Q6: 12.015289 | R6: 10.926776 | S6: 5.5412282 | T6: 6.9772377 | U6: 21.913675 | V6: -8.1191762 | W6: -9.0120312 | X6: -1.9995363
A7: 2006 | B7: economia_total | C7: economia_total | D7: -14.70775 | E7: -19.010155 | F7: -19.384467 | G7: -7.1076741 | H7: -21.545361 | I7: -9.0337953 | J7: -9.0337953 | K7: -19.420529 | L7: 51.31304 | M7: -19.88445 | N7: -30.946021 | O7: -25.556356 | P7: -47.39173 | Q7: -20.740308 | R7: -19.803738 | S7: -11.705279 | T7: -13.736872 | U7: -10.044393 | V7: -11.890215 | W7: -10.849067 | X7: 53.948884
A8: 2007 | B8: economia_total | C8: economia_total | D8: 30.761618 | E8: 37.043316 | F8: 37.660343 | G8: 17.206779 | H8: 48.351971 | I8: 15.167005 | J8: 15.167005 | K8: 85.448247 | L8: 57.688222 | M8: 14.446847 | N8: 67.851392 | O8: 39.847888 | P8: 86.66296 | Q8: 34.852078 | R8: 34.096547 | S8: 26.740558 | T8: 30.798582 | U8: 18.388045 | V8: 13.906837 | W8: 13.268655 | X8: -26.58248
A9: 2008 | B9: economia_total | C9: economia_total | D9: 7.5294149 | E9: -3.2001878 | F9: -3.912304 | G9: 6.5975742 | H9: 14.97138 | I9: 5.7296862 | J9: 5.7296862 | K9: 3.1757007 | L9: 43.526916 | M9: 106.17345 | N9: 26.73515 | O9: 60.823976 | P9: 13.52791 | Q9: -24.339164 | R9: -19.673565 | S9: 14.956004 | T9: 14.959278 | U9: 7.8309042 | V9: -29.833811 | W9: -25.507038 | X9: -14.734788
A10: 2009 | B10: economia_total | C10: economia_total | D10: -4.969414 | E10: 5.774719 | F10: 7.0101237 | G10: -2.0075988 | H10: 16.098452 | I10: -3.5880529 | J10: -3.5880529 | K10: -19.651178 | L10: -25.593368 | M10: -0.33763185 | N10: -46.816722 | O10: -21.247257 | P10: 9.3979251 | Q10: -2.500371 | R10: -3.5216587 | S10: -11.231514 | T10: -5.4103945 | U10: -4.0303552 | V10: 1.5942376 | W10: 0.53005976 | X10: -3.3119514
A11: 2010 | B11: economia_total | C11: economia_total | D11: 18.115575 | E11: 25.242392 | F11: 25.688538 | G11: 13.50992 | H11: 15.793648 | I11: 23.58463 | J11: 23.58463 | K11: 55.272471 | L11: 54.900929 | M11: -7.9666288 | N11: 233.33147 | O11: 65.341466 | P11: 9.3875216 | Q11: 46.99389 | R11: 41.57299 | S11: 13.166007 | T11: 13.852944 | U11: 21.256608 | V11: 21.225468 | W11: 16.754865 | X11: 14.494222
A12: 2011 | B12: economia_total | C12: economia_total | D12: -0.23834053 | E12: -1.8963929 | F12: -1.7717531 | G12: -9.0927855 | H12: 10.597804 | J12: -4.958752 | P12: 3.8628503 | Q12: -16.100413 | R12: -13.983733 | S12: 1.036058 | T12: 3.5783657 | U12: -3.0411918 | V12: -13.468834 | W12: -11.285763 | X12: -5.5450464
A13: 2012 | B13: economia_total | C13: economia_total | D13: 8.5008256 | E13: 6.3923691 | F13: 6.5245099 | G13: 2.7062328 | H13: 9.3064117 | J13: -2.9325077 | P13: 4.1267779 | Q13: 2.8490587 | R13: 3.1883238 | S13: 10.074374 | T13: 9.8563483 | U13: 0.13616972 | V13: 2.7091999 | W13: 3.0480036 | X13: 2.1758007
A14: 2013 | B14: economia_total | C14: economia_total | D14: 4.7639135 | E14: 8.3973572 | F14: 8.6893257 | G14: -2.5687708 | H14: 8.0252853 | I14: 4.0759025 | J14: 4.0759025 | K14: 25.595582 | L14: 22.778691 | M14: -20.788735 | N14: 131.93602 | O14: 37.720773 | P14: 4.8607086 | Q14: 13.473155 | R14: 11.751521 | S14: 2.1429663 | T14: 3.804608 | U14: 4.0044867 | V14: 9.1040963 | W14: 7.44875 | X14: 3.372711
A15: 2014 | B15: economia_total | C15: economia_total | D15: 6.4987072 | E15: 7.5862228 | F15: 7.633398 | G15: 9.5124111 | H15: 7.6360996 | I15: 12.063369 | J15: 12.063369 | K15: 52.232654 | L15: 82.701121 | M15: 8.6206945 | N15: 116.49612 | O15: 78.22054 | P15: 4.1465763 | Q15: 7.1204477 | R15: 7.0857793 | S15: 5.6662047 | T15: 6.2452875 | U15: 10.534754 | V15: -3.0888987 | W15: -3.120263 | X15: 3.3026976
A16: 2015 | B16: economia_total | C16: economia_total | D16: 2.3991258 | E16: 6.0279428 | F16: 6.0629533 | G16: 10.505792 | H16: 4.1963947 | I16: -0.18178107 | J16: -0.18178107 | K16: -39.381164 | L16: -49.145855 | M16: -31.406041 | N16: -75.882633 | O16: -66.264615 | P16: 0.34377173 | Q16: 8.1632033 | R16: 7.6939156 | S16: -0.42924078 | T16: 0.94834069 | U16: 0.10361917 | V16: 8.0512415 | W16: 7.5824396 | X16: 5.6646974
A17: 2016 | B17: economia_total | C17: economia_total | D17: -2.4040203 | E17: -0.020429384 | F17: 0.18212474 | G17: -4.2918602 | H17: 0.62878349 | I17: 2.0114022 | J17: 2.0114022 | K17: -7.9410679 | L17: -21.68985 | M17: -27.460072 | N17: -6.8988927 | O17: -15.939598 | P17: -0.72633067 | Q17: 0.6785607 | R17: 0.054860075 | S17: -4.3823144 | T17: -2.8419188 | U17: 0.77540488 | V17: -0.096099027 | W17: -0.71500066 | X17: 0.71106597
A18: 2017 | B18: economia_total | C18: economia_total | D18: 1.3129822 | E18: 5.35687 | F18: 5.5760753 | G18: 4.8435055 | H18: 3.3175135 | I18: -0.23578446 | J18: -0.23578446 | K18: -12.217117 | L18: -13.104288 | M18: 1.0807125 | N18: -6.2128764 | O18: -3.4454173 | P18: 0.86936481 | Q18: 9.6507943 | R18: 8.3781904 | S18: -2.1964049 | T18: -0.44089606 | U18: -0.28614532 | V18: 9.9654553 | W18: 8.6891994 | X18: 4.4488286
A19: 2018 | B19: economia_total | C19: economia_total | D19: 5.6112239 | E19: 4.0966349 | F19: 4.7423415 | G19: -2.2360795 | H19: 1.9714218 | I19: 1.0793578 | J19: 1.0793578 | K19: -3.2190791 | L19: 4.5014498 | M19: 15.832498 | N19: -16.770954 | O19: -3.8200842 | P19: 0.043156318 | Q19: 11.01697 | R19: 8.3500463 | S19: 7.0271319 | T19: 5.3567421 | U19: 2.12795 | V19: 8.703807 | W19: 6.0924519 | X19: 4.05173
A20: 2019 | B20: economia_total | C20: economia_total | D20: 0.25942486 | E20: -3.0778357 | F20: -3.2906192 | G20: 2.7201253 | H20: 0.080275726 | I20: 2.9759395 | J20: 2.9759395 | K20: 22.603068 | L20: -15.802874 | M20: 21.694258 | N20: 0.38033604 | O20: 10.576686 | P20: -1.3153973 | Q20: -9.6588869 | R20: -8.2446801 | S20: 3.2938271 | T20: 2.2661965 | U20: 2.7964466 | V20: -12.116502 | W20: -10.740767 | X20: -1.7859304
A21: 2020 | B21: economia_total | C21: economia_total | D21: -8.9488631 | E21: -8.1497717 | F21: -8.6112963 | G21: -4.762508 | H21: -10.702733 | I21: -5.4265003 | J21: -5.4265003 | K21: -18.036136 | L21: -8.9737046 | M21: -39.19217 | N21: -20.531718 | O21: -30.356209 | P21: -6.8127675 | Q21: -6.1577409 | R21: -5.3265529 | S21: -9.6306179 | T21: -9.9661312 | U21: -6.5686437 | V21: 0.43979109 | W21: 1.3294154 | X21: -1.4347504
A22: 2021 | B22: economia_total | C22: economia_total | D22: 8.4121404 | E22: 9.1273432 | F22: 14.508246 | G22: -8.3182975 | H22: -2.2963359 | I22: 1.2892347 | J22: 1.2892347 | K22: 44.180322 | L22: 31.061848 | M22: 58.350904 | N22: 50.922354 | O22: 54.337183 | P22: 5.739225 | Q22: 46.788101 | R22: 27.979737 | S22: 7.7919572 | T22: 4.6607044 | U22: 2.1066309 | V22: 43.759617 | W22: 25.3393 | X22: 3.2042208
A23: 2022 | B23: economia_total | C23: economia_total | D23: 5.9927733 | E23: 0.51710606 | F23: -2.1658121 | G23: -4.7728623 | H23: 1.9929866 | I23: -3.0558361 | J23: -3.0558361 | K23: -7.810469 | L23: 10.074229 | M23: -14.05262 | N23: -12.671819 | O23: -13.323066 | P23: 3.9985777 | Q23: -6.0772781 | R23: -0.13490274 | S23: 10.799783 | T23: 8.2479889 | U23: -0.24672782 | V23: -5.8449714 | W23: 0.11210166 | X23: -3.3476147
A24: 2023 | B24: economia_total | C24: economia_total | D24: -0.86551796 | E24: 1.5359306 | F24: 1.5707469 | G24: 10.653607 | H24: 11.558049 | I24: 2.4084995 | J24: 2.4084995 | K24: -0.32024329 | L24: 25.142504 | M24: -17.494431 | N24: 25.965192 | O24: 5.6402176 | P24: 5.9065889 | Q24: -11.238239 | R24: -10.109691 | S24: -2.7780656 | T24: 1.1358331 | U24: 2.0652971 | V24: -13.034338 | W24: -11.928626 | X24: -4.1268994
A25: 2024 | B25: economia_total | C25: economia_total | D25: 3.7811079 | E25: 5.4877458 | F25: 5.5858214 | G25: 3.7666622 | H25: 4.0864913 | I25: 4.2511933 | J25: 4.2511933 | K25: -15.345996 | L25: -15.417952 | M25: -2.1557003 | N25: -12.939491 | O25: -9.0006408 | P25: 2.4823205 | Q25: 8.0941548 | R25: 7.588787 | S25: 2.3616063 | T25: 2.8810448 | U25: 3.8850675 | V25: 4.0516769 | W25: 3.5652087 | X25: 2.9326281

Sheet resultados-industrial-var-pct
A1: anno | B1: ambito | C1: seccion | D1: vbp_pp_var_pct | E1: vab_pp_var_pct | F1: vab_pp_total_var_pct | G1: vab_pb_estimado_var_pct | H1: consumo_capital_fijo_var_pct | I1: costo_laboral_var_pct | J1: stock_capital_var_pct | K1: stock_capital_imputado_var_pct | L1: fbcf_var_pct | M1: fbkf_maq_eq_var_pct | N1: adquisiciones_importadas_var_pct | O1: adquisiciones_origen_importado_var_pct | P1: importaciones_maquinaria_var_pct | Q1: puestos_trabajo_var_pct | R1: ganancia_pb_var_pct | S1: ganancia_pp_var_pct | T1: consumo_intermedio_var_pct | U1: capital_circulante_adelantado_var_pct | V1: capital_total_adelantado_var_pct | W1: tasa_ganancia_pb_var_pct | X1: tasa_ganancia_pp_var_pct | Y1: vab_pp_participacion_total_var_pct | Z1: productividad_trabajo_var_pct
A2: 2001 | B2: rama_industrial | C2: C
A3: 2002 | B3: rama_industrial | C3: C | D3: 4.4138506 | E3: 9.1748607 | F3: -10.877501 | G3: 9.1748607 | H3: 6.7148744 | I3: -27.881927 | K3: 18.162972 | Q3: -32.720947 | R3: 50.660595 | S3: 36.897671 | T3: 1.7482166 | U3: -3.4776418 | V3: 12.345072 | W3: 34.105211 | X3: 21.85463 | Y3: 22.499774 | Z3: 62.271696
A4: 2003 | B4: rama_industrial | C4: C | D4: 13.947766 | E4: -9.5836329 | F4: -5.2165698 | G4: -9.5836329 | H4: 7.6345737 | I4: -3.2687337 | K4: 8.369755 | Q4: 8.8553706 | R4: -16.338787 | S4: -14.551585 | T4: 28.084367 | U4: 23.952745 | V4: 11.969083 | W4: -25.281863 | X4: -23.685706 | Y4: -4.607412 | Z4: -16.938993
A5: 2004 | B5: rama_industrial | C5: C | D5: 16.671375 | E5: 15.167991 | F5: 6.1046386 | G5: 15.167991 | H5: -1.0418388 | I5: 2.2261665 | J5: -4.6047465 | K5: -4.6047465 | L5: -15.804436 | M5: -48.456638 | N5: -72.359488 | Q5: 6.3546715 | R5: 27.204598 | S5: 23.834942 | T5: 17.308931 | U5: 15.757859 | V5: 0.60194684 | W5: 26.443476 | X5: 23.093981 | Y5: 8.5418998 | Z5: 8.2867249
A6: 2005 | B6: rama_industrial | C6: C | D6: 2.5737745 | E6: 1.9140212 | F6: 10.138726 | G6: 1.9140212 | H6: -2.1936439 | I6: 14.987469 | J6: 3.0473731 | K6: 3.0473731 | L6: 0.38082169 | M6: -13.496839 | N6: 31.384959 | O6: 20.319844 | P6: 25.615083 | Q6: 15.522317 | R6: -3.6689131 | S6: -2.2153541 | T6: 2.8484567 | U6: 3.9508733 | V6: 3.3132012 | W6: -6.7582015 | X6: -5.3512575 | Y6: -7.4675863 | Z6: -11.779798
A7: 2006 | B7: rama_industrial | C7: C | D7: -6.0427229 | E7: -6.0878698 | F7: -19.010155 | G7: -6.0878698 | H7: -21.003952 | I7: -10.082613 | J7: 2.4046138 | K7: 2.4046138 | L7: -5.3756672 | M7: 44.454851 | N7: -3.1716981 | O7: -36.612324 | P7: -19.874157 | Q7: -37.578014 | R7: -0.73577359 | S7: -2.1880769 | T7: -6.0240972 | U7: -6.4318077 | V7: -0.21128835 | W7: -0.52559576 | X7: -1.9809741 | Y7: 15.955439 | Z7: 50.4472
A8: 2007 | B8: rama_industrial | C8: C | D8: 16.263671 | E8: 19.553522 | F8: 37.043316 | G8: 19.553522 | H8: 27.416841 | I8: 32.140114 | J8: 41.100573 | K8: 41.100573 | L8: 143.47539 | M8: 28.724624 | N8: -14.159512 | O8: 64.107808 | P8: 16.766128 | Q8: 57.324913 | R8: 11.623875 | S8: 13.689812 | T8: 14.907338 | U8: 16.570963 | V8: 34.291585 | W8: -16.879472 | X8: -15.341075 | Y8: -12.762237 | Z8: -24.008525
A9: 2008 | B9: rama_industrial | C9: C | D9: 12.079069 | E9: 5.1892276 | F9: -3.2001878 | G9: 5.1892276 | H9: 26.320309 | I9: 12.725866 | J9: 13.21054 | K9: 13.21054 | L9: -6.98157 | M9: 58.480188 | N9: 65.044382 | O9: 35.445218 | P9: 48.607099 | Q9: 3.3076213 | R9: -3.4173138 | S9: -1.0593736 | T9: 15.034454 | U9: 14.781821 | V9: 13.589146 | W9: -14.971906 | X9: -12.896056 | Y9: 8.6667682 | Z9: 1.8213626
A10: 2009 | B10: rama_industrial | C10: C | D10: -14.566008 | E10: -9.5685173 | F10: 5.774719 | G10: -9.5685173 | H10: -10.573471 | I10: 14.3681 | J10: -19.894224 | K10: -19.894224 | L10: -57.641013 | M10: -47.183793 | N10: -38.657869 | O10: -63.386046 | P10: -51.173906 | Q10: 0.12893024 | R10: -26.836693 | S10: -21.806934 | T10: -16.526208 | U10: -13.205937 | V10: -18.265736 | W10: -10.48637 | X10: -4.3325749 | Y10: -14.50558 | Z10: -9.6849607
A11: 2010 | B11: rama_industrial | C11: C | D11: 8.5001209 | E11: 16.436654 | F11: 25.242392 | G11: 16.436654 | H11: -0.38207205 | I11: 7.5520262 | J11: 2.0178286 | K11: 2.0178286 | L11: 26.696131 | M11: 7.2489997 | N11: 3.8891692 | O11: 17.583776 | P11: 9.0869615 | Q11: 7.9179273 | R11: 31.536672 | S11: 26.450048 | T11: 5.1276473 | U11: 5.4709762 | V11: 2.9106627 | W11: 27.816368 | X11: 22.873612 | Y11: -7.0309561 | Z11: 7.8937089
A12: 2011 | B12: rama_industrial | C12: C | D12: -0.85979296 | E12: -6.2083713 | F12: -1.8963929 | G12: -6.2083713 | H12: -7.9279326 | I12: 3.6493605 | K12: 12.348979 | Q12: -2.5603131 | R12: -15.04253 | S12: -12.302293 | T12: 1.6574714 | U12: 1.9451189 | V12: 9.592068 | W12: -22.47845 | X12: -19.978053 | Y12: -4.3953311 | Z12: -3.7439141
A13: 2012 | B13: rama_industrial | C13: C | D13: 4.6122516 | E13: -6.3880861 | F13: 6.3923691 | G13: -6.3880861 | H13: 3.5498234 | I13: 5.9271231 | K13: -10.959755 | Q13: 0.67562067 | R13: -22.831904 | S13: -17.376821 | T13: 9.3888778 | U13: 8.8806108 | V13: -6.069121 | W13: -17.84587 | X13: -12.03832 | Y13: -12.012568 | Z13: -7.0163032
A14: 2013 | B14: rama_industrial | C14: C | D14: -0.72732197 | E14: 4.1977103 | F14: 8.3973572 | G14: 4.1977103 | H14: -3.1794302 | I14: 5.5598367 | J14: 2.0406975 | K14: 2.0406975 | L14: 55.268099 | M14: 42.541976 | N14: -61.620875 | O14: 378.0174 | P14: 90.240628 | Q14: -0.30960922 | R14: 4.451657 | S14: 4.3562082 | T14: -2.5574534 | U14: -1.3979731 | V14: 1.058162 | W14: 3.3579623 | X14: 3.2635129 | Y14: -3.8743075 | Z14: 4.5213179
A15: 2014 | B15: rama_industrial | C15: C | D15: 5.4059753 | E15: 6.8611738 | F15: 7.5862228 | G15: 6.8611738 | H15: 16.113052 | I15: 4.0188573 | J15: 39.233461 | K15: 39.233461 | L15: 148.26643 | M15: 162.92349 | N15: -18.253996 | O15: 170.07121 | P15: 145.20209 | Q15: -1.9101693 | R15: 8.5842577 | S15: 7.9376003 | T15: 4.8277395 | U15: 4.704045 | V15: 29.607117 | W15: -16.220451 | X15: -16.719388 | Y15: -0.6739236 | Z15: 8.9421533
A16: 2015 | B16: rama_industrial | C16: C | D16: -3.3257997 | E16: 6.5707588 | F16: 6.0279428 | G16: 6.5707588 | H16: 12.371023 | I16: -1.0668286 | J16: -3.9323975 | K16: -3.9323975 | L16: -68.546093 | M16: -71.387447 | N16: -42.356278 | O16: -88.029387 | P16: -86.018652 | Q16: -3.6297145 | R16: 16.28827 | S16: 12.677748 | T16: -7.3345652 | U16: -6.3823733 | V16: -4.4841808 | W16: 21.747655 | X16: 17.96763 | Y16: 0.51195561 | Z16: 10.584666
A17: 2016 | B17: rama_industrial | C17: C | D17: -4.8577321 | E17: -4.7317789 | F17: -0.020429384 | G17: -4.7317789 | H17: 0.3500688 | I17: -1.7025395 | J17: -1.9070572 | K17: -1.9070572 | L17: -39.499859 | M17: -54.829482 | N17: 13.313109 | O17: -36.094995 | P17: -27.126996 | Q17: -3.4210626 | R17: -10.213207 | S17: -8.286975 | T17: -4.9164076 | U17: -4.4004356 | V17: -2.4574557 | W17: -7.9511474 | X17: -5.9763863 | Y17: -4.7123122 | Z17: -1.3571451
A18: 2017 | B18: rama_industrial | C18: C | D18: -5.3048605 | E18: 1.0626072 | F18: 5.35687 | G18: 1.0626072 | H18: -5.8389671 | I18: 0.90769169 | J18: -8.4452923 | K18: -8.4452923 | L18: -6.5417854 | M18: 1.7898611 | N18: -2.7146167 | O18: -35.800682 | P18: -26.462636 | Q18: -2.7667968 | R18: 3.6716576 | S18: 2.7192685 | T18: -8.2769097 | U18: -6.7607506 | V18: -8.0808467 | W18: 12.785697 | X18: 11.749581 | Y18: -4.075921 | Z18: 3.9383708
A19: 2018 | B19: rama_industrial | C19: C | D19: 11.545386 | E19: 14.016549 | F19: 4.0966349 | G19: 16.617818 | H19: -2.076002 | I19: 0.22099012 | J19: 4.2987574 | K19: 4.2987574 | L19: 19.025454 | M19: 4.9887217 | N19: 28.652219 | O19: 26.732492 | P19: 27.449278 | Q19: -2.9763014 | R19: 45.031545 | S19: 29.410304 | T19: 10.274512 | U19: 8.4784214 | V19: 5.2160017 | W19: 37.841718 | X19: 22.994889 | Y19: 9.5295245 | Z19: 17.514124
A20: 2019 | B20: rama_industrial | C20: C | D20: -1.9707434 | E20: -10.460241 | F20: -3.0778357 | G20: -12.201103 | H20: 4.2591592 | I20: -1.3650599 | J20: 4.1804653 | K20: 4.1804653 | L20: 33.473178 | M20: 4.5795684 | N20: 324.51793 | O20: -6.1242993 | P20: 118.49595 | Q20: -4.319821 | R20: -25.987535 | S20: -18.908926 | T20: 2.5434045 | U20: 1.8982979 | V20: 3.6641052 | W20: -28.603575 | X20: -21.775166 | Y20: -7.6168389 | Z20: -6.4176508
A21: 2020 | B21: rama_industrial | C21: C | D21: -9.8100273 | E21: -13.381967 | F21: -8.1497717 | G21: -13.63807 | H21: -3.430124 | I21: -11.670787 | J21: 3.3105977 | K21: 3.3105977 | L21: 20.213186 | M21: -16.293408 | N21: -72.391952 | O21: -37.53336 | P21: -63.059949 | Q21: -6.31794 | R21: -19.181978 | S21: -16.753407 | T21: -8.1515629 | U21: -8.7138215 | V21: 0.63631169 | W21: -19.692981 | X21: -17.279766 | Y21: -5.6964427 | Z21: -7.540427
A22: 2021 | B22: rama_industrial | C22: C | D22: 10.953631 | E22: 10.70256 | F22: 9.1273432 | G22: 27.279754 | H22: -0.89921056 | I22: -0.45785788 | J22: 14.600771 | K22: 14.600771 | L22: 84.589746 | M22: 70.972169 | N22: -8.9552409 | O22: 99.502143 | P22: 40.144004 | Q22: 1.8505746 | R22: 75.720345 | S22: 23.166162 | T22: 11.063566 | U22: 9.2824404 | V22: 13.527846 | W22: 54.781713 | X22: 8.4898259 | Y22: 1.4434666 | Z22: 8.6911492
A23: 2022 | B23: rama_industrial | C23: C | D23: 13.079931 | E23: 11.359936 | F23: 0.51710606 | G23: -0.68416556 | H23: -6.5875821 | I23: 4.3670166 | J23: -1.7961512 | K23: -1.7961512 | L23: -21.673886 | M23: -12.66064 | N23: 17.940172 | O23: -18.590447 | P23: -5.6019585 | Q23: 3.6306028 | R23: -3.4517314 | S23: 19.620342 | T23: 13.830606 | U23: 12.498002 | V23: 0.97972748 | W23: -4.3884638 | X23: 18.459759 | Y23: 10.78705 | Z23: 7.4585435
A24: 2023 | B24: rama_industrial | C24: C | D24: -12.326433 | E24: -13.091359 | F24: 1.5359306 | G24: -15.35672 | H24: 10.218548 | I24: 4.1144913 | J24: -1.4817336 | K24: -1.4817336 | L24: -22.139502 | M24: 115.63122 | N24: -29.243939 | O24: -7.4150822 | P24: -17.111947 | Q24: 0.038489175 | R24: -36.838011 | S24: -27.1033 | T24: -11.999835 | U24: -9.8947203 | V24: -3.3018655 | W24: -34.681274 | X24: -24.614161 | Y24: -14.406023 | Z24: -13.124796
A25: 2024 | B25: rama_industrial | C25: C | D25: 1.7286759 | E25: 5.5115884 | F25: 5.4877458 | G25: 5.7332563 | H25: 6.9908414 | I25: 2.3193467 | J25: 4.2097144 | K25: 4.2097144 | L25: -25.535878 | M25: -44.351514 | N25: -30.313675 | O25: 19.062184 | P25: 0.33869687 | Q25: 1.5217388 | R25: 10.071575 | S25: 8.0218119 | T25: 0.13353052 | U25: 0.46347292 | V25: 3.4544821 | W25: 6.3961389 | X25: 4.4148206 | Y25: 0.022602311 | Z25: 3.9300446

Sheet resultados-total-ind-2005
A1: anno | B1: ambito | C1: seccion | D1: vbp_pp_ind_2005 | E1: vab_pp_ind_2005 | F1: vab_pb_estimado_ind_2005 | G1: consumo_capital_fijo_ind_2005 | H1: costo_laboral_ind_2005 | I1: stock_capital_ind_2005 | J1: stock_capital_imputado_ind_2005 | K1: fbcf_ind_2005 | L1: fbkf_maq_eq_ind_2005 | M1: adquisiciones_importadas_ind_2005 | N1: adquisiciones_origen_importado_ind_2005 | O1: importaciones_maquinaria_ind_2005 | P1: puestos_trabajo_ind_2005 | Q1: ganancia_pb_ind_2005 | R1: ganancia_pp_ind_2005 | S1: consumo_intermedio_ind_2005 | T1: capital_circulante_adelantado_ind_2005 | U1: capital_total_adelantado_ind_2005 | V1: tasa_ganancia_pb_ind_2005 | W1: tasa_ganancia_pp_ind_2005 | X1: productividad_trabajo_ind_2005
A2: 2001 | B2: economia_total | C2: economia_total | D2: 0.88327258 | E2: 1.0129915 | F2: 1.0196693 | G2: 0.7969364 | H2: 1.3406511 | J2: 0.75368235 | P2: 1.3758519 | Q2: 0.80269625 | R2: 0.82292539 | S2: 0.79274706 | T2: 0.90586786 | U2: 0.786384 | V2: 1.0207434 | W2: 1.0464676 | X2: 0.73626494
A3: 2002 | B3: economia_total | C3: economia_total | D3: 0.79652473 | E3: 0.90280335 | F3: 0.90274293 | G3: 0.83385118 | H3: 1.0249055 | J3: 0.66356599 | P3: 0.86848249 | Q3: 0.81601552 | R3: 0.82941685 | S3: 0.72235724 | T3: 0.78482164 | U3: 0.68962143 | V3: 1.1832804 | W3: 1.2027133 | X3: 1.0395182
A4: 2003 | B4: economia_total | C4: economia_total | D4: 0.84653307 | E4: 0.85570798 | F4: 0.85736106 | G4: 0.98622267 | H4: 0.89607569 | I4: 0.59747237 | J4: 0.59747237 | K4: 0.74231529 | L4: 1.6973857 | M4: 1.6878193 | P4: 0.88182148 | Q4: 0.79049396 | R4: 0.79751665 | S4: 0.84013028 | T4: 0.85168083 | U4: 0.65209674 | V4: 1.2122342 | W4: 1.2230036 | X4: 0.97038687
A5: 2004 | B5: economia_total | C5: economia_total | D5: 0.93124059 | E5: 0.90794586 | F5: 0.90436166 | G5: 1.0094337 | H5: 0.88589346 | I5: 0.78890786 | J5: 0.78890786 | K5: 0.94576086 | L5: 1.7872113 | M5: 0.63081009 | N5: 0.95738999 | O5: 0.79826646 | P5: 0.88979115 | Q5: 0.89273528 | R5: 0.90149559 | S5: 0.94749703 | T5: 0.9347783 | U5: 0.82025253 | V5: 1.0883664 | W5: 1.0990464 | X5: 1.0204033
A6: 2005 | B6: economia_total | C6: economia_total | D6: 1 | E6: 1 | F6: 1 | G6: 1 | H6: 1 | I6: 1 | J6: 1 | K6: 1 | L6: 1 | M6: 1 | N6: 1 | O6: 1 | P6: 1 | Q6: 1 | R6: 1 | S6: 1 | T6: 1 | U6: 1 | V6: 1 | W6: 1 | X6: 1
A7: 2006 | B7: economia_total | C7: economia_total | D7: 0.8529225 | E7: 0.80989845 | F7: 0.80615533 | G7: 0.92892326 | H7: 0.78454639 | I7: 0.90966205 | J7: 0.90966205 | K7: 0.80579471 | L7: 1.5131304 | M7: 0.8011555 | N7: 0.69053979 | O7: 0.74443644 | P7: 0.5260827 | Q7: 0.79259692 | R7: 0.80196262 | S7: 0.88294721 | T7: 0.86263128 | U7: 0.89955607 | V7: 0.88109785 | W7: 0.89150933 | X7: 1.5394888
A8: 2007 | B8: economia_total | C8: economia_total | D8: 1.1152953 | E8: 1.1099117 | F8: 1.1097562 | G8: 1.088761 | H8: 1.16389 | I8: 1.0476305 | J8: 1.0476305 | K8: 1.4943322 | L8: 2.3860284 | M8: 0.9168972 | N8: 1.1590807 | O8: 1.0410786 | P8: 0.98200155 | Q8: 1.0688334 | R8: 1.0754042 | S8: 1.1190522 | T8: 1.1283095 | U8: 1.0649668 | V8: 1.0036307 | W8: 1.0098006 | X8: 1.1302545
A9: 2008 | B9: economia_total | C9: economia_total | D9: 1.1992705 | E9: 1.0743924 | F9: 1.0663392 | G9: 1.1605928 | H9: 1.3381404 | I9: 1.1076565 | J9: 1.1076565 | K9: 1.5417877 | L9: 3.424593 | M9: 1.8903986 | N9: 1.4689626 | O9: 1.6743041 | P9: 1.1148458 | Q9: 0.8086883 | R9: 0.86383384 | S9: 1.2864177 | T9: 1.2970964 | U9: 1.1483634 | V9: 0.70420941 | W9: 0.7522304 | X9: 0.96371391
A10: 2009 | B10: economia_total | C10: economia_total | D10: 1.1396737 | E10: 1.1364356 | F10: 1.1410908 | G10: 1.1372928 | H10: 1.5535603 | I10: 1.0679132 | J10: 1.0679132 | K10: 1.2388082 | L10: 2.5481243 | M10: 1.8840161 | N10: 0.78124247 | O10: 1.3185604 | P10: 1.2196182 | Q10: 0.78846809 | R10: 0.83341256 | S10: 1.1419335 | T10: 1.2269184 | U10: 1.1020803 | V10: 0.71543618 | W10: 0.75621767 | X10: 0.93179617
A11: 2010 | B11: economia_total | C11: economia_total | D11: 1.3461322 | E11: 1.4232991 | F11: 1.4342204 | G11: 1.2909401 | H11: 1.7989242 | I11: 1.3197765 | J11: 1.3197765 | K11: 1.9235282 | L11: 3.9470682 | M11: 1.7339235 | N11: 2.604127 | O11: 2.1801271 | P11: 1.3341101 | Q11: 1.1589999 | R11: 1.1798871 | S11: 1.2922806 | T11: 1.3968827 | U11: 1.3363451 | V11: 0.86729086 | W11: 0.88292092 | X11: 1.0668528
A12: 2011 | B12: economia_total | C12: economia_total | D12: 1.3429238 | E12: 1.3963078 | F12: 1.4088096 | G12: 1.1735577 | H12: 1.9895707 | J12: 1.2543321 | P12: 1.3856448 | Q12: 0.97239614 | R12: 1.0148948 | S12: 1.3056694 | T12: 1.4468683 | U12: 1.2957043 | V12: 0.75047689 | W12: 0.78327656 | X12: 1.0076953
A13: 2012 | B13: economia_total | C13: economia_total | D13: 1.4570834 | E13: 1.4855649 | F13: 1.5007275 | G13: 1.2053169 | H13: 2.1747283 | J13: 1.2175487 | P13: 1.4428273 | Q13: 1.0001003 | R13: 1.047253 | S13: 1.4372074 | T13: 1.5894767 | U13: 1.2974687 | V13: 0.77080881 | W13: 0.80715086 | X13: 1.0296207
A14: 2013 | B14: economia_total | C14: economia_total | D14: 1.5264976 | E14: 1.6103131 | F14: 1.6311306 | G14: 1.1743551 | H14: 2.3492564 | J14: 1.2671748 | P14: 1.5129589 | Q14: 1.1348453 | R14: 1.1703211 | S14: 1.4680063 | T14: 1.64995 | U14: 1.3494256 | V14: 0.84098398 | W14: 0.86727351 | X14: 1.0643469
A15: 2014 | B15: economia_total | C15: economia_total | D15: 1.6257002 | E15: 1.732475 | F15: 1.7556413 | G15: 1.2860646 | H15: 2.528648 | J15: 1.4200388 | P15: 1.5756949 | Q15: 1.2156514 | R15: 1.2532475 | S15: 1.5511865 | T15: 1.7529942 | U15: 1.4915843 | V15: 0.81500684 | W15: 0.84021229 | X15: 1.099499
A16: 2015 | B16: economia_total | C16: economia_total | D16: 1.6647028 | E16: 1.8369076 | F16: 1.862085 | G16: 1.4211759 | H16: 2.6347601 | J16: 1.4174574 | P16: 1.5811117 | Q16: 1.3148875 | R16: 1.3496713 | S16: 1.5445282 | T16: 1.7696185 | U16: 1.4931299 | V16: 0.88062501 | W16: 0.90392088 | X16: 1.1617823
A17: 2016 | B17: economia_total | C17: economia_total | D17: 1.624683 | E17: 1.8365324 | F17: 1.8654763 | G17: 1.360181 | H17: 2.651327 | J17: 1.4459682 | P17: 1.5696276 | Q17: 1.3238098 | R17: 1.3504117 | S17: 1.4768421 | T17: 1.7193274 | U17: 1.5047077 | V17: 0.87977873 | W17: 0.89745784 | X17: 1.1700434
A18: 2017 | B18: economia_total | C18: economia_total | D18: 1.6460148 | E18: 1.934913 | F18: 1.9694967 | G18: 1.4260614 | H18: 2.7392851 | J18: 1.4425588 | P18: 1.5832734 | Q18: 1.451568 | R18: 1.4635518 | S18: 1.4444047 | T18: 1.7117469 | U18: 1.500402 | V18: 0.96745269 | W18: 0.97543975 | X18: 1.2220966
A19: 2018 | B19: economia_total | C19: economia_total | D19: 1.7383764 | E19: 2.0141793 | F19: 2.0628969 | G19: 1.3941736 | H19: 2.793288 | J19: 1.4581292 | P19: 1.5839567 | Q19: 1.6114868 | R19: 1.585759 | S19: 1.5459049 | T19: 1.8034408 | U19: 1.5323298 | V19: 1.0516579 | W19: 1.0348679 | X19: 1.2716126
A20: 2019 | B20: economia_total | C20: economia_total | D20: 1.7428862 | E20: 1.9521862 | F20: 1.9950148 | G20: 1.4320968 | H20: 2.7955303 | J20: 1.5015222 | P20: 1.5631214 | Q20: 1.4558351 | R20: 1.4550183 | S20: 1.5968243 | T20: 1.8443103 | U20: 1.5751806 | V20: 0.92423375 | W20: 0.92371519 | X20: 1.2489025
A21: 2020 | B21: economia_total | C21: economia_total | D21: 1.5869177 | E21: 1.7930875 | F21: 1.8232182 | G21: 1.3638931 | H21: 2.4963322 | J21: 1.4200421 | P21: 1.4566295 | Q21: 1.3661885 | R21: 1.3775159 | S21: 1.4430403 | T21: 1.6605039 | U21: 1.4717126 | V21: 0.92829845 | W21: 0.9359952 | X21: 1.2309839
A22: 2021 | B22: economia_total | C22: economia_total | D22: 1.7204114 | E22: 1.9567487 | F22: 2.0877352 | G22: 1.2504404 | H22: 2.439008 | J22: 1.4383498 | P22: 1.5402288 | Q22: 2.0054022 | R22: 1.7629413 | S22: 1.5554813 | T22: 1.7378951 | U22: 1.5027162 | V22: 1.3345183 | W22: 1.1731698 | X22: 1.2704273
A23: 2022 | B23: economia_total | C23: economia_total | D23: 1.8235118 | E23: 1.9668672 | F23: 2.0425188 | G23: 1.1907586 | H23: 2.4876171 | J23: 1.3943962 | P23: 1.601816 | Q23: 1.8835284 | R23: 1.760563 | S23: 1.7234699 | T23: 1.8812365 | U23: 1.4990085 | V23: 1.2565161 | W23: 1.174485 | X23: 1.2278983
... A25: 2024 | B25: economia_total | C25: economia_total | D25: 1.8760812 | E25: 2.1066714 | F25: 2.1904851 | G25: 1.3672476 | H25: 2.8885428 | J25: 1.4886864 | P25: 1.7385395 | Q25: 1.8071753 | R25: 1.7026738 | S25: 1.7151617 | T25: 1.9574191 | U25: 1.5894078 | V25: 1.1370117 | W25: 1.071263 | X25: 1.2117478

Sheet resultados-industrial-ind-2005
A1: anno | B1: ambito | C1: seccion | D1: vbp_pp_ind_2005 | E1: vab_pp_ind_2005 | F1: vab_pp_total_ind_2005 | G1: vab_pb_estimado_ind_2005 | H1: consumo_capital_fijo_ind_2005 | I1: costo_laboral_ind_2005 | J1: stock_capital_ind_2005 | K1: stock_capital_imputado_ind_2005 | L1: fbcf_ind_2005 | M1: fbkf_maq_eq_ind_2005 | N1: adquisiciones_importadas_ind_2005 | O1: adquisiciones_origen_importado_ind_2005 | P1: importaciones_maquinaria_ind_2005 | Q1: puestos_trabajo_ind_2005 | R1: ganancia_pb_ind_2005 | S1: ganancia_pp_ind_2005 | T1: consumo_intermedio_ind_2005 | U1: capital_circulante_adelantado_ind_2005 | V1: capital_total_adelantado_ind_2005 | W1: tasa_ganancia_pb_ind_2005 | X1: tasa_ganancia_pp_ind_2005 | Y1: vab_pp_participacion_total_ind_2005 | Z1: productividad_trabajo_ind_2005
A2: 2001 | B2: rama_industrial | C2: C | D2: 0.70232062 | E2: 0.86310687 | F2: 1.0129915 | G2: 0.86310687 | H2: 0.89950701 | I2: 1.2194849 | K2: 0.79441386 | Q2: 1.1113422 | R2: 0.64745098 | S2: 0.70596969 | T2: 0.63598696 | U2: 0.69460403 | V2: 0.76486652 | W2: 0.84648885 | X2: 0.92299724 | Y2: 0.85203762 | Z2: 0.77663466
A3: 2002 | B3: rama_industrial | C3: C | D3: 0.73332001 | E3: 0.94229572 | F3: 0.90280335 | G3: 0.94229572 | H3: 0.95990777 | I3: 0.879469 | K3: 0.93870302 | Q3: 0.74770051 | R3: 0.9754535 | S3: 0.96645606 | T3: 0.64710539 | U3: 0.67044819 | V3: 0.85928984 | W3: 1.1351857 | X3: 1.1247149 | Y3: 1.0437442 | Z3: 1.2602582
A4: 2003 | B4: rama_industrial | C4: C | D4: 0.83560176 | E4: 0.85198956 | F4: 0.85570798 | G4: 0.85198956 | H4: 1.0331926 | I4: 0.8507215 | J4: 1.0172702 | K4: 1.0172702 | L4: 1.1832051 | M4: 2.2428244 | N4: 2.753647 | Q4: 0.81391216 | R4: 0.81607623 | S4: 0.82582139 | T4: 0.82884085 | U4: 0.83103893 | V4: 0.96213895 | W4: 0.84818958 | X4: 0.85831822 | Y4: 0.99565457 | Z4: 1.0467832
A5: 2004 | B5: rama_industrial | C5: C | D5: 0.97490806 | E5: 0.98121926 | F5: 0.90794586 | G5: 0.98121926 | H5: 1.0224284 | I5: 0.86965998 | J5: 0.97042745 | K5: 0.97042745 | L5: 0.99620623 | M5: 1.1560271 | N5: 0.76112213 | O5: 0.8311181 | P5: 0.79608275 | Q5: 0.8656336 | R5: 1.0380865 | S5: 1.0226554 | T5: 0.97230433 | U5: 0.96199288 | V5: 0.96793051 | W5: 1.0724804 | X5: 1.0565381 | Y5: 1.0807024 | Z5: 1.1335272
A6: 2005 | B6: rama_industrial | C6: C | D6: 1 | E6: 1 | F6: 1 | G6: 1 | H6: 1 | I6: 1 | J6: 1 | K6: 1 | L6: 1 | M6: 1 | N6: 1 | O6: 1 | P6: 1 | Q6: 1 | R6: 1 | S6: 1 | T6: 1 | U6: 1 | V6: 1 | W6: 1 | X6: 1 | Y6: 1 | Z6: 1
A7: 2006 | B7: rama_industrial | C7: C | D7: 0.93957277 | E7: 0.9391213 | F7: 0.80989845 | G7: 0.9391213 | H7: 0.78996048 | I7: 0.89917387 | J7: 1.0240461 | K7: 1.0240461 | L7: 0.94624333 | M7: 1.4445485 | N7: 0.96828302 | O7: 0.63387676 | P7: 0.80125843 | Q7: 0.62421986 | R7: 0.99264226 | S7: 0.97811923 | T7: 0.93975903 | U7: 0.93568192 | V7: 0.99788712 | W7: 0.99474404 | X7: 0.98019026 | Y7: 1.1595544 | Z7: 1.504472
A8: 2007 | B8: rama_industrial | C8: C | D8: 1.0923818 | E8: 1.1227526 | F8: 1.1099117 | G8: 1.1227526 | H8: 1.0065427 | I8: 1.1881694 | J8: 1.444935 | K8: 1.444935 | L8: 2.3038696 | M8: 1.8594896 | N8: 0.83117887 | O8: 1.0402413 | P8: 0.93559844 | Q8: 0.98205335 | R8: 1.1080258 | S8: 1.1120219 | T8: 1.0798521 | U8: 1.0907334 | V8: 1.3400784 | W8: 0.8268365 | X8: 0.82981854 | Y8: 1.0115693 | Z8: 1.1432705
A9: 2008 | B9: rama_industrial | C9: C | D9: 1.2243314 | E9: 1.1810148 | F9: 1.0743924 | G9: 1.1810148 | H9: 1.2714678 | I9: 1.3393742 | J9: 1.6358187 | K9: 1.6358187 | L9: 2.1430233 | M9: 2.9469227 | N9: 1.371814 | O9: 1.408957 | P9: 1.3903657 | Q9: 1.014536 | R9: 1.070161 | S9: 1.1002415 | T9: 1.242202 | U9: 1.2519637 | V9: 1.5221836 | W9: 0.70304332 | X9: 0.72280468 | Y9: 1.0992397 | Z9: 1.1640936
A10: 2009 | B10: rama_industrial | C10: C | D10: 1.0459951 | E10: 1.0680092 | F10: 1.1364356 | G10: 1.0680092 | H10: 1.1370295 | I10: 1.5318169 | J10: 1.3103852 | K10: 1.3103852 | L10: 0.90776298 | M10: 1.5564528 | N10: 0.84149995 | O10: 0.51587488 | P10: 0.67886127 | Q10: 1.015844 | R10: 0.7829652 | S10: 0.86031252 | T10: 1.0369131 | U10: 1.0866301 | V10: 1.2441456 | W10: 0.6293196 | X10: 0.69148862 | Y10: 0.93978858 | Z10: 1.0513516
A11: 2010 | B11: rama_industrial | C11: C | D11: 1.134906 | E11: 1.2435542 | F11: 1.4232991 | G11: 1.2435542 | H11: 1.1326853 | I11: 1.6475001 | J11: 1.3368266 | K11: 1.3368266 | L11: 1.1501006 | M11: 1.66928 | N11: 0.87422731 | O11: 0.60658516 | P11: 0.74054913 | Q11: 1.0962778 | R11: 1.0298864 | S11: 1.0878656 | T11: 1.0900823 | U11: 1.1460794 | V11: 1.2803585 | W11: 0.80437345 | X11: 0.84965705 | Y11: 0.87371246 | Z11: 1.1343422
A12: 2011 | B12: rama_industrial | C12: C | D12: 1.1251482 | E12: 1.1663497 | F12: 1.3963078 | G12: 1.1663497 | H12: 1.0428867 | I12: 1.7076233 | K12: 1.501911 | Q12: 1.0682096 | R12: 0.8749654 | S12: 0.95403318 | T12: 1.1081501 | U12: 1.168372 | V12: 1.4031713 | W12: 0.62356277 | X12: 0.67991211 | Y12: 0.83530991 | Z12: 1.0918734
A13: 2012 | B13: rama_industrial | C13: C | D13: 1.1770428 | E13: 1.0918423 | F13: 1.4855649 | G13: 1.0918423 | H13: 1.0799074 | I13: 1.8088362 | K13: 1.3373052 | Q13: 1.0754267 | R13: 0.67519415 | S13: 0.78825255 | T13: 1.212193 | U13: 1.2721306 | V13: 1.3180112 | W13: 0.51228257 | X13: 0.59806211 | Y13: 0.73496774 | Z13: 1.0152642
A14: 2013 | B14: rama_industrial | C14: C | D14: 1.1684819 | E14: 1.1376747 | F14: 1.6103131 | G14: 1.1376747 | H14: 1.0455725 | I14: 1.9094046 | K14: 1.3645956 | Q14: 1.0720971 | R14: 0.70525147 | S14: 0.82259047 | T14: 1.1811917 | U14: 1.2543466 | V14: 1.3319579 | W14: 0.52948482 | X14: 0.61757995 | Y14: 0.70649283 | Z14: 1.0611676
A15: 2014 | B15: rama_industrial | C15: C | D15: 1.2316498 | E15: 1.2157325 | F15: 1.732475 | G15: 1.2157325 | H15: 1.2140461 | I15: 1.9861408 | K15: 1.8999737 | Q15: 1.0516182 | R15: 0.76579208 | S15: 0.88788441 | T15: 1.2382166 | U15: 1.3133516 | V15: 1.7263122 | W15: 0.4436 | X15: 0.51432436 | Y15: 0.70173161 | Z15: 1.1560588
A16: 2015 | B16: rama_industrial | C16: C | D16: 1.1906876 | E16: 1.2956153 | F16: 1.8369076 | G16: 1.2956153 | H16: 1.364236 | I16: 1.9649521 | K16: 1.8252591 | Q16: 1.0134475 | R16: 0.89052636 | S16: 1.0004482 | T16: 1.1473988 | U16: 1.2295286 | V16: 1.6489012 | W16: 0.54007259 | X16: 0.60673626 | Y16: 0.70532416 | Z16: 1.2784238
A17: 2016 | B17: rama_industrial | C17: C | D17: 1.1328472 | E17: 1.2343097 | F17: 1.8365324 | G17: 1.2343097 | H17: 1.3690118 | I17: 1.931498 | K17: 1.7904504 | Q17: 0.9787768 | R17: 0.79957506 | S17: 0.91754127 | T17: 1.090988 | U17: 1.175424 | V17: 1.6083802 | W17: 0.49713063 | X17: 0.57047536 | Y17: 0.67208709 | Z17: 1.2610737
A18: 2017 | B18: rama_industrial | C18: C | D18: 1.0727512 | E18: 1.2474255 | F18: 1.934913 | G18: 1.2474255 | H18: 1.2890757 | I18: 1.94903 | K18: 1.6392416 | Q18: 0.95169603 | R18: 0.82893272 | S18: 0.94249168 | T18: 1.0006879 | U18: 1.0959565 | V18: 1.4784095 | W18: 0.56069224 | X18: 0.63750382 | Y18: 0.64469335 | Z18: 1.3107395
A19: 2018 | B19: rama_industrial | C19: C | D19: 1.1966045 | E19: 1.4222716 | F19: 2.0141793 | G19: 1.4547205 | H19: 1.2623144 | I19: 1.9533372 | K19: 1.7097086 | Q19: 0.92337069 | R19: 1.2022139 | S19: 1.2196814 | T19: 1.1035037 | U19: 1.1888763 | V19: 1.5555233 | W19: 0.77286782 | X19: 0.78409711 | Y19: 0.70612956 | Z19: 1.540304
A20: 2019 | B20: rama_industrial | C20: C | D20: 1.1730225 | E20: 1.2734985 | F20: 1.9521862 | G20: 1.2772285 | H20: 1.3160784 | I20: 1.926673 | K20: 1.7811824 | Q20: 0.88348273 | R20: 0.88978816 | S20: 0.98905271 | T20: 1.1315702 | U20: 1.2114447 | V20: 1.6125193 | W20: 0.55179999 | X20: 0.61335866 | Y20: 0.65234481 | Z20: 1.4414527
A21: 2020 | B21: rama_industrial | C21: C | D21: 1.0579486 | E21: 1.1030794 | F21: 1.7930875 | G21: 1.1030392 | H21: 1.2709353 | I21: 1.7018151 | K21: 1.8401502 | Q21: 0.82766482 | R21: 0.71910919 | S21: 0.82335268 | T21: 1.0393296 | U21: 1.1058816 | V21: 1.62278 | W21: 0.44313413 | X21: 0.50737172 | Y21: 0.61518436 | Z21: 1.332761
A22: 2021 | B22: rama_industrial | C22: C | D22: 1.1738324 | E22: 1.2211371 | F22: 1.9567487 | G22: 1.4039456 | H22: 1.2595069 | I22: 1.6940232 | K22: 2.1088263 | Q22: 0.84298137 | R22: 1.2636212 | S22: 1.0140919 | T22: 1.1543165 | U22: 1.2085344 | V22: 1.8423072 | W22: 0.68589059 | X22: 0.5504467 | Y22: 0.62406434 | Z22: 1.4485932
A23: 2022 | B23: rama_industrial | C23: C | D23: 1.3273689 | E23: 1.3598575 | F23: 1.9668672 | G23: 1.3943403 | H23: 1.1765359 | I23: 1.7680015 | K23: 2.0709486 | Q23: 0.87358668 | R23: 1.2200043 | S23: 1.2130602 | T23: 1.3139655 | U23: 1.359577 | V23: 1.8603568 | W23: 0.65579053 | X23: 0.65205783 | Y23: 0.69138247 | Z23: 1.5566372
... A25: 2024 | B25: rama_industrial | C25: C | D25: 1.1838692 | E25: 1.2469715 | F25: 2.1066714 | G25: 1.2478801 | H25: 1.3874152 | I25: 1.883439 | K25: 2.1261519 | Q25: 0.88722174 | R25: 0.84818845 | S25: 0.9552162 | T25: 1.1578358 | U25: 1.2307285 | V25: 1.861074 | W25: 0.45575214 | X25: 0.51326073 | Y25: 0.59191551 | Z25: 1.405479
